Workbook
Name _1610914392: 'ICT Cost'!$B$3
Name _1663400178: 'ICT Cost'!$B$25
Name Backup: #REF!
Name ChaiData: #REF!
Name ChaiPOS: #REF!
Name email: #REF!
Name Excel_BuiltIn_Print_Area_5_1: #REF!
Name Excel_BuiltIn_Print_Area_6: #REF!
Name Factory: #REF!
Name Farmers: #REF!
Name finance: #REF!
Name Financials: #REF!
Name Fleet: #REF!
Name Infrastructure: #REF!
Name KTDARegions: #REF!
Name OLE_LINK1: 'ICT Cost'!#REF!
Name Services: #REF!

Sheet Infrastructure and Systems
B1: Regions 1-7
B2: Region 1 | M2: 45930
A3: No. | B3: Item | C3: KAMBAA | D3: KAGWE | E3: THETA | F3: NDARUGU | G3: GACHEGE | H3: MATAARA | I3: NGERE | J3: NJUNU | K3: MAKOS | L3: NDUTI | M3: IKUMBI | N3: GACHARAGE
A4: 1 | B4: Local Area Network (LAN) | C4: LAN Upgrade completed | D4: LAN Upgrade not done | E4: LAN Upgrade not done | F4: LAN Upgrade not done | G4: LAN Upgrade not done | H4: LAN Upgrade not done | I4: LAN Upgrade completed | J4: LAN Upgrade not done | K4: LAN Upgrade not done | L4: LAN Upgrade not done | M4: LAN Upgrade completed | N4: LAN Upgrade not done
A5: 2 | B5: Wide Area Network (WAN) | C5: on Last mile Fibre | D5: Microwave-Viable on last mile Fibre | E5: Microwave-Viable on last mile Fibre | F5: on Last mile Fibre | G5: Microwave-Viable on last mile Fibre | H5: Microwave-Viable on last mile Fibre | I5: on Microwave | J5: on Microwave | K5: Microwave-Viable on last mile Fibre | L5: on Microwave | M5: Microwave-Viable on last mile Fibre | N5: on Microwave
A6: 3 | B6: Safaricom Backup VPN Line Status | C6: ok | D6: ok | E6: ok | F6: ok | G6: ok | H6: ok | I6: ok | J6: ok | K6: ok | L6: ok | M6: ok | N6: ok
A7: 4 | B7: Firewall | C7: Sophos License Expired | D7: Sophos License Expired | E7: Sophos License Valid | F7: Sophos License Valid | G7: Sophos License Expired | H7: Sophos License Expired | I7: Sophos License Expired | J7: Sophos License Expired | K7: Sophos License Expired | L7: Sophos License Expired | M7: Sophos License Expired | N7: Sophos License Expired
A8: 5 | B8: E-Mail Server | C8: Lotus Domino | D8: Lotus Domino | E8: Lotus Domino | F8: Lotus Domino | G8: Lotus Domino | H8: Lotus Domino | I8: Lotus Domino | J8: Lotus Domino | K8: Lotus Domino | L8: Lotus Domino | M8: Lotus Domino | N8: Lotus Domino
A9: 6 | B9: Business Servers (EWS, Chaipro) | C9: Working | D9: Working | E9: Working | F9: Working | G9: Working | H9: Working | I9: Working | J9: Working | K9: Working | L9: Working | M9: Working | N9: Working
A10: 7 | B10: Electronic Weighment Solution (EWS Version) | C10: 1.0.52 | D10: 1.0.52 | E10: 1.0.52 | F10: 1.0.52 | G10: 1.0.52 | H10: 1.0.52 | I10: 1.0.52 | J10: 1.0.57 | K10: 1.0.52 | L10: 1.0.52 | M10: 1.0.52 | N10: 1.0.52
A11: 8 | B11: EWS Kits | C11: EWS Kits10+ 2 Spare Kits | D11: EWS Kits 9+ 2 Spare Kits | E11: EWS Kits 7+ 2 Spare Kits | F11: EWS Kits 7+ 1 Spare Kits | G11: EWS Kits 8+ 2 Spare Kits | H11: EWS Kits 8+ 2 Spare Kits | I11: EWS Kits15+ 1 Spare Kit | J11: EWS Kits 7+ 1 Spare Kit | K11: EWS Kits14+ 1 Spare Kits | L11: EWS Kits 6+ 1 Spare Kit | M11: EWS Kits10+ 2 Spare Kits | N11: EWS Kits 8+ 1 Spare Kit
A12: 9 | B12: Printer (NFC Card & DFX) | C12: Fully Operational | D12: Fully Operational | E12: Fully Operational | F12: Fully Operational | G12: Fully Operational | H12: Fully Operational | I12: Fully Operational | J12: Fully Operational | K12: Fully Operational | L12: Fully Operational | M12: Fully Operational | N12: Fully Operational
A13: 10 | B13: WeighBridge Status | C13: Fully Operational | D13: Fully Operational | E13: Fully Operational | F13: Fully Operational | G13: Fully Operational | H13: Weighbridge not Installed | I13: Fully Operational | J13: Fully Operational | K13: Fully Operational | L13: Fully Operational | M13: Fully Operational | N13: Fully Operational
A14: 11 | B14: CCTV | C14: NVR has issues of hanging and thus having issues with retrieving data. | D14: 30 CAMERAS WORKING OK.3 CAMERAS UNDER REPAIR. | E14: CCTV is not functional – Faulty NVR and 2 cameras | F14: OK- no of cameras-25 and 20working\ 5not working | G14: Fully Operational | H14: 17 CAMERA NOT WORKING DUE TO ONGOING CONTRUCTION DEMOLISION OF OLD STORE | I14: NOT ADEQUATE- Request sent via RICTM to KTDA security manager for CCTV Assessment for additional cameras and repair of faulty ones | J14: Request for upgrade done by KTDA security Manager and RICTM | K14: 32 cameras installed 29 working | L14: 32 cameras 28 working 4 faulty | M14: 41 CAMERAS IN OPERATION | N14: Operational, 5 Cameras not working. Needs an Upgrade
A15: 12 | B15: SAP Connection (PRD,PSM) | C15: WORKING OK | D15: WORKING OK | E15: WORKING OK | F15: WORKING OK | G15: WORKING OK | H15: WORKING OK | I15: WORKING OK | J15: WORKING OK | K15: WORKING OK | L15: WORKING OK | M15: WORKING OK | N15: WORKING OK
A16: 13 | B16: AFMS | C16: Not Installed | D16: Installed | E16: Not Installed | F16: Not Installed | G16: Not Installed | H16: Not Installed | I16: Not Installed | J16: Not Installed | K16: Not Installed | L16: Not Installed | M16: Not Installed | N16: Not Installed
A17: 14 | B17: Any other
B19: Region 2
A20: No. | B20: Item | C20: Ragati | D20: Gathuthi | E20: Gitugi | F20: Iriaini | G20: Chinga | H20: Kiru | I20: Gatunguru | J20: Kanyenyaini | K20: Githambo
A21: 1 | B21: Local Area Network (LAN) | C21: No Issue Reported | D21: No Issue Reported | E21: No Issue Reported | F21: No Issue Reported | G21: No Issue Reported | H21: No Issue Reported | I21: No Issue Reported | J21: No Issue Reported | K21: No Issue Reported
A22: 2 | B22: Wide Area Network (WAN) | C22: No Issue Reported | D22: No Issue Reported | E22: No Issue Reported | F22: No Issue Reported | G22: No Issue Reported | H22: No Issue Reported | I22: No Issue Reported | J22: No Issue Reported | K22: No Issue Reported
A23: 3 | B23: Safaricom Backup VPN Line Status | C23: No Issue Reported | D23: No Issue Reported | E23: No Issue Reported | F23: No Issue Reported | G23: No Issue Reported | H23: No Issue Reported | I23: No Issue Reported | J23: No Issue Reported | K23: No Issue Reported
A24: 4 | B24: Firewall | C24: Domino in Use | D24: Domino in Use | E24: Domino in Use | F24: Domino in Use | G24: Domino in Use | H24: Domino in Use | I24: Domino in Use | J24: Domino in Use | K24: Domino in Use
A25: 5 | B25: E-Mail Server | C25: No Issue Reported | D25: No Issue Reported | E25: No Issue Reported | F25: No Issue Reported | G25: No Issue Reported | H25: No Issue Reported | I25: No Issue Reported | J25: No Issue Reported | K25: No Issue Reported
A26: 6 | B26: Business Servers (EWS, Chaipro) | C26: No Issue Reported | D26: No Issue Reported | E26: No Issue Reported | F26: No Issue Reported | G26: No Issue Reported | H26: No Issue Reported | I26: No Issue Reported | J26: No Issue Reported | K26: No Issue Reported
A27: 7 | B27: Electronic Weighment Solution (EWS Version) | C27: No Issue Reported | D27: No Issue Reported | E27: No Issue Reported | F27: No Issue Reported | G27: No Issue Reported | H27: No Issue Reported | I27: No Issue Reported | J27: No Issue Reported | K27: No Issue Reported
A28: 8 | B28: EWS Kits | C28: No Issue Reported | D28: No Issue Reported | E28: No Issue Reported | F28: No Issue Reported | G28: No Issue Reported | H28: No Issue Reported | I28: No Issue Reported | J28: No Issue Reported | K28: No Issue Reported
A29: 9 | B29: Printer (NFC Card & DFX) | C29: No Issue Reported | D29: No Issue Reported | E29: No Issue Reported | F29: No Issue Reported | G29: No Issue Reported | H29: No Issue Reported | I29: No Issue Reported | J29: No Issue Reported | K29: No Issue Reported
A30: 10 | B30: WeighBridge Status | C30: No Issue Reported | D30: No Issue Reported | E30: No Issue Reported | F30: No Issue Reported | G30: No Issue Reported | H30: No Issue Reported | I30: No Issue Reported | J30: No Issue Reported | K30: No Issue Reported
A31: 11 | B31: CCTV | C31: No Issue Reported | D31: No Issue Reported | E31: No Issue Reported | F31: No Issue Reported | G31: No Issue Reported | H31: No Issue Reported | I31: No Issue Reported | J31: No Issue Reported | K31: No Issue Reported
A32: 12 | B32: SAP Connection (PRD,PSM) | C32: No Issue Reported | D32: No Issue Reported | E32: No Issue Reported | F32: No Issue Reported | G32: No Issue Reported | H32: No Issue Reported | I32: No Issue Reported | J32: No Issue Reported | K32: No Issue Reported
... A34: 14 | B34: Any other | C34: None | D34: None | E34: None | F34: None | G34: None | H34: None | I34: None | J34: None | K34: None
B36: Region 3
A37: No. | B37: Item | C37: Ndima | D37: Mununga | E37: Kangaita | F37: Kimunye | G37: Thumaita | H37: Kathangariri | I37: Mungania | J37: Rukuriri
A38: 1 | B38: Local Area Network (LAN) | C38: Working OK Cat5 | D38: Working OK Cat 6 | E38: Working OK Cat5 | F38: Working OK Cat6 | G38: Working OK Cat6 | H38: Working OK Cat5 | I38: Working OK Cat5
A39: 2 | B39: Wide Area Network (WAN) | C39: Working OK | D39: Working OK | E39: Working OK | F39: Working OK | G39: Working OK | H39: Working OK | I39: Working OK
A40: 3 | B40: Safaricom Backup VPN Line Status | C40: Working OK | D40: Working OK | E40: OK | F40: Ok | G40: OKAY | H40: Working well | I40: Working OK
A41: 4 | B41: Firewall | C41: NO FIREWALL | D41: Working OK | E41: OK | F41: Ok | G41: N/A | H41: NOT WORKING | I41: Working OK
A42: 5 | B42: E-Mail Server | C42: Working OK | D42: Working OK | E42: OK though space needs to be increased | F42: Ok | G42: OKAY | H42: Working well | I42: Working OK
A43: 6 | B43: Business Servers (EWS, Chaipro) | C43: Working OK | D43: Working OK | E43: OK | F43: Ok | G43: OKAY | H43: Working well | I43: Working OK
A44: 7 | B44: Electronic Weighment Solution (EWS Version) | C44: 1.0.52 | D44: 1.0.52 | E44: 1.0.57 | F44: Ok | G44: VER.58 | H44: VER. .58 | I44: AMITY ver .52
A45: 8 | B45: EWS Kits | C45: 9 | D45: 9 | E45: 10 | F45: 8 | G45: 11 | H45: 12 KITS | I45: 9
A46: 9 | B46: Printer (NFC Card & DFX) | C46: All OK | D46: All OK | E46: OK | F46: Ok | G46: OKAY | H46: OKAY | I46: All OK
A47: 10 | B47: WeighBridge Status | C47: Working OK (calibration done) | D47: Working OK (calibration done) | E47: Working OK (calibration done) | F47: Working OK (calibration done) | G47: OKAY | H47: Working OK (calibration done) | I47: Working OK (calibration done)
A48: 11 | B48: CCTV | C48: OKAY -NEEDS SERVICING | D48: OKAY -NEEDS SERVICING | E48: OKAY -NEEDS SERVICING | F48: OKAY -NEEDS SERVICING | G48: OKAY | H48: OKAY -NEEDS SERVICING | I48: OKAY -NEEDS SERVICING
A49: 12 | B49: SAP Connection (PRD,PSM) | C49: OK | D49: OK | E49: OK | F49: Ok | G49: OKAY | H49: STABLE | I49: OK
A50: 13 | B50: AFMS | C50: N/A | D50: N/A | E50: N/A | F50: N/A | G50: N/A | H50: N/A | I50: N/A
A51: 14 | B51: Any other | C51: None | D51: NONE | E51: NONE | F51: NONE | G51: NONE | H51: NONE | I51: NONE
B53: Region 4
A54: No. | B54: Item | C54: Kiegoi | D54: Michimikuru | E54: Githongo | F54: Imenti | G54: Kionyo | H54: Kinoro | I54: Igembe | J54: Weru
A55: 1 | B55: Local Area Network (LAN) | C55: ok | D55: OK | E55: ok | F55: ok | G55: ok | H55: ok | I55: ok | J55: ok
A56: 2 | B56: Wide Area Network (WAN) | C56: ok | D56: OK | E56: ok | F56: ok | G56: ok | H56: ok | I56: ok | J56: ok
A57: 3 | B57: Safaricom Backup VPN Line Status | C57: ok | D57: OK | E57: ok | F57: ok | G57: ok | H57: ok | I57: ok | J57: ok
A58: 4 | B58: Firewall | C58: not installed | D58: NOT INSTALLED | E58: License has expired | F58: installed | G58: installed | H58: installed | I58: not installed | J58: License has expired
A59: 5 | B59: E-Mail Server | C59: ok | D59: OK | E59: ok | F59: ok | G59: ok | H59: ok | I59: ok | J59: ok
A60: 6 | B60: Business Servers (EWS, Chaipro) | C60: ok | D60: OK | E60: ok | F60: ok | G60: ok | H60: ok | I60: ok | J60: ok
A61: 7 | B61: Electronic Weighment Solution (EWS Version) | C61: Amity V52 | D61: VIRTUAL CITY 3.1.5.6 | E61: ok | F61: VIRTUAL CITY 3.1.5.6 | G61: VIRTUAL CITY 3.1.5.6 | H61: VIRTUAL CITY 3.1.5.6 | I61: Amity V52 | J61: ok
A62: 8 | B62: EWS Kits | C62: 12 WORKING 2 FAULTY SCALES | D62: 13 WORKING 2 SCALE UNECONOMICAL | E62: 3 PDAS uneconomical to repair - boarded | F62: 12 | G62: 12 | H62: 12 | I62: 6 | J62: 15 WORKING 3 PDAS uneconomical to repair - boarded
A63: 9 | B63: Printer (NFC Card & DFX) | C63: ok | D63: DTC4500e, DFX9000 | E63: DTC4500e, DFX9000 | F63: DTC4500e, DFX9000 | G63: DTC4500e, DFX9000 | H63: DTC4500e, DFX9000 | I63: ok | J63: DTC4500e, DFX9000
A64: 10 | B64: WeighBridge Status | C64: ok | D64: OK | F64: ok | G64: ok | H64: ok | I64: ok
A65: 11 | B65: CCTV | C65: needs upgrading | D65: OK | E65: 25 cameras in use all are online | F65: 42 cameras FACTORY LINK DOWN | G65: working ok | H65: requires upgrading | I65: needs upgrading | J65: 27 cameras in use all are online
A66: 12 | B66: SAP Connection (PRD,PSM) | C66: ok | D66: OK | E66: ok | F66: 172.16.10.151 | G66: 172.16.10.151 | H66: 172.16.10.151 | I66: ok | J66: ok
A67: 13 | B67: AFMS | C67: ok | E67: ok | F67: 2.5.2.8 | G67: 2.5.2.8 | H67: 2.5.2.8 | I67: ok | J67: ok
A68: 14 | B68: Any other
B70: Region 5
A71: No. | B71: Item | C71: KAPKATET | D71: MOMUL | E71: TEGAT | F71: CHELAL | G71: TEBESONIK | H71: LITEIN | I71: TOROR | J71: KAPSET | K71: MOGOGOSIEK | L71: MOTIGO | M71: KOBEL | N71: KAPKOROS | O71: TRIGAGA | P71: ROROK | Q71: OLENGRUONE | R71: BOITO
A72: 1 | B72: Local Area Network (LAN) | C72: Okay | D72: WORKING | E72: OK | F72: Working | G72: Okay | H72: Working | I72: Fully functional | J72: okay | K72: OK | L72: WORKING | M72: Fully Functional | N72: Working | O72: OK | P72: okay | Q72: OK | R72: Fully Functional
A73: 2 | B73: Wide Area Network (WAN) | C73: Okay | D73: WORKING | E73: OK | F73: Working | G73: Okay | H73: Working | I73: Fully functional | J73: okay | K73: OK | L73: WORKING | M73: Fully Functional | N73: Working | O73: OK | P73: okay | Q73: OK | R73: Fully Functional
A74: 3 | B74: Safaricom Backup VPN Line status | C74: In place and active | D74: WORKING | E74: OK | F74: Working | G74: None | H74: Working | I74: Fully functional | J74: Not in place | K74: OK | L74: WORKING | M74: Fully Functional | N74: Working | O74: OK | P74: Not in place | Q74: OK | R74: Fully Functional
A75: 4 | B75: Firewall | C75: Not installed | D75: WORKING | E75: OK | F75: Working | G75: Not installed | H75: Unavailable | I75: Fully functional | J75: Okay | K75: OK | L75: N/A | M75: Fully Functional | N75: Working | O75: OK | P75: Okay | Q75: Not available, | R75: Fully Functional
A76: 5 | B76: E-Mail Server | C76: Okay | D76: WORKING | E76: OK | F76: Working | G76: Okay | H76: Working | I76: Fully functional (domino\Exchange) | J76: Okay | K76: OK | L76: WORKING | M76: Fully Functional | N76: Working | O76: OK | P76: Okay | Q76: OK | R76: Fully Functional
A77: 6 | B77: Business Servers (EWS, Chaipro) | C77: GMS In Use | D77: WORKING | E77: OK | F77: Working | G77: GMS In Use | H77: Working | I77: Fully functional | J77: Okay | K77: OK | L77: WORKING | M77: Fully Functional | N77: Working | O77: OK | P77: Okay | Q77: OK | R77: Fully Functional
A78: 7 | B78: Electronic Weighment Solution (EWS version) | C78: 3.1.5.6 | D78: WORKING | E78: OK | F78: 1.0.0.56 | G78: 3.1.5.6 | H78: 1.0.0.57 | I78: Fully functional | J78: 3.1.5.6 | K78: VER 52 | L78: WORKING | M78: Fully Functional | N78: Working | O78: OK | P78: 3.1.5.6 | Q78: OK | R78: Fully Functional
A79: 8 | B79: EWS Kits | C79: 13 | D79: WORKING | E79: OK | F79: 7 Operational 1 spare | G79: 9 | H79: 12 Operational 1 spare | I79: Fully functional | J79: Okay | K79: OK | L79: WORKING | M79: Fully Functional | N79: Working | O79: OK one spare scale | P79: Okay | Q79: OK | R79: Fully Functional
A80: 9 | B80: Printer (NFC Card & DFX) | C80: Both Okay | D80: WORKING | E80: ok | F80: NFC – Unavailable DFX – Working | G80: Both Okay | H80: NFC – Working DFX – Not Working | I80: Fully functional | J80: NFC card faulty ,in HQ, Dfx Okay | K80: OK | L80: WORKING | M80: Fully Functional | N80: Working DFX Faulty | O80: ok | P80: NFC card Printer not available, Dfx faulty sprocket, faulty Printer head, mechanism Jam | Q80: Not Available | R80: Fully Functional
A81: 10 | B81: Weighbridge | C81: Okay | D81: WORKING | E81: ok | F81: Unavailable | G81: Okay | H81: Working | I81: Fully functional | J81: Okay | K81: OK | L81: WORKING | M81: Fully Functional | N81: Working | O81: ok | P81: Okay | Q81: OK | R81: Fully Functional
A82: 11 | B82: CCTV | C82: 11 Cameras | D82: WORKING | E82: ok | F82: All Cameras Working except 1 | G82: 29 Cameras | H82: All Cameras Working | I82: Fully functional | J82: Okay,10 cameras not up | K82: OK | L82: WORKING | M82: Fully Functional | N82: Working | O82: ok | P82: Okay | Q82: OK. | R82: Fully Functional
A83: 12 | B83: SAP Connection (PRD, PSM) | C83: Okay | D83: WORKING | E83: ok | F83: Working | G83: Okay | H83: Working | I83: Fully functional | J83: Okay | K83: OK | L83: WORKING | M83: Fully Functional | N83: Working | O83: ok | P83: Okay | Q83: OK | R83: Fully Functional
A84: 13 | B84: AFMS | C84: Not installed | D84: Still waiting for the installation | E84: Not installed | F84: Unavailable | G84: Not installed | H84: Unavailable | I84: Not yet incorporated | J84: Not In place | K84: N/A | L84: N/A | M84: N/A | N84: N/A | O84: N/A | P84: Okay | Q84: OK | R84: N/A
A85: 14 | B85: Any other | C85: Website development underway | G85: Website development underway
B87: Region 6
A88: No. | B88: Item/Factory | C88: Gianchore | D88: Sanganyi | E88: Kebirigo | F88: Tombe | G88: Matunwa | H88: Nyansiongo | I88: Nyankoba | J88: Sombogo | K88: Kiamokama | L88: Mwamu | M88: Nyamache | N88: Itumbe | O88: Ogembo | P88: Eberege
A89: 1 | B89: Local Area Network (LAN) | C89: Working OK Cat5 | D89: Working OK Cat5 | E89: Working OK Cat5 | F89: Working OK Cat5 | G89: Working OK Cat6 | H89: Working OK Cat5 | I89: Working OK Cat5 | J89: Working OK Cat6 | K89: Working OK Cat5 | L89: Working OK Cat5 | M89: Working OK Cat5 | N89: Working OK Cat5 | O89: Working OK Cat5 | P89: Working OK Cat5
A90: 2 | B90: Wide Area Network (WAN) | C90: Working OK | D90: Working OK | E90: Working OK | F90: Working OK | G90: Working OK | H90: Working OK | I90: Working OK | J90: Working OK | K90: Working OK | L90: Working OK | M90: Working OK | N90: Working OK | O90: Working OK | P90: Working OK
A91: 3 | B91: Safaricom Backup VPN Line Status | C91: Working OK | D91: Working OK | E91: OK | F91: Ok | G91: OKAY | H91: Working well | I91: Working OK | J91: Ok | K91: Ok | L91: Ok | M91: OK | N91: Ok | O91: EWS VPN lines are not working | P91: EWS Lines are not working
A92: 4 | B92: Firewall | C92: Working OK | D92: Working OK | E92: OK | F92: Ok | G92: N/A | H92: NOT WORKING | I92: Working OK | J92: N/A | K92: Ok | L92: Ok | M92: OK | N92: Ok | O92: OK | P92: OK
A93: 5 | B93: E-Mail Server | C93: Working OK | D93: Working OK | E93: OK though space needs to be increased | F93: Ok | G93: OKAY | H93: Working well | I93: Working OK | J93: Ok | K93: Ok | L93: Ok | M93: OK | N93: Ok | O93: OK | P93: OK
A94: 6 | B94: Business Servers (EWS, Chaipro) | C94: Working OK | D94: Working OK | E94: OK | F94: Ok | G94: OKAY | H94: Working well | I94: Working OK | J94: Ok – Cisco Server | K94: Ok | L94: Ok | M94: OK | N94: Ok | O94: OK | P94: OK
A95: 7 | B95: Electronic Weighment Solution (EWS Version) | C95: 1.0.52 | D95: 1.0.52 | E95: 1.0.57 | F95: Ok | G95: VER.58 | H95: VER. .58 | I95: AMITY ver .52 | J95: Ok | K95: Ok | L95: Ok | M95: OK | N95: Ok Ver.52 | O95: OK | P95: OK
A96: 8 | B96: EWS Kits | C96: 9 | D96: 9 | E96: 10 | F96: 8 | G96: NONE | H96: 12 KITS | I96: 9 | J96: 5 | K96: 11 | L96: 7 | M96: OK | N96: Ok 12 kits | O96: 10 | P96: 7
A97: 9 | B97: Printer (NFC Card & DFX) | C97: All OK | D97: All OK | E97: OK | F97: Ok | G97: N/A | H97: OKAY | I97: All OK | J97: N/A | K97: Ok | L97: OK | M97: OK | N97: We don’t have NFC & DFX is Faulty | O97: OK | P97: OK
A98: 10 | B98: WeighBridge Status | C98: Working OK (calibration done) | D98: Working OK (calibration done) | E98: Working OK (calibration done) | F98: Working OK (calibration done) | G98: N/A | H98: Working OK (calibration done) | I98: Working OK (calibration done) | J98: OK | K98: Ok | L98: OK | M98: OK | N98: Ok | O98: OK | P98: OK
A99: 11 | B99: CCTV | C99: None | D99: OK, | E99: OK 8 cameras not working | F99: N/A | G99: N/A | H99: N/A | I99: 25 Working 6 Disconnected due to fac expansion. | J99: N/A | K99: n/a | L99: N/A | M99: OK | N99: Ok | O99: OK | P99: OK
A100: 12 | B100: SAP Connection (PRD,PSM) | C100: OK | D100: OK | E100: OK | F100: Ok | G100: OKAY | H100: STABLE | I100: OK | J100: OK | K100: Ok | L100: Ok | M100: OK | N100: Ok | O100: OK | P100: OK
A101: 13 | B101: AFMS | C101: N/A | D101: N/A | E101: N/A | F101: N/A | G101: N/A | H101: N/A | I101: N/A | J101: N/A | K101: n/a | L101: n/a | M101: OK | N101: N/A | O101: N/A | P101: N/A
A102: 14 | B102: Any other | C102: None | D102: NONE | E102: NONE | F102: NONE | G102: NONE | H102: NONE | I102: NONE | J102: N/A | K102: None | L102: None | M102: None | N102: None | O102: None | P102: None
B104: Region 7
A105: No. | B105: Item/Factory | C105: Chebut | D105: Kaptumo | E105: Mudete | F105: Kapsara
A106: 1 | B106: Local Area Network (LAN) | C106: Working | D106: Working | E106: Working | F106: Working
A107: 2 | B107: Wide Area Network (WAN) | C107: Working | D107: Working | E107: Working | F107: Working
...

Sheet Chaipro-SAP
B1: Region 1 | G1: ='Infrastructure and Systems'!M2 -> 45930
A2: No. | B2: Item | C2: KAMBAA | D2: KAGWE | E2: THETA | F2: NDARUGU | G2: GACHEGE | H2: MATAARA | I2: NGERE | J2: NJUNU | K2: MAKOS | L2: NDUTI | M2: IKUMBI | N2: GACHARAGE
A3: 1 | B3: Chaipro Financials | C3: SAP Module-FICO/MM | D3: SAP Module-FICO/MM | E3: SAP Module-FICO/MM | F3: SAP Module-FICO/MM | G3: SAP Module-FICO/MM | H3: SAP Module-FICO/MM | I3: SAP Module-FICO/MM | J3: SAP Module-FICO/MM | K3: SAP Module-FICO/MM | L3: SAP Module-FICO/MM | M3: SAP Module-FICO/MM | N3: SAP Module-FICO/MM
A4: 2 | B4: Chaipro Factory/TVAP | C4: SAP Module-PP/PM | D4: SAP Module-PP/PM | E4: SAP Module-PP/PM | F4: SAP Module-PP/PM | G4: SAP Module-PP/PM | H4: SAP Module-PP/PM | I4: SAP Module-PP/PM | J4: SAP Module-PP/PM | K4: SAP Module-PP/PM | L4: SAP Module-PP/PM | M4: SAP Module-PP/PM | N4: SAP Module-PP/PM
A5: 3 | B5: Chaipro Farmers | C5: 2.8.0.0 | D5: 2.8.0.0 | E5: 2.8.0.0 | F5: 2.8.0.0 | G5: 2.8.0.0 | H5: 2.8.0.0 | I5: 2.8.0.0 | J5: 2.8.0.0 | K5: 2.8.0.0 | L5: 2.8.0.0 | M5: 2.8.0.0 | N5: 2.8.0.0
A6: 4 | B6: Chaipro Fleet | C6: 3.2.5.1 | D6: 3.2.5.1 | E6: 3.2.5.1 | F6: 3.2.5.1 | G6: 3.2.5.1 | H6: 3.2.5.1 | I6: 3.2.5.1 | J6: 3.2.5.1 | K6: 3.2.5.1 | L6: 3.2.5.1 | M6: 3.2.5.1 | N6: 3.2.5.1
A7: 6 | B7: KTDA Replicator | C7: Version 10 fully operational | D7: Version 10 fully operational | E7: Version 10 fully operational | F7: Version 10 fully operational | G7: Version 10 fully operational | H7: Version 10 fully operational | I7: Version 10 fully operational | J7: Version 10 fully operational | K7: Version 10 fully operational | L7: Version 10 fully operational | M7: Version 10 fully operational | N7: Version 10 fully operational
A8: 7 | B8: Chai Data | C8: 1.0.0.3 | D8: 1.0.0.3 | E8: 1.0.0.3 | F8: 1.0.0.3 | G8: 1.0.0.3 | H8: 1.0.0.3 | I8: 1.0.0.3 | J8: 1.0.0.3 | K8: 1.0.0.3 | L8: 1.0.0.3 | M8: 1.0.0.3 | N8: 1.0.0.3
A9: 8 | B9: ETR Device | C9: OPERATIONAL | D9: OPERATIONAL | E9: OPERATIONAL | F9: OPERATIONAL | G9: OPERATIONAL | H9: OPERATIONAL | I9: OPERATIONAL | J9: OPERATIONAL | K9: OPERATIONAL | L9: OPERATIONAL | M9: OPERATIONAL | N9: OPERATIONAL
A10: 9 | B10: SMS Portal/USSD (Date growers received) | C10: 3rd October | D10: 3rd October | E10: 3rd October | F10: 3rd October | G10: 3rd October | H10: 3rd October | I10: 3rd October | J10: 3rd October | K10: 3rd October | L10: 3rd October | M10: 3rd October | N10: 3rd October
A11: 10 | B11: % NFC Card Usage | C11: 1 | D11: 1 | E11: 1 | F11: 1 | G11: 1 | H11: 1 | I11: 1 | J11: 1 | K11: 1 | L11: 1 | M11: 1 | N11: 1
B13: Region 2
A14: No. | B14: Item | C14: Ragati | D14: Gathuthi | E14: Gitugi | F14: Iriaini | G14: Chinga | H14: Kiru | I14: Gatunguru | J14: Kanyenyaini | K14: Githambo
A15: 1 | B15: Chaipro Financials | C15: 2.5.5.8 -fully utilized. | D15: 2.5.5.8 -fully utilized. | E15: 2.5.5.8 -fully utilized. | F15: 2.5.5.8 -fully utilized. | G15: 2.5.5.8 -fully utilized. | H15: 2.5.5.8 -fully utilized. | I15: 2.5.5.8-fully utilized. | J15: 2.5.5.8 -fully utilized. | K15: 2.5.5.8 -fully utilized.
A16: 2 | B16: Chaipro Factory/TVAP | C16: 2.5.2.7 - fully utilized. | D16: 2.5.2.7 - fully utilized. | E16: 2.5.2.7 - fully utilized. | F16: 2.5.2.7 - fully utilized. | G16: 2.5.2.7 - fully utilized. | H16: 2.5.2.7 - fully utilized. | I16: 2.5.2.7 - fully utilized. | J16: 2.5.2.7 - fully utilized. | K16: 2.5.2.7 - fully utilized.
A17: 3 | B17: Chaipro Farmers | C17: 2.8.0.0 - fully utilized. | D17: 2.8.0.0 - fully utilized. | E17: 2.8.0.0 - fully utilized. | F17: 2.8.0.0 - fully utilized. | G17: 2.8.0.0 - fully utilized. | H17: 2.8.0.0 - fully utilized. | I17: 2.8.0.0 - fully utilized. | J17: 2.8.0.0 - fully utilized. | K17: 2.8.0.0 - fully utilized.
A19: 4 | B19: Chaipro Fleet | C19: 3.2.5.1 - fully utilized. | D19: 3.2.5.1 - fully utilized. | E19: 3.2.5.1 - fully utilized. | F19: 3.2.5.1 - fully utilized. | G19: 3.2.5.1 - fully utilized. | H19: 3.2.5.1 - fully utilized. | I19: 3.2.5.1 - fully utilized. | J19: 3.2.5.1 - fully utilized. | K19: 3.2.5.1 - fully utilized.
A20: 6 | B20: KTDA Replicator | C20: Functional. | D20: Fully utilized. | E20: Fully utilized. | F20: Fully utilized. | G20: Fully utilized. | H20: Fully utilized. | I20: Fully utilized. | J20: Fully utilized. | K20: Fully utilized.
A21: 7 | B21: Chai Data | C21: 1.0.0.3 - fully utilized. | D21: 1.0.0.3 - fully utilized. | E21: 1.0.0.3 - fully utilized. | F21: 1.0.0.3 - fully utilized. | G21: 1.0.0.3 - fully utilized. | H21: 1.0.0.3 - fully utilized. | I21: 1.0.0.3 - fully utilized. | J21: 1.0.0.3 - fully utilized. | K21: 1.0.0.3 - fully utilized.
A22: 8 | B22: ETR Device
A23: 9 | B23: SMS Portal/USSD (Date growers received)
A24: 10 | B24: % NFC Card Usage
B26: Region 3
A27: No. | B27: Item | C27: NDIMA | D27: MUNUNGA | E27: KANGAITA | F27: Tombe | G27: KIMUNYE | H27: THUMAITA | I27: KATHANGARIRI | J27: MUNGANIA | K27: RUKURIRI
A28: 1 | B28: Chaipro Financials | C28: 2.5.5.9 | D28: 2.5.5.9 | E28: 2.5.5.9……not in use, we are On SAP | F28: 2.5.6.0 (Legacy) | G28: Okay - Ver. 2.5.5.9 | H28: Okay - Ver. 2.5.5.9 | I28: Partially Used | J28: 2.5.6.0 (Legacy) | K28: Fully on SAP
A29: 2 | B29: Chaipro Factory/ TVAP | C29: 2.5.2.7 | D29: 2.5.2.7 | E29: 2.5.2.7…… partially utilized | F29: 2.5.2.7 (Legacy) | G29: Okay - 2.5.2.7 | H29: Okay - 2.5.2.7 | I29: OK | J29: 2.5.2.7 (Legacy) | K29: Fully on SAP
A30: 3 | B30: Chaipro Farmers | C30: 3.0.0.1 | D30: 3.0.0.1 | E30: Fully utilized | F30: 3.0.0.1 (Fully Utilized) | G30: Okay - 3.0.0.1 | H30: Okay - 3.0.0.1 | I30: OK | J30: 3.0.0.1 (Fully Utilized) | K30: 3.0.0.1 - fully utilized.
A31: 4 | B31: Chaipro Fleet | C31: 3.2.5.1 | D31: 3.2.5.1 | E31: 3.2.5.1 partially utilized | F31: 3.2.1.1 (Legacy) | G31: Okay - 3.2.5.1 | H31: Okay - 3.2.5.1 | I31: Partially Used | J31: 3.2.1.1 (Legacy) | K31: 3.2.5.1 - Partly utilized.
A32: 6 | B32: KTDA Replicator | C32: 0.0.0.1 | D32: 0.0.0.1 | E32: Fully utilized | F32: 010 Fully Utilized | G32: Okay | H32: Okay | I32: OK | J32: 010 Fully Utilized | K32: fully utilized.
A33: 7 | B33: Chai Data | C33: ok | D33: replication software installed and working ok | E33: N/a | F33: 1.0.0.3 (Legacy) | G33: Okay | H33: Okay | I33: OK | J33: 1.0.0.3 (Legacy) | K33: Fully on SAP
A34: 8 | B34: ETR Device | C34: OK | D34: OK | E34: OK | F34: 2 pcs – Utilized 1 pc – under repair | G34: Okay | H34: Okay | I34: OK | J34: 2 pcs – Utilized 1 pc – under repair | K34: New TIMS ETR in use
A35: 9 | B35: SMS Portal/USSD (Date growers received) | C35: 3rd Oct | D35: 3rd Oct | E35: 2.10.2025 | F35: 2025-09-02 – Utilized | G35: 3rd Oct | H35: 3rd Oct | I35: OK | J35: 2025-09-02 – Utilized | K35: 3rd Oct
A36: 10 | B36: % NFC Card Usage | C36: 1 | D36: 1 | E36: 1 | F36: 1 | G36: 1 | H36: 1 | I36: 1 | J36: 0.9
B38: Region 4
A39: No. | B39: Item | C39: Kiegoi | D39: Michimikuru | E39: Githongo | F39: Imenti | G39: Kionyo | H39: Kinoro | I39: Igembe | J39: Weru
A40: 1 | B40: Chaipro Financials | C40: Ok 2.5.5.9 | D40: Ok 2.5.5.9 | E40: Ok 2.5.5.9 | F40: Ok 2.5.5.9 | G40: Ok 2.5.5.9 | H40: Ok 2.5.5.9 | I40: Ok 2.5.5.9 | J40: Ok 2.5.5.9
A41: 2 | B41: Chaipro Factory/ TVAP | C41: Ok 2.5.2.7 | D41: Ok 2.5.2.7 | E41: Ok 2.5.2.7 | F41: Ok 2.5.2.7 | G41: Ok 2.5.2.7 | H41: Ok 2.5.2.7 | I41: Ok 2.5.2.7 | J41: Ok 2.5.2.7
A42: 3 | B42: Chaipro Farmers | C42: Ok 3.0.0.1 | D42: Ok 3.0.0.1 | E42: Ok 3.0.0.1 | F42: Ok 3.0.0.1 | G42: Ok 3.0.0.1 | H42: Ok 3.0.0.1 | I42: Ok 3.0.0.1 | J42: Ok 3.0.0.1
A43: 4 | B43: Chaipro Fleet | C43: Ok 3.2.5.1 | D43: Ok 3.2.5.1 | E43: Ok 3.2.5.1 | F43: Ok 3.2.5.1 | G43: Ok 3.2.5.1 | H43: Ok 3.2.5.1 | I43: Ok 3.2.5.1 | J43: Ok 3.2.5.1
A44: 6 | B44: KTDA Replicator | C44: Ok 0.0.0.1 | D44: Ok 0.0.0.1 | E44: Ok 0.0.0.1 | F44: Ok 0.0.0.1 | G44: Ok 0.0.0.1 | H44: Ok 0.0.0.1 | I44: Ok 0.0.0.1 | J44: Ok 0.0.0.1
A45: 7 | B45: Chai Data | C45: OK | D45: OK | E45: OK | F45: OK | G45: OK | H45: OK | I45: OK | J45: OK
A46: 8 | B46: ETR Device | C46: OK | D46: OK | E46: OK | F46: OK | G46: OK | H46: OK | I46: OK | J46: OK
A47: 9 | B47: SMS Portal/USSD (Date growers received) | C47: Functional | D47: Functional | E47: Functional | F47: Functional | G47: Functional | H47: Functional | I47: Functional | J47: Functional
A48: 10 | B48: % NFC Card Usage | C48: 0.999 | D48: 0.69 | E48: 0.99 | F48: 0.98 | G48: 0.998 | H48: 0.989 | I48: 0.69 | J48: 0.95
B50: Region 5
A51: No. | B51: Item | C51: KAPKATET | D51: MOMUL | E51: TEGAT | F51: CHELAL | G51: TEBESONIK | H51: LITEIN | I51: TOROR | J51: KAPSET | K51: MOGOGOSIEK | L51: MOTIGO | M51: KOBEL | N51: KAPKOROS | O51: TRIGAGA | P51: ROROK | Q51: OLENGRUONE | R51: BOITO
A52: 1 | B52: Chaipro Financials | C52: 2.5.5.9 | D52: 2.5.5.9 | E52: 2.5.6.0 | F52: Working | G52: 2.5.5.9 | H52: Working | I52: 2.5.5.9 Retired by SAP | J52: 2.5.5.9 | K52: 2.5.5.9 | L52: Working 2.5.5.8 | M52: Fully Functional | N52: Working 2.5.5.8 | O52: OK 2.5.5.9 | P52: 2.5.5.9 | Q52: 2.5.6.0 | R52: Fully Functional
A53: 2 | B53: Chaipro Factory/TVAP | C53: 2.5.2.7 | D53: 2.5.2.7 | E53: 2.5.5.7 | F53: Working | G53: 2.5.2.7 | H53: Working | I53: 2.5.2.7 Retired by SAP | J53: 2.5.2.7 | K53: 2.5.2.7 | L53: Working 2.5.2.7 | M53: Fully Functional | N53: Working 2.5.2.7 | O53: OK 2.5.2.7 | P53: 2.5.2.7 | Q53: 2.5.2.7 | R53: Fully Functional
A54: 3 | B54: Chaipro Farmers | C54: 3.0.0.1 | D54: 3.0.0.1 | E54: 3.0.0 | F54: Working | G54: 3.0.0.1 | H54: Working | I54: 3.0.0 Fully utilized | J54: 3.0.0.1 | K54: 3.0.0.1 | L54: Working 3.0.0.2 | M54: Fully Functional | N54: Working 3.0.0.1 | O54: OK 3.0.0.2 | P54: 3.0.0.1 | Q54: 3.0.0.2 | R54: Fully Functional
A55: 4 | B55: Chaipro Fleet | C55: 3.2.5.1 | D55: 3.0.3 | E55: 1.0.6 | F55: Working | G55: 3.2.5.1 | H55: Working | I55: 3.2.5.1 Partially… in use | J55: 3.2.5.1 | K55: 3.2.5.1 | L55: Working 3.2.5.1 | M55: Fully Functional | N55: Working 3.2.5.1 | O55: N/A | P55: 3.2.5.1 | Q55: 3.2.5.1 | R55: Fully Functional
A56: 5 | B56: KTDA Replicator | C56: 0.0.0.1 | D56: VER010 | E56: ok | F56: Working | G56: 0.0.0.1 | H56: Working | I56: Fully utilized | J56: 0.1 | L56: Working | M56: Fully Functional | N56: Working | O56: OK | P56: 0.1 | Q56: OK | R56: Fully Functional
A57: 6 | B57: Chai Data | C57: N/A | D57: 1.0.0.3 | E57: n/a | F57: Working | G57: N/A | H57: Working | I57: 2.2 Fully utilized | J57: Not in use | L57: Working | M57: Fully Functional | N57: Working | O57: OK | P57: Not in use | Q57: Not in use | R57: Fully Functional
A58: 7 | B58: ETR Device | C58: 2 | D58: INCOTEX181 | E58: 4 pcs | F58: Working | G58: 2 | H58: Working | I58: 2.0.1.5 Fully in use | J58: okay | K58: 2 | L58: Working | M58: Fully Functional | N58: Working | O58: OK | P58: okay | Q58: Incotext 181 | R58: Fully Functional
A59: 8 | B59: SMS Portal/USSD (Date the growers received) | C59: 02.10.2025 | D59: Growers normally receive the sms on 2nd day . | E59: 45935 | F59: 45902 | G59: 02.10.2025 | H59: 45902 | I59: 45931 | J59: 45931 | K59: 2 | L59: Working | M59: Fully Functional | N59: Working | O59: OK | P59: 45933.694 | Q59: 3rd Oct 2025 | R59: Fully Functional
A60: 9 | B60: % NFC Card usage | C60: 1 | D60: 1 | E60: 1 | F60: 1 | G60: 1 | H60: 1 | I60: 1 | J60: 0 | K60: 0.98 | L60: 1 | M60: Fully Functional | N60: 1 | O60: 1 | P60: 0.25 | Q60: 0.97 | R60: Fully Functional
A61: 10 | B61: Any other | M61: Fully Functional | R61: Fully Functional
B63: Region 6
A64: No. | B64: Item | C64: Gianchore | D64: Sanganyi | E64: Kebirigo | F64: Tombe | G64: Matunwa | H64: Nyansiongo | I64: Nyankoba | J64: Sombogo | K64: Kiamokama | L64: Mwamu | M64: Nyamache | N64: Itumbe | O64: Ogembo | P64: Eberege
A65: 1 | B65: Chaipro Financials | C65: 2.5.5.9 | D65: 2.5.5.9 | E65: 2.5.5.9……not in use, we are On SAP | F65: 2.5.6.0 (Legacy) | G65: Okay - Ver. 2.5.5.9 | H65: Okay - Ver. 2.5.5.9 | I65: Partially Used | J65: 2.5.6.0 (Legacy) | K65: Fully on SAP | L65: Fully on SAP | M65: 2.5.5.9 | N65: 2.5.5.9 Partially utilized | O65: 2.5.5.9 | P65: 2.5.5.9
A66: 2 | B66: Chaipro Factory/ TVAP | C66: 2.5.2.7 | D66: 2.5.2.7 | E66: 2.5.2.7…… partially utilized | F66: 2.5.2.7 (Legacy) | G66: Okay - 2.5.2.7 | H66: Okay - 2.5.2.7 | I66: OK | J66: 2.5.2.7 (Legacy) | K66: Fully on SAP | L66: Fully on SAP | M66: 2.5.2.7 | N66: 2.5.2.7 Partially utilized | O66: 2.5.2.7 | P66: 2.5.2.7
A67: 3 | B67: Chaipro Farmers | C67: 3.0.0.1 | D67: 3.0.0.1 | E67: Fully utilized | F67: 3.0.0.1 (Fully Utilized) | G67: Okay - 3.0.0.1 | H67: Okay - 3.0.0.1 | I67: OK | J67: 3.0.0.1 (Fully Utilized) | K67: 3.0.0.1 - fully utilized. | L67: 3.0.0.1 - fully utilized. | M67: 3.0.0.1 | N67: 3.0.0.1 Being fully utilized | O67: 2.8.0.0 | P67: 2.8.0.0
A68: 4 | B68: Chaipro Fleet | C68: 3.2.5.1 | D68: 3.2.5.1 | E68: 3.2.5.1 partially utilized | F68: 3.2.1.1 (Legacy) | G68: Okay - 3.2.5.1 | H68: Okay - 3.2.5.1 | I68: Partially Used | J68: 3.2.1.1 (Legacy) | K68: 3.2.5.1 - Partly utilized. | L68: 3.2.5.1 - Partly utilized. | M68: 3.2.5.1 | N68: 3.2.5.1 Partially utilized | O68: 3.2.5.1 | P68: 3.2.5.1
A69: 6 | B69: KTDA Replicator | C69: 0.0.0.1 | D69: 0.0.0.1 | E69: Fully utilized | F69: 010 Fully Utilized | G69: Okay | H69: Okay | I69: OK | J69: 010 Fully Utilized | K69: fully utilized. | L69: fully utilized. | M69: 0.0.0.1 | N69: 0.0.0.1 Sending and Receiving package as expected. | O69: 0.0.0.1 | P69: 0.0.0.1
A70: 7 | B70: Chai Data | C70: ok | D70: replication software installed and working ok | E70: N/a | F70: 1.0.0.3 (Legacy) | G70: Okay | H70: Okay | I70: OK | J70: 1.0.0.3 (Legacy) | K70: Fully on SAP | L70: Fully on SAP | M70: ok | N70: N/A | O70: OK | P70: OK
A71: 8 | B71: ETR Device | C71: OK | D71: OK | E71: OK | F71: 2 pcs – Utilized 1 pc – under repair | G71: Okay | H71: Okay | I71: OK | J71: 2 pcs – Utilized 1 pc – under repair | K71: New TIMS ETR in use | L71: New TIMS ETR in use | M71: OK | N71: Working well | O71: OK | P71: OK
A72: 9 | B72: SMS Portal/USSD (Date growers received) | C72: 3rd Oct | D72: 3rd Oct | E72: 2.10.2025 | F72: 2025-09-02 – Utilized | G72: 3rd Oct | H72: 3rd Oct | I72: OK | J72: 2025-09-02 – Utilized | K72: 3rd Oct | L72: 3rd Oct | M72: 3rd Oct | N72: Ok, Though not 100% registered. | O72: 3rd Oct | P72: 3rd Oct
A73: 10 | B73: % NFC Card Usage | C73: 1 | D73: 1 | E73: 1 | F73: 1 | G73: N/A | H73: 1 | I73: 1 | J73: 0.5935 | M73: 1 | N73: At 100% | O73: 1 | P73: 1
B75: Region 7
A76: No. | B76: Item | C76: Chebut | D76: Kaptumo | E76: Mudete | F76: Kapsara
A77: 1 | B77: Chaipro Financials | C77: 2.5.5.9,Decommissined | D77: 2.5.5.9,Decommissined | E77: 2.5.5.9,Decommissined | F77: 2.5.5.9,Decommissined
A78: 2 | B78: Chaipro Factory/ TVAP | C78: 2.5.2.7, Working | D78: 2.5.2.7, Working | E78: 2.5.2.7, Working | F78: 2.5.2.7, Working
A79: 3 | B79: Chaipro Farmers | C79: 3.0.0.2, Working | D79: 3.0.0.2, Working | E79: 3.0.0.2, Working | F79: 3.0.0.2, Working
A80: 4 | B80: Chaipro Fleet | C80: 3.2.5.1, Working | D80: 3.2.5.1, Working | E80: 3.2.5.1, Working | F80: 3.2.5.1, Working
A81: 6 | B81: KTDA Replicator | C81: Working | D81: Working | E81: Working | F81: Working
A82: 7 | B82: Chai Data | C82: Not in Use | D82: Not in Use | E82: Not in Use | F82: Not in Use
A83: 8 | B83: ETR Device | C83: Working | D83: Working | E83: Working | F83: Working
A84: 9 | B84: SMS Portal/USSD (Date growers received) | C84: Working, received on 03/10/25 | D84: Working, received on 03/10/25 | E84: Working, received on 03/10/25 | F84: Working, received on 03/10/25
A85: 10 | B85: % NFC Card Usage | C85: 0.84 | D85: 1 | E85: 1 | F85: 0.85

Sheet ICT Inventory
B1: Region 1 | J1: ='Infrastructure and Systems'!M2 -> 45930
A2: No. | B2: Item/Factory | C2: KAMBAA | D2: KAGWE | E2: THETA | F2: Ndarugu | G2: GACHEGE | H2: MATAARA | I2: NGERE | J2: NJUNU | K2: MAKOS | L2: NDUTI | M2: IKUMBI | N2: GACHARAGE
A3: 1 | B3: Network Equipment (e.g. Switches and routers functionality and any other additional information) | C3: Fully Operational | D3: Fully Operational | E3: Fully Operational | F3: Fully Operational | G3: Fully Operational | H3: Fully Operational | I3: Fully Operational | J3: Fully Operational | K3: Fully Operational | L3: Fully Operational | M3: Fully Operational | N3: Fully Operational
A4: 2 | B4: Software (e.g. 3rd party, Licenses, etc.) | C4: Procured 10 Licences for Microsoft 2016 | D4: Procured 5 Licences for Microsoft 2016 | E4: Procured 6 Licences for Microsoft 2016 | F4: Procured 5 Licences for Microsoft 2016 | G4: Procured 10 Licences for icrosoft 2016 | H4: EWS software, Windows server software, Office 2016. | I4: Procured 5 Licences for Microsoft 2016 | J4: Procured 5 Licences for microsoft 2016 | K4: Procured 10 Licenses for Microsoft 2016 in October | L4: Raised an order of 7 Microsoft 2016 office | M4: OPERATIONALIZED for MS office licenses | N4: Procured 7 Licences for Microsoft 2016
A5: 3 | B5: Hardware (e.g. Servers, | C5: Fully Operational | D5: Fully Operational | E5: Fully Operational | F5: Fully Operational | G5: Fully Operational | H5: Fully Operational | I5: Fully Operational | J5: Fully Operational | K5: Fully Operational | L5: Fully Operational | M5: Fully Operational | N5: Fully Operational
B6: PCs, | C6: Fully Operational | D6: Fully Operational | E6: Fully Operational | F6: Fully Operational | G6: Fully Operational | H6: Fully Operational | I6: Fully Operational | J6: Fully Operational | K6: Fully Operational | L6: Fully Operational | M6: Fully Operational | N6: Fully Operational
B7: Laptops, | C7: Fully Operational | D7: Fully Operational | E7: Fully Operational | F7: Fully Operational | G7: Fully Operational | H7: Fully Operational | I7: Fully Operational | J7: Fully Operational | K7: Fully Operational | L7: Fully Operational | M7: Fully Operational | N7: Fully Operational
B8: UPS's | C8: Fully Operational | D8: Fully Operational | E8: Fully Operational | F8: Fully Operational | G8: Fully Operational | H8: Fully Operational | I8: Fully Operational | J8: Fully Operational | K8: Fully Operational | L8: Fully Operational | M8: Fully Operational | N8: Fully Operational
B9: Das, | C9: Fully Operational | D9: Fully Operational | E9: Fully Operational | F9: Fully Operational | G9: Fully Operational | H9: Fully Operational | I9: Fully Operational | J9: Fully Operational | K9: Fully Operational | L9: Fully Operational | M9: Fully Operational | N9: Fully Operational
B10: Printers, | C10: Fully Operational | D10: Fully Operational | E10: Fully Operational | F10: Fully Operational | G10: Fully Operational | H10: Fully Operational | I10: Fully Operational | J10: Fully Operational | K10: Fully Operational | L10: Fully Operational | M10: Fully Operational | N10: Fully Operational
B11: Scanners, | C11: Fully Operational | D11: Fully Operational | E11: Fully Operational | F11: Fully Operational | G11: Fully Operational | H11: Fully Operational | I11: Fully Operational | J11: Fully Operational | K11: Fully Operational | L11: Fully Operational | M11: Fully Operational | N11: Fully Operational
B12: ESD, | C12: Fully Operational | D12: Fully Operational | E12: Fully Operational | F12: Fully Operational | G12: Fully Operational | H12: Fully Operational | I12: Fully Operational | J12: Fully Operational | K12: Fully Operational | L12: Fully Operational | M12: Fully Operational | N12: Fully Operational
B13: Fiscal Printers) | C13: Fully Operational | D13: Fully Operational | E13: Fully Operational | F13: Fully Operational | G13: Fully Operational | H13: Fully Operational | I13: Fully Operational | J13: Fully Operational | K13: Fully Operational | L13: Fully Operational | M13: Fully Operational | N13: Fully Operational
A14: 4 | B14: Firewall | C14: Sophos License Expired | D14: Sophos License Expired | E14: Sophos License Valid | F14: Sophos License Valid | G14: Sophos License Expired | H14: Sophos License Expired | I14: Sophos License Expired | J14: Sophos License Expired | K14: Sophos License Expired | L14: Sophos License Expired | M14: Sophos License Expired | N14: Sophos License Expired
A15: 5 | B15: Tablets | C15: Fully Operational | D15: Fully Operational | E15: Fully Operational | F15: Fully Operational | G15: Fully Operational | H15: Fully Operational | I15: Fully Operational | J15: Fully Operational | K15: Fully Operational | L15: Fully Operational | M15: Fully Operational | N15: Fully Operational
A16: 6 | B16: EWS (Working)
B17: PDA | C17: 10 | D17: 9 | E17: 7 | F17: 8 | G17: 8 | H17: 8 | J17: 7 | K17: 14 | L17: 7 | M17: 10 | N17: 8
B18: SCALE | C18: 10 | D18: 9 | E18: 7 | F18: 8 | G18: 8 | H18: 8 | J18: 7 | K18: 14 | L18: 7 | M18: 10 | N18: 8
B19: PRINTER | C19: 10 | D19: 9 | E19: 7 | F19: 8 | G19: 8 | H19: 8 | J19: 7 | K19: 14 | L19: 7 | M19: 10 | N19: 8
A20: 7 | B20: Other Equipment (please specify) | C20: none | D20: none | E20: none | F20: none | G20: none | H20: none | I20: none | J20: none | K20: none | L20: none | M20: none | N20: none
B22: Region 2 | J22: ='Infrastructure and Systems'!M23 -> 0
A23: No. | B23: Item/Factory | C23: Ragati | D23: Gathuthi | E23: Gitugi | F23: Iriaini | G23: Chinga | H23: Kiru | I23: Gatunguru | J23: Kanyenyaini | K23: Githambo
A24: 1 | B24: Network Equipment (e.g. Switches and routers functionality and any other additional information) | C24: functional | D24: functional | E24: functional | F24: functional | G24: functional | H24: functional | I24: functional | J24: functional | K24: functional
A25: 2 | B25: Software (e.g. 3rd party, Licenses, etc.) | C25: functional | D25: functional | E25: functional | F25: functional | G25: functional | H25: functional | I25: functional | J25: functional | K25: functional
A26: 3 | B26: Hardware (e.g. Servers, | C26: functional | D26: functional | E26: functional | F26: functional | G26: functional | H26: functional | I26: functional | J26: functional | K26: functional
B27: PCs, | C27: functional | D27: functional | E27: functional | F27: functional | G27: functional | H27: functional | I27: functional | J27: functional | K27: functional
B28: Laptops, | C28: functional | D28: functional | E28: functional | F28: functional | G28: functional | H28: functional | I28: functional | J28: functional | K28: functional
B29: UPS's | C29: functional | D29: functional | E29: functional | F29: functional | G29: functional | H29: functional | I29: functional | J29: functional | K29: functional
B30: Das, | C30: functional | D30: functional | E30: functional | F30: functional | G30: functional | H30: functional | I30: functional | J30: functional | K30: functional
B31: Printers, | C31: functional | D31: functional | E31: functional | F31: functional | G31: functional | H31: functional | I31: functional | J31: functional | K31: functional
B32: Scanners, | C32: functional | D32: functional | E32: functional | F32: functional | G32: functional | H32: functional | I32: functional | J32: functional | K32: functional
B33: ESD, | C33: functional | D33: functional | E33: functional | F33: functional | G33: functional | H33: functional | I33: functional | J33: functional | K33: functional
B34: Fiscal Printers) | C34: functional | D34: functional | E34: functional | F34: functional | G34: functional | H34: functional | I34: functional | J34: functional | K34: functional
A35: 4 | B35: Firewall | C35: functional | D35: functional | E35: functional | F35: functional | G35: functional | H35: functional | I35: functional | J35: functional | K35: functional
A36: 5 | B36: Tablets
A37: 6 | B37: EWS (Working)
B38: PDA
B39: SCALE
B40: PRINTER
A41: 7 | B41: Other Equipment (please specify)
B43: Region 3 | J43: ='Infrastructure and Systems'!M44 -> 0
A44: No. | B44: Item | C44: NDIMA | D44: MUNUNGA | E44: KANGAITA | F44: KIMUNYE | G44: THUMAITA | H44: KATHANGARIRI | I44: MUNGANIA | J44: RUKURIRI
A45: 1 | B45: Network Equipment (e.g. Switches and routers functionality and any other additional information) | C45: Working OK Cat5 | D45: Working OK Cat 6 | E45: Working OK Cat5 | F45: Working OK Cat6 | G45: Working OK Cat6 | H45: Working OK Cat5 | I45: Working OK Cat5
A46: 2 | B46: Software (e.g. 3rd party, Licenses, etc.) | C46: Working OK | D46: Working OK | E46: Working OK | F46: Working OK | G46: Working OK | H46: Working OK | I46: Working OK
A47: 3 | B47: Hardware (e.g. Servers, | C47: Working OK | D47: Working OK | E47: OK | F47: Ok | G47: OKAY | H47: Working well | I47: Working OK
B48: PCs, | C48: NO FIREWALL | D48: Working OK | E48: OK | F48: Ok | G48: N/A | H48: NOT WORKING | I48: Working OK
B49: Laptops, | C49: Working OK | D49: Working OK | E49: OK though space needs to be increased | F49: Ok | G49: OKAY | H49: Working well | I49: Working OK
B50: UPS's | C50: Working OK | D50: Working OK | E50: OK | F50: Ok | G50: OKAY | H50: Working well | I50: Working OK
B51: Das, | C51: 1.0.52 | D51: 1.0.52 | E51: 1.0.57 | F51: Ok | G51: VER.58 | H51: VER. .58 | I51: AMITY ver .52
B52: Printers, | C52: 9 | D52: 9 | E52: 10 | F52: 8 | G52: 11 | H52: 12 KITS | I52: 9
B53: Scanners, | C53: All OK | D53: All OK | E53: OK | F53: Ok | G53: OKAY | H53: OKAY | I53: All OK
B54: ESD, | C54: Working OK (calibration done) | D54: Working OK (calibration done) | E54: Working OK (calibration done) | F54: Working OK (calibration done) | G54: OKAY | H54: Working OK (calibration done) | I54: Working OK (calibration done)
B55: Fiscal Printers) | C55: OKAY -NEEDS SERVICING | D55: OKAY -NEEDS SERVICING | E55: OKAY -NEEDS SERVICING | F55: OKAY -NEEDS SERVICING | G55: OKAY | H55: OKAY -NEEDS SERVICING | I55: OKAY -NEEDS SERVICING
A56: 4 | B56: Firewall | C56: OK | D56: OK | E56: OK | F56: Ok | G56: OKAY | H56: STABLE | I56: OK
A57: 5 | B57: Tablets | C57: N/A | D57: N/A | E57: N/A | F57: N/A | G57: N/A | H57: N/A | I57: N/A
A58: 6 | B58: EWS (Working) | C58: None | D58: NONE | E58: NONE | F58: NONE | G58: NONE | H58: NONE | I58: NONE
B59: PDA
B60: SCALE
B61: PRINTER
A62: 7 | B62: Other Equipment (please specify)
B64: Region 4
A65: No. | B65: Item/Factory | C65: Kiegoi | D65: Michimikuru | E65: Githongo | F65: Imenti | G65: Kionyo | H65: Kinoro | I65: Igembe | J65: Weru
A66: 1 | B66: Network Equipment (e.g. Switches and routers functionality and any other additional information) | C66: PM’s Office Switch | D66: Hub FSC Office | E66: FACTORY and LEAFBASE | F66: FACTORY and LEAFBASE | G66: FACTORY and LEAFBASE | H66: FACTORY and LEAFBASE | I66: Server room Switch | J66: 1 cabinet –server room
A67: 2 | B67: Software (e.g. 3rd party, Licenses, etc.) | C67: AFA’s Office | D67: Switch -FUM Office | E67: Switch -FUM Office | F67: Switch -FUM Office | G67: Switch -FUM Office | H67: Switch -FUM Office | I67: PM’s Office Switch | J67: 1 cabinet – Fsc office
A68: 3 | B68: Hardware (e.g. Servers, | C68: Weighbridge | D68: Switch -Server Room | E68: Switch -Server Room | F68: Switch -Server Room | G68: Switch -Server Room | H68: Switch -Server Room | I68: Weighbridge switch | J68: Cisco router – server room
B69: PCs, | C69: NFC Card Printing software ok. | D69: PCs -15 | E69: PCs -14 | F69: PCs -13 | G69: 9PC'S | H69: 9PC'S | I69: 7PC'S | J69: 9PC'S
B70: Laptops, | C70: SAP in place | D70: Laptops -9 | E70: LAPTOPS 11 | F70: LAPTOPS 12 | G70: 13 LAPTOPS | H70: 13 LAPTOPS | I70: 5 LAPTOPS | J70: 13 LAPTOPS
B71: UPS's | C71: 3 Servers | D71: IBM X3500 | E71: SERVERS 3 | F71: SERVERS 3 | G71: 3SERVERS | H71: 3SERVERS | I71: 1 SERVER | J71: 3 SERVERS
B72: Das, | C72: 10 PCs | D72: IBM X3500 M3 | E72: LAPTOPS 11 | F72: LAPTOPS 11 | G72: 13 Laptops | H72: 13 Laptops | I72: 5 LAPTOPS | J72: 7 Laptops
B73: Printers, | C73: 8 Laptops | D73: Cisco Server | E73: PRINTERS 5 | F73: PRINTERS 6 | G73: 9 printers | H73: 9 printers | I73: 5 PRINTERS | J73: 9 printers
B74: Scanners, | C74: 10 UPS | D74: 2SCANNERS | E74: SCANNER on printers | F74: SCANNER on printers | G74: 2 SCANNERS | H74: 2 SCANNERS | I74: 2 SCANERS | J74: 3 SCANNERS
B75: ESD, | C75: 10 Printers | G75: 1 etr Machine | H75: 1 etr Machine | I75: 1 ETR | J75: 1 etr Machine
B76: Fiscal Printers) | C76: Scanners | D76: Printer-DFX 9000,DTC,HP
A77: 4 | B77: Firewall | C77: None | D77: NA | E77: budgeted | F77: Fortnet Firewall | G77: Fortnet Firewall | H77: Fortnet Firewall | I77: BUDGETED | J77: Fortnet Firewall
A78: 5 | B78: Tablets | C78: 7 tablets | D78: 6 (Directors) | E78: 7 | F78: 6 | G78: 9 | H78: 6 mini laptops | I78: 1 tablets | J78: 5
A79: 6 | B79: EWS (Working) | C79: 12 | E79: 14 | F79: 12 | G79: 12 | H79: 13 | I79: 6 | J79: 13
B80: PDA | C80: 12 | D80: 14 | E80: 13 | F80: 12 | G80: 16 | H80: 16 | I80: 8 | J80: 13
B81: SCALE | C81: 12 | D81: 18 | E81: 14 | F81: 12 | G81: 14 | H81: 15 | I81: 6 | J81: 13
B82: PRINTER | C82: 12 | D82: 13 | E82: 13 | F82: 12 | G82: 15 | H82: 14 | I82: 6 | J82: 13
A83: 7 | B83: Other Equipment (please specify)
B85: Region 5
A86: No. | B86: Item | C86: KAPKATET | D86: MOMUL | E86: TEGAT | F86: CHELAL | G86: TEBESONIK | H86: LITEIN | I86: TOROR | J86: KAPSET | K86: MOGOGSIEK | L86: MOTIGO | M86: KOBEL | N86: KAPKOROS | O86: TRIGAGA | P86: ROROK | Q86: OLENG | R86: BOITO
A87: 1 | B87: Network Equipment (e.g. Switches and routers functionality and any other additional information) | C87: 6 Switches (LB,PM Office, FUM Office, Stores, Server Room) | D87: switches -server room-1 -leafbase cabinet-1 Factory cabinet-1 Routers Server room-2 | F87: Working | G87: 3 Switches (Management Office, Server Room) | H87: Working | I87: 3 Switches (Management Office, Server Room) | J87: Server room, accounts office,fsa work shop and stores. | K87: Working well | L87: 2 Routers, 2 Switches Server Room Working, Server Cisco Server Room Working | M87: Fully Functional | N87: 1 Switch, 2 Routers Server Room - Working | O87: FSA OFFICE==OK | P87: Server room, Fum office | Q87: Server room, | R87: Fully Functional
A88: 2 | B88: Software (e.g. 3rd party, Licenses, etc.) | C88: Assorted | D88: Windows 2008 | G88: Assorted | I88: Assorted | J88: None | L88: PCs 2 Gen Office, 2 Sec Office, 2 Mech Office,1 Weighbridge, 3 GL Office– All working | M88: Fully Functional | O88: OK | P88: None | Q88: Server room | R88: Fully Functional
A89: 3 | B89: Hardware (Servers, PCs, Laptops, UPS, Printers, Scanners, etc.) | C89: 3 Servers | D89: Servers-2 | F89: Servers : 2 (working) | G89: No Server | H89: Servers : 3 (working) | I89: 2 Servers | J89: Servers-Okay | K89: 11 pcs | L89: 7 Laptops – All working | M89: Fully Functional | N89: 2 Servers Server Room - Working | O89: EWS SERVER OK | P89: Servers-Okay | Q89: Server room | R89: Fully Functional
C90: 10 Laptops | D90: Laptops-8pcs | F90: Laptops: 7 (Working) | G90: 5 Laptops | H90: Laptops:11 (Working) | I90: 5 Laptops | J90: Pcs-Okay | K90: 8 laptops | L90: 2 Servers Server Room – All working | M90: Fully Functional | N90: 1 UPS Server Room - Working | O90: CHAIPRO SERVER OK | P90: Pcs-Okay | Q90: PC’s and Laptops, Located in Users Designated offices | R90: Fully Functional
C91: 14 Pcs | D91: Desktops-11pcs | F91: PC’s : 5 (working) | G91: 12 Pcs | H91: PC’s : 6 (working) | I91: 18 Pcs | J91: Printers-Okay | K91: 2 sever | L91: 1 Printer Sec Office, 1 Gen Office, 1 Stores - Working | M91: Fully Functional | N91: 7 Laptops - Working | O91: DOMINO SERVER OK | P91: Printers-Okay | Q91: Scanner in Genral Office | R91: Fully Functional
C92: 7 Assorted Printers | D92: Scanner-1pc | F92: PRINTER: 2 (working) | G92: 6 Assorted Printers | H92: PRINTER: 4 (working) | I92: 4Assorted Printers | J92: UPS-Okay | L92: 1 Scanner Gen Office - Working | M92: Fully Functional | N92: 7 PCs - Working | O92: PRINTERS OK | P92: UPS-Okay | R92: Fully Functional
C93: 1 Flatbed Scanner | D93: Printers-7pcs & UPS 2.2KVA-5pcs | F93: UPS : 4 (working) | H93: UPS : 5 (working) | L93: 2 UPS Server Room - Working | M93: Fully Functional | N93: 3 Printers Working | O93: SCANNER OK | R93: Fully Functional
A94: 4 | B94: Firewall | C94: None | D94: 1 | E94: FGR7OF SN:FR70FTK23000032 | F94: Working | G94: None | H94: Unavailable | I94: None | J94: Okay | K94: 1 | L94: N/A | M94: Fully Functional | N94: Server Room - Working | O94: FORTIGATE =OK | P94: Not in place | Q94: Server room | R94: Fully Functional
A95: 5 | B95: Tablets | C95: 7 | D95: 9 | E95: 6 | F95: Working | G95: 1 | H95: Working | I95: 2 | J95: Okay | L95: 2 Working | M95: Fully Functional | N95: 2 Directors Working | O95: OK | P95: Okay | Q95: Director, FUM, FA, FSA | R95: Fully Functional
A96: 6 | B96: EWS (Working) | C96: 13 | D96: WORKING | E96: 10 | F96: 8 | G96: 9 | H96: 13 | I96: 11 | J96: okay | L96: 13 Working | M96: Fully Functional | N96: 17 - Working | O96: OK | P96: Okay | Q96: Virtual City | R96: Fully Functional
B97: PDA | C97: 13 | D97: 18 | E97: 10 | F97: 9 | G97: 10 | H97: 13 | I97: 12 | J97: Okay | K97: 13 | L97: 13 Working | M97: Fully Functional | N97: 17 - Working | O97: OK | P97: Okay | Q97: With designated LA’s | R97: Fully Functional
B98: Scale | C98: 13 | D98: 22 | E98: 10 | F98: 9 | G98: 9 | H98: 13 | I98: 13 | J98: Okay | K98: 13 | L98: 13 Working | M98: Fully Functional | N98: 17 - Working | O98: OK | P98: Okay | Q98: With designated LA’s | R98: Fully Functional
B99: Printer | C99: 13 | D99: 19 & 5PCS Require replacement | E99: 10 | F99: 8 | G99: 9 | H99: 13 | I99: 13 | J99: Okay | K99: 15 | L99: 13 Working | M99: Fully Functional | N99: 17 - Working | O99: WORKING | P99: Okay | Q99: With designated LA’s | R99: Fully Functional
A100: 7 | B100: Other Equipment(Specify) | D100: EWS server require replacement | G100: Hybrid PABX | O100: CCTV NVR WORKING
B102: Region 6
A103: No. | B103: Item/Factory | C103: Gianchore | D103: Sanganyi | E103: Kebirigo | F103: Tombe | G103: Matunwa | H103: Nyansiongo | I103: Nyankoba | J103: Sombogo | K103: Kiamokama | L103: Mwamu | M103: Nyamache | N103: Itumbe | O103: Ogembo | P103: Eberege
A104: 1 | B104: Network Equipment (e.g. Switches and routers functionality and any other additional information) | C104: 2 functional switches 1 Outdoor unit 1 Cisco router | D104: 3 PoE Switche(s) | E104: 2 24 PORT CISCO SWITCH FUNCTIONAL One cisco router OK Micrototik router OK | F104: 2 LAN Switches- Requires upgrade | G104: 2 Switches functional | H104: 2 Functional | I104: 3 SMART D-LINK SWITCH | J104: 2 LAN Switches | K104: 2 Switches | L104: 2 functional switches 1 Outdoor unit 2 Cisco router | M104: 3 FUNCTIONAL | N104: Switches – Four (4), Functional , 1 is POE. | O104: 2 Functional | P104: 2 Functional
A105: 2 | B105: Software (e.g. 3rd party, Licenses, etc.) | C105: Backoffice 1 Domino Server 1 Windows 2008 1 | D105: NONE | E105: MS Window server 2008 Ms Windows 7 SUSE LINUX | F105: N/A | G105: Office 2019 | H105: Ofiice 2007 Windows &7,10 Win Server 2008 Win server 2012 | I105: NONE | J105: N/A | K105: Virtual city, SQL, Lotus Domino,Microsoft Windows Server 2008, Linux Suse, all good. | L105: Virtual city, SQL, Lotus Domino,Microsoft Windows Server 2008, Linux Suse, all good. | M105: None | N105: Back office, Windows server 2008, SQL 2000, Windows 7,10 & Symantec 12/14
...

Sheet BCP
B1: Region 1 | F1: ='Infrastructure and Systems'!M2 -> 45930
A2: No. | B2: Item/Factory | C2: KAMBAA | D2: KAGWE | E2: THETA | F2: NDARUGU | G2: GACHEGE | H2: MATAARA | I2: NGERE | J2: NJUNU | K2: MAKOS | L2: NDUTI | M2: IKUMBI | N2: GACHEGE
A3: 1 | B3: Onsite Backup | C3: In place | D3: In place | E3: In place | F3: In place | G3: In place | H3: In place | I3: In place | J3: In place | K3: In place | L3: In place | M3: In place | N3: In place
A4: 2 | B4: Remote Backup | C4: In place | D4: In place | E4: In place | F4: In place | G4: In place | H4: In place | I4: In place | J4: In place | K4: In place | L4: In place | M4: In place | N4: In place
A5: 3 | B5: Mail Server Backup (Date) | C5: 45931 | D5: 45931 | E5: 45931 | F5: 45931 | G5: 45931 | H5: 45931 | I5: 45931 | J5: 45931 | K5: 45931 | L5: 45931 | M5: 45931 | N5: 45931
B7: Region 2
A8: No. | B8: Item/Factory | C8: Ragati | D8: Gathuthi | E8: Gitugi | F8: Iriaini | G8: Chinga | H8: Kiru | I8: Gatunguru | J8: Kanyenyaini
A9: 1 | B9: Onsite Backup | C9: SQL chaipro backup EWS 2 Backup | D9: SQL chaipro backup EWS 2 Backup | E9: SQL chaipro backup EWS 2 Backup | F9: SQL chaipro backup EWS 2 Backup | G9: SQL chaipro backup EWS 2 Backup | H9: SQL chaipro backup EWS 2 Backup | I9: SQL chaipro backup EWS 2 Backup | J9: SQL chaipro backup EWS 2 Backup
A10: 2 | B10: Remote Backup | C10: SQL chaipro backup EWS 2 Backup | D10: SQL chaipro backup EWS 2 Backup | E10: SQL chaipro backup EWS 2 Backup | F10: SQL chaipro backup EWS 2 Backup | G10: SQL chaipro backup EWS 2 Backup | H10: SQL chaipro backup EWS 2 Backup | I10: SQL chaipro backup EWS 2 Backup | J10: SQL chaipro backup EWS 2 Backup
A11: 3 | B11: Mail Server Backup (Date)
B13: Region 3
A14: No. | B14: Item/Factory | C14: NDIMA | D14: MUNUNGA | E14: KANGAITA | F14: KIMUNYE | G14: THUMAITA | H14: KATHANGARIRI | I14: MUNGANIA | J14: RUKURIRI
A15: 1 | B15: Onsite Backup | C15: Automated Full Back up on external hard drive | D15: Weighbridge PC | E15: Done at the weighbridge pc | F15: Ok | G15: In place | H15: Okay | I15: Ok | J15: Ok
A16: 2 | B16: Remote Backup | C16: Region office 4:00am | D16: Region office 4:00am | E16: Regional office 10:50 pm | F16: Regional office 2:50 pm | G16: In place | H16: Okay | I16: Regional office 11:55 pm | J16: Regional office 10:05 pm
A17: 3 | B17: Mail Server Backup (Date) | D17: 45904 | E17: [3.10.2025] | F17: Ok | G17: [03.10.2025] | H17: [03.10.2025] | I17: [03.10.2025]
B20: Region 4
A21: No. | B21: Item/Factory | C21: Kiegoi | D21: Michimikuru | E21: Githongo | F21: Imenti | G21: Kionyo | H21: Kinoro | I21: Igembe | J21: Weru
A22: 1 | B22: Onsite Backup | C22: Back to PC machine Back up to External HDD | D22: Back to A PC machine Back up to External HDD | E22: Back to PC machine Back up to External HDD | F22: Back to PCmachine Back up to External HDD | G22: Back to PC machine Back up to External HDD | H22: Back to PC machine Back up to External HDD | I22: Back to PC machine Back up to External HDD | J22: Back to PC machine Back up to External HDD
A23: 2 | B23: Remote Backup | C23: Not yet active | D23: Not yet active | E23: Not yet active | F23: Not yet active | G23: Not yet active | H23: Not yet active | I23: Not yet active | J23: Not yet active
A24: 3 | B24: Mail Server Backup (Date) | C24: Back up done on 30/9 | D24: Back up done on 30/9 | E24: Back up done on 30/9 | F24: Back up done on 30/9 | G24: Back up done on 30/9 | H24: Back up done on 30/9 | I24: Back up done on 30/9 | J24: Back up done on 30/9
B26: Region 5
A27: No. | B27: Item | C27: KAPKATET | D27: MOMUL | E27: TEGAT | F27: CHELAL | G27: TEBESONIK | H27: LITEIN | I27: TOROR | J27: KAPSET | K27: MOGOGSIEK | L27: MOTIGO | M27: KOBEL | N27: KAPKOROS | O27: TRIGAGA | P27: ROROK | Q27: OLENGRUONE | R27: BOITO | S27: MOTIGO | T27: KOBEL | U27: KAPKOROS | V27: TRIGAGA | W27: ROROK | X27: OLENGRUONE | Y27: BOITO
A28: 1 | B28: Onsite Backup | C28: In Place | D28: OK | E28: Ok/tested | F28: working | G28: In Place | H28: working | I28: Ok/tested | J28: local backup 10.11.6.31 | K28: ok | L28: OK | M28: OK | N28: Working | O28: OK | P28: local backup 10.11.16.150 | Q28: OK | S28: OK | T28: OK | U28: Working | V28: OK | W28: local backup 10.11.16.150 | X28: OK
A29: 2 | B29: Remote Backup | C29: External HDD | D29: N/A | E29: No remote backup | F29: working | H29: working | I29: No remote backup | J29: Remote 10.11.16.150 | K29: non | L29: N/A | M29: N/A | N29: N/A | O29: OK | P29: Remote 10.11.6.31 | Q29: Not Available. | S29: N/A | T29: N/A | U29: N/A | V29: OK | W29: Remote 10.11.6.31 | X29: Not Available.
A30: 3 | B30: Mail Server Backup (Date) | C30: 25.09.2025 | E30: Ok/30/09/2025 | G30: 30.09.2025 | I30: Ok/30/09/2025 | J30: None in place | K30: 25th Sep 2025 | P30: None in place | Q30: 3rd Oct 2025 | W30: None in place | X30: 3rd Oct 2025
B32: Region 6
A33: No. | B33: Item/Factory | C33: Gianchore | D33: Sanganyi | E33: Kebirigo | F33: Tombe | G33: Matunwa | H33: Nyansiongo | I33: Nyankoba | J33: Sombogo | K33: Kiamokama | L33: Mwamu | M33: Nyamache | N33: Itumbe | O33: Ogembo | P33: Eberege
A34: 1 | B34: Onsite Backup | C34: Automated Full Back up on external hard drive | D34: Weighbridge PC | E34: Done at the weighbridge pc | F34: Ok | G34: In place | H34: Okay | I34: Ok | J34: Ok | K34: Ok | L34: Ok | M34: Ok | N34: Full back up on One remote computer | O34: Weighbridge PC | P34: Weighbridge/GL Clerk PC
A35: 2 | B35: Remote Backup | C35: Region office 4:00am | D35: Region office 4:00am | E35: Regional office 10:50 pm | F35: Regional office 2:50 pm | G35: In place | H35: Okay | I35: Regional office 11:55 pm | J35: Regional office 10:05 pm | K35: Regional office 11:00 pm | L35: Regional office 10:20 pm | M35: Regional office 11:00am | N35: automatically every night to an external hard disk and region office 12:00 am. | O35: Region office 12:05 am | P35: Region office 3:00 pm
A36: 3 | B36: Mail Server Backup (Date) | D36: 45904 | E36: [3.10.2025] | F36: Ok | G36: [03.10.2025] | H36: [03.10.2025] | I36: [03.10.2025] | K36: [02/10/2025] | M36: [5TH OCT 2025] | N36: [11th September 2025] | O36: 45930 | P36: 45904
B38: Region 7
A39: No. | B39: Item/Factory | C39: Chebut | D39: Kaptumo | E39: Mudete | F39: Kapsara
A40: 1 | B40: Onsite Backup | C40: Okay | D40: Okay | E40: Okay | F40: Okay
A41: 2 | B41: Remote Backup | C41: Okay | D41: Not Working | E41: Not Working | F41: Not Working
A42: 3 | B42: Mail Server Backup (Date) | C42: 02.10.2025

Sheet ICT Cost
A1: Region 1 | K1: ='Infrastructure and Systems'!M2 -> 45930
A2: Item | B2: Kambaa | C2: Kagwe | D2: Theta | E2: Gachege | F2: Ndarugu | G2: Mataara | H2: Ngere | I2: Gacharage | J2: Ikumbi | K2: Nduti | L2: Makos | M2: Njunu | N2: Total
A3: Recurrent costs for the month | B3: 168896.79 | C3: 181420 | D3: 116487.47 | E3: 24000.75 | F3: 26783 | G3: 70121.37 | H3: 507991.43 | I3: 92217.6 | J3: 168896.79 | K3: 25100 | L3: 62309.6 | M3: 63741.26 | N3: =SUM(B3:M3) -> 1507966.1
A4: Capital costs for the month | B4: 0 | C4: - | D4: 396253.8 | E4: 0 | F4: 0 | G4: - | H4: 0 | I4: 0 | J4: 0 | K4: 889000 | L4: 0 | M4: 0 | N4: =SUM(B4:M4) -> 1285253.8
A5: Total Cost for month | B5: 168896.79 | C5: 181420 | D5: 512741.27 | E5: 24000.75 | F5: 26783 | G5: 70121.37 | H5: 507991.43 | I5: 92217.6 | J5: 168896.79 | K5: 914100 | L5: 62309.6 | M5: 63741.26 | N5: =SUM(B5:M5) -> 2793219.9
A6: Recurrent to date as at AUG 25 | B6: 465516.79 | C6: 538470 | D6: 175977.09 | E6: 234062.5 | F6: 370125 | G6: 292859.37 | H6: 1084650.4 | I6: 175635.24 | J6: 223971.79 | K6: 249158 | L6: 169619.6 | M6: 348741.26 | N6: =SUM(B6:M6) -> 4328787.1
A7: Capital to date as at AUG 25 | D7: 396253.8 | E7: 1331680 | K7: 889000 | N7: =SUM(B7:M7) -> 2616933.8
A8: Total Cost As at AUG FOR ICT Fin. Yr 25.26 | B8: 465516.79 | C8: 538470 | D8: 572230.89 | E8: 1565742.5 | F8: 370125 | G8: 292859.37 | H8: 1084650.4 | I8: 175635.24 | J8: 223971.79 | K8: 1138158 | L8: 169619.6 | M8: 348741.26 | N8: =SUM(B8:M8) -> 6945720.9
A9: Comments
A10: BUDGET 25.26 | N10: =SUM(B10:M10) -> 0
A12: Region 2
A13: Item/Factory | B13: Ragati | C13: Gathuthi | D13: Gitugi | E13: Iriaini | F13: Chinga | G13: Kiru | H13: Gatunguru | I13: Kanyenyaini | J13: Githambo | K13: TOTALS
A14: Recurrent costs (month) | B14: 16700 | C14: 0 | D14: 0 | E14: 0 | F14: 0 | G14: 18,100 | H14: 110000 | I14: 0 | J14: 66368 | K14: =SUM(B14:J14) -> 193068
A15: Capital costs (month) | B15: 0 | C15: 0 | D15: 0 | E15: 0 | F15: 0 | G15: 0 | H15: 0 | I15: 218,080 | J15: 48,000 | K15: =SUM(B15:J15) -> 0
A16: Total Cost (month) | B16: 16700 | C16: 0 | D16: 0 | E16: 0 | F16: 0 | G16: 50168 | H16: 110000 | I16: 0 | J16: 114368 | K16: =SUM(B16:J16) -> 291236
A17: Recurrent (To Date) | B17: 43900 | C17: 0 | D17: 39560 | E17: 6420 | F17: 27168 | G17: 50168 | H17: 260,000 | I17: 0 | J17: 183,816 | K17: =SUM(B17:J17) -> 94068
A18: Capital Costs (To Date) | B18: 0 | C18: 0 | D18: 0 | E18: 0 | F18: 0 | G18: 0 | H18: 0 | I18: 0 | J18: 415,810 | K18: =SUM(B18:J18) -> 0
A19: Total Cost to date (2025/2026) | B19: 43900 | C19: 0 | D19: 39560 | E19: 6420 | F19: 27168 | G19: 50,168 | H19: 260,000 | I19: 218,080 | J19: 599626 | K19: =SUM(B19:J19) -> 643526
A20: Comments
A21: Total Budget (2025/2026)
A24: Region 3
A25: Item | B25: NDIMA | C25: MUNUNGA | D25: KANGAITA | E25: KIMUNYE | F25: THUMAITA | G25: KATHANGARIRI | H25: MUNGANIA | I25: RUKURIRI | J25: TOTALS
A26: Recurrent costs for the month | B26: 64500 | C26: 52600 | D26: 76800 | E26: 86000 | F26: 111749.93 | G26: 57866.6 | H26: 26800 | I26: 101335.54 | J26: =SUM(B26:I26) -> 577652.07
A27: Capital costs for the month | B27: 0 | C27: 0 | D27: 2,8,000,000.00 | E27: 0 | F27: 0 | H27: 0 | I27: 0 | J27: =SUM(B27:I27) -> 0
A28: Total Cost for month | J28: =SUM(B28:I28) -> 0
A29: Recurrent to date | B29: 630000 | C29: 528000 | D29: 245500 | E29: 230660 | F29: 411592.65 | G29: 639425.77 | H29: 477.900.00 | I29: 261132.2 | J29: =SUM(B29:I29) -> 2946310.6
A30: Capital to date | D30: 2,8,000,000.00 | J30: =SUM(B30:I30) -> 0
A31: Total Cost to date 2023/2024 | J31: =SUM(B31:I31) -> 0
A32: Comments
A33: Total Budget 2024/2025 | B33: 23500000 | C33: 15000000 | D33: 13500000 | E33: 24718302 | F33: 15830000 | G33: 13500000 | H33: 15531411 | I33: 32275600 | J33: =SUM(B33:I33) -> 153855313
A35: Region 4
A36: Item/Factory | B36: Weru | C36: Kinoro | D36: Kionyo | E36: Imenti | F36: Githongo | G36: Michi | H36: Kiegoi | I36: Igembe | J36: TOTALS
A37: Recurrent costs (month) | B37: 57500 | C37: 0 | D37: 55595 | E37: 78000 | F37: 58250 | G37: 0 | H37: 62946.6 | I37: 45002 | J37: =SUM(B37:I37) -> 357293.6
A38: Capital costs (month) | B38: 0 | C38: 0 | D38: 184699 | E38: 0 | F38: 0 | G38: 0 | H38: 0 | I38: 0 | J38: =SUM(B38:I38) -> 184699
A39: Total Cost (month) | B39: 57500 | C39: 0 | D39: 240294 | E39: 78000 | F39: 58250 | G39: 0 | H39: 62946.6 | I39: 45002 | J39: =SUM(B39:I39) -> 541992.6
A40: Recurrent (To Date) | B40: 160053.89 | C40: 0 | D40: 322365.75 | E40: 156000 | F40: 133350 | G40: 225220 | H40: 142387.1 | I40: 111267.23 | J40: =SUM(B40:I40) -> 1250644
A41: Capital Costs (To Date) | B41: 0 | C41: 0 | D41: 774899 | E41: 0 | F41: 0 | G41: 0 | H41: 0 | I41: 0 | J41: =SUM(B41:I41) -> 774899
A42: Total Cost to date (2025/2026) | B42: 160053.89 | C42: 0 | D42: 1097264.8 | E42: 234000 | F42: 133350 | G42: 225220 | H42: 142387.1 | I42: 111267.23 | J42: =SUM(B42:I42) -> 2103543
A43: Comments | H43: No capital items purchased yet. | I43: No capital items purchased yet. | J43: =SUM(B43:I43) -> 0
A44: Total Budget (2025/2026) | C44: 15000000 | D44: 16679960 | E44: 15512000 | F44: 6000000 | G44: 13870000 | H44: 21680000 | I44: 21680000 | J44: =SUM(C44:I44) -> 110421960
A46: Region 5
A47: Item/Factory | B47: KAPKATET | C47: MOMUL | D47: TEGAT | E47: CHELAL | F47: TEBES | G47: LITEIN | H47: TOROR | I47: KAPSET | J47: MOGOGO | K47: MOTIGO | L47: KOBEL | M47: KAPKOROS | N47: TIRGAGA | O47: ROROK | P47: OLENGURUONE | Q47: BOITO | R47: TOTALS
A48: Recurrent costs for the Month | B48: 1350 | C48: 20000 | D48: 54000 | E48: 57000 | F48: 2700 | G48: 56500 | H48: 0 | I48: 0 | J48: 28900 | K48: 35941.96 | L48: 21000 | M48: 0 | N48: 0 | O48: 0 | P48: 22584 | Q48: 0 | R48: =SUM(B48:Q48) -> 299975.96
A49: Capital costs for the Month | B49: 0 | C49: 0 | D49: 0 | E49: 0 | F49: 0 | G49: 0 | H49: 0 | I49: 0 | J49: 0 | K49: 56079.07 | L49: 0 | M49: 0 | N49: 162400 | O49: 0 | P49: 0 | Q49: 80040 | R49: =SUM(B49:Q49) -> 298519.07
A50: Total cost for the Month | B50: 1350 | C50: 20000 | D50: 54000 | E50: 57000 | F50: 2700 | G50: 56500 | H50: 0 | I50: 0 | J50: 28900 | K50: 92021.03 | L50: 21000 | M50: 0 | N50: 162400 | O50: 0 | P50: 22584 | Q50: 80040 | R50: =SUM(B50:Q50) -> 598495.03
A51: Recurrent to date | B51: 16300 | C51: 0 | D51: 391000 | E51: 120000 | F51: 4050 | G51: 113500 | H51: 85376 | I51: 0 | J51: 67400 | K51: 428066.96 | L51: 243806 | M51: 327037.9 | N51: 5600 | O51: 0 | P51: 239117 | Q51: 121299 | R51: =SUM(B51:Q51) -> 2162552.9
A52: Capital to date | B52: 0 | C52: 20000 | D52: 0 | E52: 0 | F52: 0 | G52: 0 | H52: 8000 | I52: 0 | J52: 0 | K52: 308619.07 | L52: 0 | M52: 99000 | N52: 235480 | O52: 0 | P52: 0 | Q52: 80040 | R52: =SUM(B52:Q52) -> 751139.07
A53: Total cost to date 2025/2026 | B53: 16300 | C53: 20000 | D53: 391000 | E53: 120000 | F53: 4050 | G53: 113500 | H53: 93376 | I53: 0 | J53: 67400 | K53: 736686.03 | L53: 222806 | M53: 427037.9 | N53: 241080 | O53: 0 | P53: 239553 | Q53: 201339 | R53: =SUM(B53:Q53) -> 2894127.9
A54: Comments | R54: 0
A55: Total budget 2025/2026 | B55: 15836000 | C55: 24655000 | D55: 31572000 | E55: 32666600 | F55: 15170000 | G55: 29850000 | H55: 28052000 | I55: 8495000 | J55: 31685900 | K55: 14500000 | L55: 11305000 | M55: 23440000 | N55: 22266000 | O55: 7530000 | P55: 18000000 | Q55: 33302000 | R55: =SUM(B55:Q55) -> 348325500
A57: Region 6
A58: Item | B58: Gianchore | C58: Sanganyi | D58: Kebirigo | E58: Tombe | F58: Matunwa | G58: Nyansiongo | H58: Nyankoba | I58: Sombogo | J58: Kiamokama | K58: Mwamu | L58: Nyamache | M58: Itumbe | N58: Ogembo | O58: Eberege | P58: TOTALS
A59: Recurrent costs for the month | B59: 254420.34 | C59: 0 | D59: 71983.21 | E59: 0 | F59: 0 | G59: 0 | H59: 11400 | I59: 45172.09 | J59: 66279.4 | K59: 16000 | L59: 4182 | M59: 0 | N59: 17640.52 | O59: 12175 | P59: =SUM(B59:O59) -> 499252.56
A60: Capital costs for the month | B60: 0 | C60: 0 | D60: 0 | E60: 0 | F60: 0 | G60: 0 | H60: 0 | I60: 0 | J60: 0 | K60: 0 | L60: 0 | M60: 0 | N60: 0 | O60: 0 | P60: =SUM(B60:O60) -> 0
A61: Total Cost for month | B61: 254420.34 | C61: 0 | D61: 71983.21 | E61: 0 | F61: 0 | G61: 0 | H61: 11400 | I61: 45172.09 | J61: 66279.4 | K61: 16000 | L61: 4182 | M61: 0 | N61: 17640.52 | O61: 12175 | P61: =SUM(B61:O61) -> 499252.56
A62: Recurrent to date | B62: 308184.34 | C62: 222726.75 | D62: 168273.9 | E62: 88140 | F62: 5000 | G62: 206369.54 | H62: 171713.17 | I62: 168363.3 | J62: 299878.4 | K62: 60920 | L62: 31562 | M62: 209645.69 | N62: 112236 | O62: 40774 | P62: =SUM(B62:O62) -> 2093787.1
A63: Capital to date | B63: 0 | C63: 0 | D63: 0 | E63: 135000 | F63: 0 | G63: 0 | H63: 0 | I63: 46000 | J63: 0 | K63: 0 | L63: 0 | M63: 0 | N63: 0 | O63: 0 | P63: =SUM(B63:O63) -> 181000
A64: Total Cost to date 2025/2026 | B64: 308184.34 | C64: 222726.75 | D64: 168273.9 | E64: 223140 | F64: 5000 | G64: 206369.54 | H64: 171713.17 | I64: 214363.3 | J64: 299878.4 | K64: 60920 | L64: 31562 | M64: 209645.69 | N64: 112236 | O64: 40774 | P64: =SUM(B64:O64) -> 2274787.1
A65: Comments | B65: 0 | C65: 0 | D65: 0 | E65: 0 | F65: 0 | G65: 0 | H65: 0 | I65: 0 | J65: 0 | K65: 0 | L65: 0 | M65: 0 | N65: 0 | O65: 0 | P65: 0
A66: Total Budget 2025/2026 | B66: 0 | C66: 27710000 | D66: 0 | E66: 0 | F66: 0 | G66: 0 | H66: 4000000 | I66: 0 | J66: 10210000 | K66: 0 | L66: 0 | M66: 0 | N66: 0 | O66: 0 | P66: =SUM(B66:O66) -> 41920000
A68: Region 7
A69: Item/Factory | B69: Chebut | C69: Kapsara | D69: Kaptumo | E69: Mudete | F69: TOTALS
A70: Recurrent costs (month) | B70: 535122.58 | C70: 32120 | D70: 13753 | E70: 6500 | F70: =SUM(B70:E70) -> 587495.58
A71: Capital costs (month) | B71: 0 | C71: 163800 | D71: 0 | F71: =SUM(B71:E71) -> 163800
A72: Total Cost (month) | B72: 535122.58 | C72: 195920 | D72: 13753 | E72: 6500 | F72: =SUM(B72:E72) -> 751295.58
A73: Recurrent (To Date) | B73: 671322.58 | C73: 87960 | D73: 28719.66 | E73: 99304.9 | F73: =SUM(B73:E73) -> 887307.14
A74: Capital Costs (To Date) | B74: 119035 | C74: 163800 | D74: 0 | E74: 0 | F74: =SUM(B74:E74) -> 282835
A75: Total Cost to date (2025/2026) | B75: 790357.58 | C75: 251750 | D75: 28719.66 | E75: 99304.9 | F75: =SUM(B75:E75) -> 1170132.1
A76: Comments | B76: 0 | C76: 0 | D76: 0 | E76: 0 | F76: 0
A77: Total Budget (2025/2026) | B77: 11749000 | C77: 10941000 | D77: 12859320 | E77: 21803382 | F77: =SUM(B77:E77) -> 57352702

Sheet R1
B1: Region 1 | G1: 45838
B2: Infrastructure
A3: ='Infrastructure and Systems'!A3 -> No. | B3: Service | C3: No of Factories | D3: Region 1 | E3: % Uptime Service | F3: Factories Having Issues | G3: Summary of Issues | H3: Duration (days) | I3: Tickets Raised
A4: ='Infrastructure and Systems'!A4 -> 1 | B4: ='Infrastructure and Systems'!B4 -> Local Area Network (LAN) | C4: =COUNTA('Infrastructure and Systems'!$C$3:$N$3) -> 12 | D4: =COUNTIF('Infrastructure and Systems'!C4:N4,"No Issue Reported")+COUNTIF('Infrastructure and Systems'!C4:N4,"Partially Working")*0.7+COUNTIF('Infrastructure and Systems'!C4:N4,"Total Failure")*0.3 -> 0 | E4: =D4/C4 -> 0
A5: ='Infrastructure and Systems'!A5 -> 2 | B5: ='Infrastructure and Systems'!B5 -> Wide Area Network (WAN) | C5: =COUNTA('Infrastructure and Systems'!$C$3:$N$3) -> 12 | D5: =COUNTIF('Infrastructure and Systems'!C5:N5,"No Issue Reported")+COUNTIF('Infrastructure and Systems'!C5:N5,"Partially Working")*0.7+COUNTIF('Infrastructure and Systems'!C5:N5,"Total Failure")*0.3 -> 0 | E5: =D5/C5 -> 0
A6: ='Infrastructure and Systems'!A7 -> 4 | B6: ='Infrastructure and Systems'!B7 -> Firewall | C6: =COUNTA('Infrastructure and Systems'!$C$3:$N$3) -> 12 | D6: =COUNTIF('Infrastructure and Systems'!C7:N7,"No Issue Reported")*1+COUNTIF('Infrastructure and Systems'!C7:N7,"Partially Working")*0.7+COUNTIF('Infrastructure and Systems'!C7:N7,"Total Failure")*0.3 -> 0 | E6: =IF('Infrastructure and Systems'!C7="Internet slow even sometimes not available",(D6/C6),(D6/C6)) -> 0
A7: ='Infrastructure and Systems'!A8 -> 5 | B7: ='Infrastructure and Systems'!B8 -> E-Mail Server | C7: =COUNTA('Infrastructure and Systems'!$C$3:$N$3) -> 12 | D7: =COUNTIF('Infrastructure and Systems'!C8:N8,"Domino in use")*1+COUNTIF('Infrastructure and Systems'!C8:N8,"Exchange in Use")*0.8+COUNTIF('Infrastructure and Systems'!C8:N8,"Domino In Use-Issues")*0.6+COUNTIF('Infrastructure and Systems'!C8:N8,"Exchange In Use-Issues")*0.4+COUNTIF('Infrastructure and Systems'!C8:N8,"None")*0.2 -> 0 | E7: =D7/C7 -> 0
A8: ='Infrastructure and Systems'!A9 -> 6 | B8: ='Infrastructure and Systems'!B9 -> Business Servers (EWS, Chaipro) | C8: =COUNTA('Infrastructure and Systems'!$C$3:$N$3) -> 12 | D8: =COUNTIF('Infrastructure and Systems'!C9:N9,"No Issue Reported")+COUNTIF('Infrastructure and Systems'!C9:N9,"Partially Working")*0.7+COUNTIF('Infrastructure and Systems'!C9:N9,"Total Failure")*0.3 -> 0 | E8: =D8/C8 -> 0
A9: ='Infrastructure and Systems'!A10 -> 7 | B9: ='Infrastructure and Systems'!B10 -> Electronic Weighment Solution (EWS Version) | C9: =COUNTA('Infrastructure and Systems'!$C$3:$N$3) -> 12 | D9: =COUNTIF('Infrastructure and Systems'!C10:N10,"No Issue Reported")+COUNTIF('Infrastructure and Systems'!C10:N10,"Partially Working")*0.7+COUNTIF('Infrastructure and Systems'!C10:N10,"Total Failure")*0.3 -> 0 | E9: =D9/C9 -> 0
A10: ='Infrastructure and Systems'!#REF! -> #REF! | B10: ='Infrastructure and Systems'!#REF! -> #REF! | C10: =COUNTA('Infrastructure and Systems'!$C$3:$N$3) -> 12 | D10: =COUNTIF('Infrastructure and Systems'!#REF!,"No Issue Reported")+COUNTIF('Infrastructure and Systems'!#REF!,"Partially Working")*0.7+COUNTIF('Infrastructure and Systems'!#REF!,"Total Failure")*0.3 -> #REF! | E10: =D10/C10 -> #REF!
B11: Average | E11: =AVERAGE(E4:E10) -> #REF!
B13: ChaiPro/SAP
A14: No | B14: Service | C14: No of Factories | D14: Region 1 | E14: % Uptime Service | F14: Factories Affected | G14: Issue
A15: 1 | B15: Chaipro Financials | C15: =COUNTA('Chaipro-SAP'!$C$3:$N$3) -> 12 | D15: =COUNTIF('Chaipro-SAP'!C3:N3,"SAP Module-FICO/MM")*1+COUNTIF('Chaipro-SAP'!C3:N3,"2.5.5.7")*1+COUNTIF('Chaipro-SAP'!C3:N3,"2.5.5.8")*1+COUNTIF('Chaipro-SAP'!C3:N3,"2.5.5.9")*1+COUNTIF('Chaipro-SAP'!C3:N3,"Other version Working")*0.8+COUNTIF('Chaipro-SAP'!C3:N3,"2.5.5.7 With Issues")*0.6+COUNTIF('Chaipro-SAP'!C3:N3,"Other version With Issues")*0.4 + COUNTIF('Chaipro-SAP'!C3:N3,"None")*0.25 -> 12 | E15: =D15/C15 -> 1
A16: 2 | B16: Chaipro Factory/TVAP | C16: =COUNTA('Chaipro-SAP'!$C$3:$N$3) -> 12 | D16: =COUNTIF('Chaipro-SAP'!C4:N4,"SAP Module-PP/PM")*1+COUNTIF('Chaipro-SAP'!C4:N4,"2.5.2.5")*1+COUNTIF('Chaipro-SAP'!C4:N4,"2.5.2.7")*1+COUNTIF('Chaipro-SAP'!C4:N4,"Other version Working")*0.8+COUNTIF('Chaipro-SAP'!C4:N4,"2.5.2.5 With Issues")*0.6+COUNTIF('Chaipro-SAP'!C4:N4,"Other version With Issues")*0.4 + COUNTIF('Chaipro-SAP'!C4:N4,"None")*0.25 -> 12 | E16: =D16/C16 -> 1
A17: 3 | B17: Chaipro Farmers | C17: =COUNTA('Chaipro-SAP'!$C$3:$N$3) -> 12 | D17: =COUNTIF('Chaipro-SAP'!C5:N5,"2.8.0.0")*1+COUNTIF('Chaipro-SAP'!C5:N5,"Other version Working")*0.8+COUNTIF('Chaipro-SAP'!C5:N5,"2.8.0.0 With Issues")*0.6+COUNTIF('Chaipro-SAP'!C5:N5,"Other version With Issues")*0.4 + COUNTIF('Chaipro-SAP'!C5:N5,"None")*0.25 -> 12 | E17: =D17/C17 -> 1
A18: 4 | B18: Chaipro Fleet | C18: =COUNTA('Chaipro-SAP'!$C$3:$N$3) -> 12 | D18: =COUNTIF('Chaipro-SAP'!C6:N6,"3.2.5.1")*1+COUNTIF('Chaipro-SAP'!C6:N6,"Other version Working")*0.8+COUNTIF('Chaipro-SAP'!C6:N6,"3.2.5.1 With Issues")*0.6+COUNTIF('Chaipro-SAP'!C6:N6,"Other version With Issues")*0.4 + COUNTIF('Chaipro-SAP'!C6:N6,"None")*0.25 -> 12 | E18: =D18/C18 -> 1
A19: 6 | B19: KTDA Replicator | C19: =COUNTA('Chaipro-SAP'!$C$3:$N$3) -> 12 | D19: =COUNTIF('Chaipro-SAP'!C7:N7,"Working")*1+COUNTIF('Chaipro-SAP'!C7:N7,"Version 10 fully operational ")*1+COUNTIF('Chaipro-SAP'!C7:N7,"Working With Issues")*0.5 -> 12 | E19: =D19/C19 -> 1
A20: 7 | B20: Chai Data | C20: =COUNTA('Chaipro-SAP'!$C$3:$N$3) -> 12 | D20: =COUNTIF('Chaipro-SAP'!C8:N8,"1.0.0.3")*1+COUNTIF('Chaipro-SAP'!C8:N8,"Other version Working")*0.8+COUNTIF('Chaipro-SAP'!C8:N8,"1.0.0.3 With Issues")*0.6+COUNTIF('Chaipro-SAP'!C8:N8,"Other version With Issues")*0.4 + COUNTIF('Chaipro-SAP'!C8:N8,"None")*0.25 -> 12 | E20: =D20/C20 -> 1
A21: 8 | B21: Chai POS | C21: =COUNTA('Chaipro-SAP'!$C$3:$N$3) -> 12 | D21: =COUNTIF('Chaipro-SAP'!C9:N9,"2.2")*1+COUNTIF('Chaipro-SAP'!C9:N9,"Other version Working")*0.8+COUNTIF('Chaipro-SAP'!C9:N9,"2.2 With Issues")*0.6+COUNTIF('Chaipro-SAP'!C9:N9,"Other version With Issues")*0.4 + COUNTIF('Chaipro-SAP'!C9:N9,"None")*0.25 -> 0 | E21: =D21/C21 -> 0
B22: Average | E22: =AVERAGE(E15:E21) -> 0.85714286
B24: Inventory
A25: No | B25: Service | C25: No of Factories | D25: Region 1 | E25: % Uptime Service | F25: Factories Affected | G25: Issue
A26: 1 | B26: Network Equipments (e.g. Switch, 2, Functional, any additional details) | C26: =COUNTA('ICT Inventory'!#REF!) -> 1 | D26: =COUNTIF('ICT Inventory'!#REF!,"No Issue Reported")+COUNTIF('ICT Inventory'!#REF!,"Partially Working")*0.7+COUNTIF('ICT Inventory'!#REF!,"Total Failure")*0.3 -> #REF! | E26: =D26/C26 -> #REF!
A27: 2 | B27: Software (e.g. third party software) etc | C27: =COUNTA('ICT Inventory'!#REF!) -> 1 | D27: =COUNTIF('ICT Inventory'!#REF!,"No Issue Reported")+COUNTIF('ICT Inventory'!#REF!,"Partially Working")*0.7+COUNTIF('ICT Inventory'!#REF!,"Total Failure")*0.3 -> #REF! | E27: =D27/C27 -> #REF!
A28: 3 | B28: Hardware (e.g. Servers, PCs, Laptops, UPS, DAs, Printers, Scanners, ESD, Fiscal Printers, Tablets) | C28: =COUNTA('ICT Inventory'!#REF!) -> 1 | D28: =COUNTIF('ICT Inventory'!#REF!,"No Issue Reported")+COUNTIF('ICT Inventory'!#REF!,"Partially Working")*0.7+COUNTIF('ICT Inventory'!#REF!,"Total Failure")*0.3 -> #REF! | E28: =D28/C28 -> #REF!
A29: 4 | B29: Other Equipment (please specify) | C29: =IF('ICT Inventory'!#REF!<>"N/A",COUNTA('ICT Inventory'!#REF!)) -> #REF! | D29: =COUNTIF('ICT Inventory'!#REF!,"No Issue Reported")*1+COUNTIF('ICT Inventory'!#REF!,"WIFI & CCTV Installed")*1+COUNTIF('ICT Inventory'!#REF!,"Partially Working")*0.7+COUNTIF('ICT Inventory'!#REF!,"Total Failure")*0.3 -> #REF! | E29: =D29/C29 -> #REF!
B30: Average | E30: =AVERAGE(E26:E29) -> #REF!
B32: BCP
A33: No | B33: Service | C33: No of Factories | D33: Region 1 | E33: % Uptime Service | F33: Factories Affected | G33: Issue
A34: 1 | B34: Business Continuity Mechanism e.g. Backups | C34: =IF(BCP!#REF!<>"N/A",COUNTA(BCP!#REF!)) -> #REF! | D34: =COUNTIF(BCP!#REF!,"Offsite & Schedule backups in place") -> #REF! | E34: =D34/C34 -> #REF!
B35: Average | E35: =AVERAGE(E34) -> #REF!
B38: PURCHASES
A39: No | B39: Service | C39: No of Factories | D39: Total Cost | E39: Total Budget | F39: Factories Affected | G39: Issue
A40: 1 | B40: Purchases | C40: =COUNTA('ICT Cost'!$B$2:$L$2) -> 11 | D40: ='ICT Cost'!N8 -> 6945720.9
B41: Average

Sheet R2
B1: Region 2 | F1: 45838
B2: Infrastructure
A3: ='Infrastructure and Systems'!A3 -> No. | B3: Service | C3: No of Factories | D3: Region 2 | E3: % Uptime Service | F3: Factories Having Issues | G3: Summary of Issues | H3: Duration (days) | I3: Tickets Raised
A4: ='Infrastructure and Systems'!A4 -> 1 | B4: ='Infrastructure and Systems'!B4 -> Local Area Network (LAN) | C4: =COUNTA('Infrastructure and Systems'!$C$20:$K$20) -> 9 | D4: =COUNTIF('Infrastructure and Systems'!C21:K21,"No Issue Reported")+COUNTIF('Infrastructure and Systems'!C21:K21,"Partially Working")*0.7+COUNTIF('Infrastructure and Systems'!C21:K21,"Total Failure")*0.3 -> 9 | E4: =D4/C4 -> 1
A5: ='Infrastructure and Systems'!A5 -> 2 | B5: ='Infrastructure and Systems'!B5 -> Wide Area Network (WAN) | C5: =COUNTA('Infrastructure and Systems'!$C$20:$K$20) -> 9 | D5: =COUNTIF('Infrastructure and Systems'!C22:K22,"No Issue Reported")+COUNTIF('Infrastructure and Systems'!C22:K22,"Partially Working")*0.7+COUNTIF('Infrastructure and Systems'!C22:K22,"Total Failure")*0.3 -> 9 | E5: =D5/C5 -> 1
A6: ='Infrastructure and Systems'!A7 -> 4 | B6: ='Infrastructure and Systems'!B7 -> Firewall | C6: =COUNTA('Infrastructure and Systems'!$C$20:$K$20) -> 9 | D6: =COUNTIF('Infrastructure and Systems'!C23:K23,"No Issue Reported")+COUNTIF('Infrastructure and Systems'!C23:K23,"Partially Working")*0.7+COUNTIF('Infrastructure and Systems'!C23:K23,"Total Failure")*0.3 -> 9 | E6: =IF('Infrastructure and Systems'!C7="Internet slow even sometimes not available",(D6/C6)/2,(D6/C6)) -> 1
A7: ='Infrastructure and Systems'!A8 -> 5 | B7: ='Infrastructure and Systems'!B8 -> E-Mail Server | C7: =COUNTA('Infrastructure and Systems'!$C$20:$K$20) -> 9 | D7: =COUNTIF('Infrastructure and Systems'!C24:K24,"Domino in use")*1+COUNTIF('Infrastructure and Systems'!C24:K24,"Exchange in Use")*0.8+COUNTIF('Infrastructure and Systems'!C24:K24,"Domino In Use-Issues")*0.6+COUNTIF('Infrastructure and Systems'!C24:K24,"Exchange In Use-Issues")*0.4+COUNTIF('Infrastructure and Systems'!C24:K24,"None")*0.2 -> 9 | E7: =D7/C7 -> 1
A8: ='Infrastructure and Systems'!A9 -> 6 | B8: ='Infrastructure and Systems'!B9 -> Business Servers (EWS, Chaipro) | C8: =COUNTA('Infrastructure and Systems'!$C$20:$K$20) -> 9 | D8: =COUNTIF('Infrastructure and Systems'!C25:K25,"No Issue Reported")+COUNTIF('Infrastructure and Systems'!C25:K25,"Partially Working")*0.7+COUNTIF('Infrastructure and Systems'!C25:K25,"Total Failure")*0.3 -> 9 | E8: =D8/C8 -> 1
A9: ='Infrastructure and Systems'!A10 -> 7 | B9: ='Infrastructure and Systems'!B10 -> Electronic Weighment Solution (EWS Version) | C9: =COUNTA('Infrastructure and Systems'!$C$20:$K$20) -> 9 | D9: =COUNTIF('Infrastructure and Systems'!C26:K26,"No Issue Reported")+COUNTIF('Infrastructure and Systems'!C26:K26,"Partially Working")*0.7+COUNTIF('Infrastructure and Systems'!C26:K26,"Total Failure")*0.3 -> 9 | E9: =D9/C9 -> 1
A10: ='Infrastructure and Systems'!#REF! -> #REF! | B10: ='Infrastructure and Systems'!#REF! -> #REF! | C10: =COUNTA('Infrastructure and Systems'!$C$20:$K$20) -> 9 | D10: =COUNTIF('Infrastructure and Systems'!C27:K27,"No Issue Reported")+COUNTIF('Infrastructure and Systems'!C27:K27,"Partially Working")*0.7+COUNTIF('Infrastructure and Systems'!C27:K27,"Total Failure")*0.3 -> 9 | E10: =D10/C10 -> 1
B11: Average | E11: =AVERAGE(E4:E10) -> 1
B13: ChaiPro
A14: No | B14: Service | C14: No of Factories | D14: Region 2 | E14: % Uptime Service | F14: Factories Affected | G14: Issue
A15: 1 | B15: Chaipro Financials | C15: =COUNTA('Infrastructure and Systems'!$C$20:$K$20) -> 9 | D15: =COUNTIF('Chaipro-SAP'!#REF!,"SAP")*1+COUNTIF('Chaipro-SAP'!#REF!,"2.5.5.7")*1+COUNTIF('Chaipro-SAP'!#REF!,"Other version Working")*0.8+COUNTIF('Chaipro-SAP'!#REF!,"2.5.5.7 With Issues")*0.6+COUNTIF('Chaipro-SAP'!#REF!,"Other version With Issues")*0.4 + COUNTIF('Chaipro-SAP'!C3:N3,"None")*0.25 -> #REF! | E15: =D15/C15 -> #REF!
A16: 2 | B16: Chaipro Factory/TVAP | C16: =COUNTA('Infrastructure and Systems'!$C$20:$K$20) -> 9 | D16: =COUNTIF('Chaipro-SAP'!#REF!,"SAP")*1+COUNTIF('Chaipro-SAP'!#REF!,"2.5.5.7")*1+COUNTIF('Chaipro-SAP'!#REF!,"Other version Working")*0.8+COUNTIF('Chaipro-SAP'!#REF!,"2.5.5.7 With Issues")*0.6+COUNTIF('Chaipro-SAP'!#REF!,"Other version With Issues")*0.4 + COUNTIF('Chaipro-SAP'!C4:N4,"None")*0.25 -> #REF! | E16: =D16/C16 -> #REF!
A17: 3 | B17: Chaipro Farmers | C17: =COUNTA('Infrastructure and Systems'!$C$20:$K$20) -> 9 | D17: =COUNTIF('Chaipro-SAP'!#REF!,"2.8.0.0")*1+COUNTIF('Chaipro-SAP'!#REF!,"Other version Working")*0.8+COUNTIF('Chaipro-SAP'!#REF!,"2.8.0.0 With Issues")*0.6+COUNTIF('Chaipro-SAP'!#REF!,"Other version With Issues")*0.4 + COUNTIF('Chaipro-SAP'!C5:N5,"None")*0.25 -> #REF! | E17: =D17/C17 -> #REF!
A18: 4 | B18: Chaipro Fleet | C18: =COUNTA('Infrastructure and Systems'!$C$20:$K$20) -> 9 | D18: =COUNTIF('Chaipro-SAP'!#REF!,"3.2.5.1")*1+COUNTIF('Chaipro-SAP'!#REF!,"Other version Working")*0.8+COUNTIF('Chaipro-SAP'!#REF!,"3.2.5.1 With Issues")*0.6+COUNTIF('Chaipro-SAP'!#REF!,"Other version With Issues")*0.4 + COUNTIF('Chaipro-SAP'!#REF!,"None")*0.25 -> #REF! | E18: =D18/C18 -> #REF!
A19: 6 | B19: KTDA Replicator | C19: =COUNTA('Infrastructure and Systems'!$C$20:$K$20) -> 9 | D19: =COUNTIF('Chaipro-SAP'!#REF!,"Working")*1+COUNTIF('Chaipro-SAP'!#REF!,"Working With Issues")*0.5 -> #REF! | E19: =D19/C19 -> #REF!
A20: 7 | B20: Chai Data | C20: =COUNTA('Infrastructure and Systems'!$C$20:$K$20) -> 9 | D20: =COUNTIF('Chaipro-SAP'!#REF!,"1.0.0.3")*1+COUNTIF('Chaipro-SAP'!#REF!,"Other version Working")*0.8+COUNTIF('Chaipro-SAP'!#REF!,"1.0.0.3 With Issues")*0.6+COUNTIF('Chaipro-SAP'!#REF!,"Other version With Issues")*0.4 + COUNTIF('Chaipro-SAP'!B8:L8,"None")*0.25 -> #REF! | E20: =D20/C20 -> #REF!
A21: 8 | B21: Chai POS | C21: =COUNTA('Infrastructure and Systems'!$C$20:$K$20) -> 9 | D21: =COUNTIF('Chaipro-SAP'!#REF!,"2.2")*1+COUNTIF('Chaipro-SAP'!#REF!,"Other version Working")*0.8+COUNTIF('Chaipro-SAP'!#REF!,"2.2 With Issues")*0.6+COUNTIF('Chaipro-SAP'!#REF!,"Other version With Issues")*0.4 + COUNTIF('Chaipro-SAP'!#REF!,"None")*0.25 -> #REF! | E21: =D21/C21 -> #REF!
B22: Average | E22: =AVERAGE(E15:E21) -> #REF!
B24: Inventory
A25: No | B25: Service | C25: No of Factories | D25: Region 2 | E25: % Uptime Service | F25: Factories Affected | G25: Issue
A26: 1 | B26: Network Equipments (e.g. Switch, 2, Functional, any additional details) | C26: =COUNTA('Infrastructure and Systems'!$C$20:$K$20) -> 9 | D26: =COUNTIF('ICT Inventory'!#REF!,"No Issue Reported")+COUNTIF('ICT Inventory'!#REF!,"Partially Working")*0.7+COUNTIF('ICT Inventory'!#REF!,"Total Failure")*0.3 -> #REF! | E26: =D26/C26 -> #REF!
A27: 2 | B27: Software (e.g. third party software) etc | C27: =COUNTA('Infrastructure and Systems'!$C$20:$K$20) -> 9 | D27: =COUNTIF('ICT Inventory'!#REF!,"No Issue Reported")+COUNTIF('ICT Inventory'!#REF!,"Partially Working")*0.7+COUNTIF('ICT Inventory'!#REF!,"Total Failure")*0.3 -> #REF! | E27: =D27/C27 -> #REF!
A28: 3 | B28: Hardware (e.g. Servers, PCs, Laptops, UPS, DAs, Printers, Scanners, ESD, Fiscal Printers, Tablets) | C28: =COUNTA('Infrastructure and Systems'!$C$20:$K$20) -> 9 | D28: =COUNTIF('ICT Inventory'!#REF!,"No Issue Reported")+COUNTIF('ICT Inventory'!#REF!,"Partially Working")*0.7+COUNTIF('ICT Inventory'!#REF!,"Total Failure")*0.3 -> #REF! | E28: =D28/C28 -> #REF!
A29: 4 | B29: Other Equipment (please specify) | C29: =COUNTA('Infrastructure and Systems'!$C$20:$K$20) -> 9 | D29: =COUNTIF('ICT Inventory'!#REF!,"No Issue Reported")+COUNTIF('ICT Inventory'!#REF!,"Partially Working")*0.7+COUNTIF('ICT Inventory'!#REF!,"Total Failure")*0.3 -> #REF! | E29: =D29/C29 -> #REF!
B30: Average | E30: =AVERAGE(E26:E29) -> #REF!
B32: BCP
A33: No | B33: Service | C33: No of Factories | D33: Region 2 | E33: % Uptime Service | F33: Factories Affected | G33: Issue
A34: 1 | B34: Business Continuity Mechanism e.g. Backups | C34: =COUNTA(BCP!#REF!) -> 1 | D34: =COUNTA(BCP!#REF!) -> 1 | E34: =D34/C34 -> 1
B35: Average | E35: =AVERAGE(E34) -> 1
B38: PURCHASES
A39: No | B39: Service | C39: No of Factories | D39: Total Cost | E39: Cost vs budget | F39: Factories Affected | G39: Issue
A40: 1 | B40: Purchases | C40: =COUNTA('ICT Cost'!$B$13:$J$13) -> 9 | D40: ='ICT Cost'!J18 -> 415,810
B41: Average

Sheet R3
B1: Region 3
B2: Infrastructure
A3: ='Infrastructure and Systems'!A3 -> No. | B3: Service | C3: No of Factories | D3: Region 3 | E3: % Uptime Service | F3: Factories Having Issues | G3: Summary of Issues | H3: Duration (days) | I3: Tickets Raised
A4: ='Infrastructure and Systems'!A4 -> 1 | B4: ='Infrastructure and Systems'!B4 -> Local Area Network (LAN) | C4: =COUNTA('Infrastructure and Systems'!$C$37:$J$37) -> 8 | D4: =COUNTIF('Infrastructure and Systems'!#REF!,"No Issue Reported")+COUNTIF('Infrastructure and Systems'!#REF!,"Partially Working")*0.7+COUNTIF('Infrastructure and Systems'!#REF!,"Total Failure")*0.3 -> #REF! | E4: =D4/C4 -> #REF!
A5: ='Infrastructure and Systems'!A5 -> 2 | B5: ='Infrastructure and Systems'!B5 -> Wide Area Network (WAN) | C5: =COUNTA('Infrastructure and Systems'!$C$37:$J$37) -> 8 | D5: =COUNTIF('Infrastructure and Systems'!C38:J38,"No Issue Reported")+COUNTIF('Infrastructure and Systems'!C38:J38,"Partially Working")*0.7+COUNTIF('Infrastructure and Systems'!C38:J38,"Total Failure")*0.3 -> 0 | E5: =D5/C5 -> 0
A6: ='Infrastructure and Systems'!A7 -> 4 | B6: ='Infrastructure and Systems'!B7 -> Firewall | C6: =COUNTA('Infrastructure and Systems'!$C$37:$J$37) -> 8 | D6: =COUNTIF('Infrastructure and Systems'!C39:J39,"No Issue Reported")+COUNTIF('Infrastructure and Systems'!C39:J39,"Partially Working")*0.7+COUNTIF('Infrastructure and Systems'!C39:J39,"Total Failure")*0.3 -> 0 | E6: =IF('Infrastructure and Systems'!C7="Internet slow even sometimes not available",(D6/C6)/2,(D6/C6)) -> 0
A7: ='Infrastructure and Systems'!A8 -> 5 | B7: ='Infrastructure and Systems'!B8 -> E-Mail Server | C7: =COUNTA('Infrastructure and Systems'!$C$37:$J$37) -> 8 | D7: =COUNTIF('Infrastructure and Systems'!C40:J40,"Domino in use")*1+COUNTIF('Infrastructure and Systems'!C40:J40,"Exchange in Use")*0.8+COUNTIF('Infrastructure and Systems'!C40:J40,"Domino In Use-Issues")*0.6+COUNTIF('Infrastructure and Systems'!C24:K24,"Exchange In Use-Issues")*0.4+COUNTIF('Infrastructure and Systems'!C24:K24,"None")*0.2 -> 0 | E7: =D7/C7 -> 0
A8: ='Infrastructure and Systems'!A9 -> 6 | B8: ='Infrastructure and Systems'!B9 -> Business Servers (EWS, Chaipro) | C8: =COUNTA('Infrastructure and Systems'!$C$37:$J$37) -> 8 | D8: =COUNTIF('Infrastructure and Systems'!C41:J41,"No Issue Reported")+COUNTIF('Infrastructure and Systems'!C41:J41,"Partially Working")*0.7+COUNTIF('Infrastructure and Systems'!C41:J41,"Total Failure")*0.3 -> 0 | E8: =D8/C8 -> 0
A9: ='Infrastructure and Systems'!A10 -> 7 | B9: ='Infrastructure and Systems'!B10 -> Electronic Weighment Solution (EWS Version) | C9: =COUNTA('Infrastructure and Systems'!$C$37:$J$37) -> 8 | D9: =COUNTIF('Infrastructure and Systems'!C42:J42,"No Issue Reported")+COUNTIF('Infrastructure and Systems'!C42:J42,"Partially Working")*0.7+COUNTIF('Infrastructure and Systems'!C42:J42,"Total Failure")*0.3 -> 0 | E9: =D9/C9 -> 0
A10: ='Infrastructure and Systems'!#REF! -> #REF! | B10: ='Infrastructure and Systems'!#REF! -> #REF! | C10: =COUNTA('Infrastructure and Systems'!$C$37:$J$37) -> 8 | D10: =COUNTIF('Infrastructure and Systems'!C43:J43,"No Issue Reported")+COUNTIF('Infrastructure and Systems'!C43:J43,"Partially Working")*0.7+COUNTIF('Infrastructure and Systems'!C43:J43,"Total Failure")*0.3 -> 0 | E10: =D10/C10 -> 0
B11: Average | E11: =AVERAGE(E4:E10) -> #REF!
B13: ChaiPro
A14: No | B14: Service | C14: No of Factories | D14: Region 3 | E14: % Uptime Service | F14: Factories Affected | G14: Issue
A15: 1 | B15: Chaipro Financials | C15: =COUNTA('Infrastructure and Systems'!$C$37:$J$37) -> 8 | D15: =COUNTIF('Chaipro-SAP'!C28:J28,"2.5.5.7")*1+COUNTIF('Chaipro-SAP'!C28:J28,"2.5.5.8")*1+COUNTIF('Chaipro-SAP'!C28:J28,"2.5.5.9")*1+COUNTIF('Chaipro-SAP'!C28:J28,"2.5.6.0")*1+COUNTIF('Chaipro-SAP'!C28:J28,"SAP")*1+COUNTIF('Chaipro-SAP'!C28:J28,"Other version Working")*0.8+COUNTIF('Chaipro-SAP'!C28:J28,"2.5.5.7 With Issues")*0.6+COUNTIF('Chaipro-SAP'!C28:J28,"Other version With Issues")*0.4 + COUNTIF('Chaipro-SAP'!C28:J28,"None")*0.25 -> 2 | E15: =D15/C15 -> 0.25
A16: 2 | B16: Chaipro Factory/TVAP | C16: =COUNTA('Infrastructure and Systems'!$C$37:$J$37) -> 8 | D16: =COUNTIF('Chaipro-SAP'!C29:J29,"2.5.2.5")*1+COUNTIF('Chaipro-SAP'!C29:J29,"2.5.2.7")*1+COUNTIF('Chaipro-SAP'!C29:J29,"SAP")*1+COUNTIF('Chaipro-SAP'!C29:J29,"Other version Working")*0.8+COUNTIF('Chaipro-SAP'!C29:J29,"2.5.2.5 With Issues")*0.6+COUNTIF('Chaipro-SAP'!C29:J29,"Other version With Issues")*0.4 + COUNTIF('Chaipro-SAP'!C29:J29,"None")*0.25 -> 2 | E16: =D16/C16 -> 0.25
A17: 3 | B17: Chaipro Farmers | C17: =COUNTA('Infrastructure and Systems'!$C$37:$J$37) -> 8 | D17: =COUNTIF('Chaipro-SAP'!C30:J30,"3.0.0.1")*1+COUNTIF('Chaipro-SAP'!C30:J30,"2.8.0.0")*1+COUNTIF('Chaipro-SAP'!C30:J30,"Other version Working")*0.8+COUNTIF('Chaipro-SAP'!C30:J30,"2.8.0.0 With Issues")*0.6+COUNTIF('Chaipro-SAP'!C30:J30,"Other version With Issues")*0.4 + COUNTIF('Chaipro-SAP'!C30:J30,"None")*0.25 -> 2 | E17: =D17/C17 -> 0.25
A18: 4 | B18: Chaipro Fleet | C18: =COUNTA('Infrastructure and Systems'!$C$37:$J$37) -> 8 | D18: =COUNTIF('Chaipro-SAP'!C31:J31,"3.2.5.1")*1+COUNTIF('Chaipro-SAP'!C31:J31,"Other version Working")*0.8+COUNTIF('Chaipro-SAP'!C31:J31,"3.2.5.1 With Issues")*0.6+COUNTIF('Chaipro-SAP'!C31:J31,"Other version With Issues")*0.4 + COUNTIF('Chaipro-SAP'!C31:J31,"None")*0.25 -> 2 | E18: =D18/C18 -> 0.25
A19: 6 | B19: KTDA Replicator | C19: =COUNTA('Infrastructure and Systems'!$C$37:$J$37) -> 8 | D19: =COUNTIF('Chaipro-SAP'!C32:J32,"Working")*1+COUNTIF('Chaipro-SAP'!C32:J32,"Working With Issues")*0.5 -> 0 | E19: =D19/C19 -> 0
A20: 7 | B20: Chai Data | C20: =COUNTA('Infrastructure and Systems'!$C$37:$J$37) -> 8 | D20: =COUNTIF('Chaipro-SAP'!C33:J33,"1.0.0.3")*1+COUNTIF('Chaipro-SAP'!C33:J33,"Other version Working")*0.8+COUNTIF('Chaipro-SAP'!C22:J33,"1.0.0.3 With Issues")*0.6+COUNTIF('Chaipro-SAP'!C33:J33,"Other version With Issues")*0.4 + COUNTIF('Chaipro-SAP'!B8:L8,"None")*0.25 -> 0 | E20: =D20/C20 -> 0
A21: 8 | B21: Chai POS | C21: =COUNTA('Infrastructure and Systems'!$C$37:$J$37) -> 8 | D21: =COUNTIF('Chaipro-SAP'!#REF!,"2.2")*1+COUNTIF('Chaipro-SAP'!#REF!,"Other version Working")*0.8+COUNTIF('Chaipro-SAP'!#REF!,"2.2 With Issues")*0.6+COUNTIF('Chaipro-SAP'!#REF!,"Other version With Issues")*0.4 + COUNTIF('Chaipro-SAP'!#REF!,"None")*0.25 -> #REF! | E21: =D21/C21 -> #REF!
B22: Average | E22: =AVERAGE(E15:E21) -> #REF!
B24: Inventory
A25: No | B25: Service | C25: No of Factories | D25: Region 3 | E25: % Uptime Service | F25: Factories Affected | G25: Issue
A26: 1 | B26: Network Equipments (e.g. Switch, 2, Functional, any additional details) | C26: =COUNTA('Infrastructure and Systems'!$C$37:$J$37) -> 8 | D26: =COUNTIF('ICT Inventory'!#REF!,"No Issue Reported")+COUNTIF('ICT Inventory'!#REF!,"Partially Working")*0.7+COUNTIF('ICT Inventory'!#REF!,"Total Failure")*0.3 -> #REF! | E26: =D26/C26 -> #REF!
A27: 2 | B27: Software (e.g. third party software) etc | C27: =COUNTA('Infrastructure and Systems'!$C$37:$J$37) -> 8 | D27: =COUNTIF('ICT Inventory'!#REF!,"No Issue Reported")+COUNTIF('ICT Inventory'!#REF!,"Partially Working")*0.7+COUNTIF('ICT Inventory'!#REF!,"Total Failure")*0.3 -> #REF! | E27: =D27/C27 -> #REF!
A28: 3 | B28: Hardware (e.g. Servers, PCs, Laptops, UPS, DAs, Printers, Scanners, ESD, Fiscal Printers, Tablets) | C28: =COUNTA('Infrastructure and Systems'!$C$37:$J$37) -> 8 | D28: =COUNTIF('ICT Inventory'!#REF!,"No Issue Reported")+COUNTIF('ICT Inventory'!#REF!,"Partially Working")*0.7+COUNTIF('ICT Inventory'!#REF!,"Total Failure")*0.3 -> #REF! | E28: =D28/C28 -> #REF!
A29: 4 | B29: Other Equipment (please specify) | C29: =COUNTA('Infrastructure and Systems'!$C$37:$J$37) -> 8 | D29: =COUNTIF('ICT Inventory'!#REF!,"No Issue Reported")+COUNTIF('ICT Inventory'!#REF!,"Partially Working")*0.7+COUNTIF('ICT Inventory'!#REF!,"Total Failure")*0.3 -> #REF! | E29: =D29/C29 -> #REF!
B30: Average | E30: =AVERAGE(E26:E29) -> #REF!
B32: BCP
A33: No | B33: Service | C33: No of Factories | D33: Region 3 | E33: % Uptime Service | F33: Factories Affected | G33: Issue
A34: 1 | B34: Business Continuity Mechanism e.g. Backups | C34: =COUNTA('Infrastructure and Systems'!$C$37:$J$37) -> 8 | D34: =COUNTIF(BCP!#REF!,"Offsite & Schedule backups in place") -> #REF! | E34: =D34/C34 -> #REF! | F34: =IF(E34=100%,"None") -> #REF!
B35: Average | E35: =AVERAGE(E34) -> #REF!
B38: PURCHASES
A39: No | B39: Service | C39: No of Factories | D39: Total Cost | E39: Cost vs budget | F39: Factories Affected | G39: Issue
A40: 1 | B40: Purchases | C40: =COUNTA('ICT Cost'!#REF!) -> 1 | D40: ='ICT Cost'!J30 -> 0
B41: Average

Sheet R4
B1: Region 4
B2: Infrastructure
A3: ='Infrastructure and Systems'!A3 -> No. | B3: Service | C3: No of Factories | D3: Region 4 | E3: % Uptime Service | F3: Factories Having Issues | G3: Summary of Issues | H3: Duration (days) | I3: Tickets Raised
A4: ='Infrastructure and Systems'!A4 -> 1 | B4: ='Infrastructure and Systems'!B4 -> Local Area Network (LAN) | C4: =COUNTA('Infrastructure and Systems'!$C$54:$J$54) -> 8 | D4: =COUNTIF('Infrastructure and Systems'!C55:J55,"No Issue Reported")+COUNTIF('Infrastructure and Systems'!C55:J55,"Partially Working")*0.7+COUNTIF('Infrastructure and Systems'!C55:J55,"Total Failure")*0.3 -> 0 | E4: =D4/C4 -> 0
A5: ='Infrastructure and Systems'!A5 -> 2 | B5: ='Infrastructure and Systems'!B5 -> Wide Area Network (WAN) | C5: =COUNTA('Infrastructure and Systems'!$C$54:$J$54) -> 8 | D5: =COUNTIF('Infrastructure and Systems'!C56:J56,"No Issue Reported")+COUNTIF('Infrastructure and Systems'!C56:J56,"Partially Working")*0.7+COUNTIF('Infrastructure and Systems'!C56:J56,"Total Failure")*0.3 -> 0 | E5: =D5/C5 -> 0
A6: ='Infrastructure and Systems'!A7 -> 4 | B6: ='Infrastructure and Systems'!B7 -> Firewall | C6: =COUNTA('Infrastructure and Systems'!$C$54:$J$54) -> 8 | D6: =COUNTIF('Infrastructure and Systems'!C57:J57,"No Issue Reported")+COUNTIF('Infrastructure and Systems'!C57:J57,"Partially Working")*0.7+COUNTIF('Infrastructure and Systems'!C57:J57,"Total Failure")*0.3 -> 0 | E6: =IF('Infrastructure and Systems'!C7="Internet slow even sometimes not available",(D6/C6)/2,(D6/C6)) -> 0
A7: ='Infrastructure and Systems'!A8 -> 5 | B7: ='Infrastructure and Systems'!B8 -> E-Mail Server | C7: =COUNTA('Infrastructure and Systems'!$C$54:$J$54) -> 8 | D7: =COUNTIF('Infrastructure and Systems'!C58:J58,"Domino in use")*1+COUNTIF('Infrastructure and Systems'!C58:J58,"Exchange in Use")*0.8+COUNTIF('Infrastructure and Systems'!C58:J58,"Domino In Use-Issues")*0.6+COUNTIF('Infrastructure and Systems'!C58:J58,"Exchange In Use-Issues")*0.4+COUNTIF('Infrastructure and Systems'!C58:J58,"None")*0.2 -> 0 | E7: =(D27/C7) -> #REF!
A8: ='Infrastructure and Systems'!A9 -> 6 | B8: ='Infrastructure and Systems'!B9 -> Business Servers (EWS, Chaipro) | C8: =COUNTA('Infrastructure and Systems'!$C$54:$J$54) -> 8 | D8: =COUNTIF('Infrastructure and Systems'!C59:J59,"No Issue Reported")+COUNTIF('Infrastructure and Systems'!C59:J59,"Partially Working")*0.7+COUNTIF('Infrastructure and Systems'!C59:J59,"Total Failure")*0.3 -> 0 | E8: =D8/C8 -> 0
A9: ='Infrastructure and Systems'!A10 -> 7 | B9: ='Infrastructure and Systems'!B10 -> Electronic Weighment Solution (EWS Version) | C9: =COUNTA('Infrastructure and Systems'!$C$54:$J$54) -> 8 | D9: =COUNTIF('Infrastructure and Systems'!C60:J60,"No Issue Reported")+COUNTIF('Infrastructure and Systems'!C60:J60,"Partially Working")*0.7+COUNTIF('Infrastructure and Systems'!C60:J60,"Total Failure")*0.3 -> 0 | E9: =D9/C9 -> 0
A10: ='Infrastructure and Systems'!#REF! -> #REF! | B10: ='Infrastructure and Systems'!#REF! -> #REF! | C10: =COUNTA('Infrastructure and Systems'!$C$54:$J$54) -> 8 | D10: =COUNTIF('Infrastructure and Systems'!C61:J61,"No Issue Reported")+COUNTIF('Infrastructure and Systems'!C61:J61,"Partially Working")*0.7+COUNTIF('Infrastructure and Systems'!C61:J61,"Total Failure")*0.3 -> 0 | E10: =D10/C10 -> 0
B11: Average | E11: =AVERAGE(E4:E10) -> #REF!
B13: ChaiPro
A14: No | B14: Service | C14: No of Factories | D14: Region 4 | E14: % Uptime Service | F14: Factories Affected | G14: Issue
A15: 1 | B15: Chaipro Financials | C15: =COUNTA('Infrastructure and Systems'!$C$54:$J$54) -> 8 | D15: =COUNTIF('Chaipro-SAP'!#REF!,"2.5.5.9")*1+COUNTIF('Chaipro-SAP'!#REF!,"SAP")*1+COUNTIF('Chaipro-SAP'!D28:J28,"Other version Working")*0.8+COUNTIF('Chaipro-SAP'!#REF!,"2.5.5.7 With Issues")*0.6+COUNTIF('Chaipro-SAP'!#REF!,"Other version With Issues")*0.4 + COUNTIF('Chaipro-SAP'!#REF!,"None")*0.25 -> #REF! | E15: =D15/C15 -> #REF!
A16: 2 | B16: Chaipro Factory/TVAP | C16: =COUNTA('Infrastructure and Systems'!$C$54:$J$54) -> 8 | D16: =COUNTIF('Chaipro-SAP'!#REF!,"2.5.2.7")*1+COUNTIF('Chaipro-SAP'!#REF!,"SAP")*1+COUNTIF('Chaipro-SAP'!#REF!,"Other version Working")*0.8+COUNTIF('Chaipro-SAP'!#REF!,"2.5.2.5 With Issues")*0.6+COUNTIF('Chaipro-SAP'!#REF!,"Other version With Issues")*0.4 + COUNTIF('Chaipro-SAP'!#REF!,"None")*0.25 -> #REF! | E16: =D16/C16 -> #REF!
A17: 3 | B17: Chaipro Farmers | C17: =COUNTA('Infrastructure and Systems'!$C$54:$J$54) -> 8 | D17: =COUNTIF('Chaipro-SAP'!#REF!,"2.8.0.0")*1+COUNTIF('Chaipro-SAP'!#REF!,"Other version Working")*0.8+COUNTIF('Chaipro-SAP'!#REF!,"2.8.0.0 With Issues")*0.6+COUNTIF('Chaipro-SAP'!#REF!,"Other version With Issues")*0.4 + COUNTIF('Chaipro-SAP'!#REF!,"None")*0.25 -> #REF! | E17: =D17/C17 -> #REF!
A18: 4 | B18: Chaipro Fleet | C18: =COUNTA('Infrastructure and Systems'!$C$54:$J$54) -> 8 | D18: =COUNTIF('Chaipro-SAP'!#REF!,"3.2.5.1")*1+COUNTIF('Chaipro-SAP'!#REF!,"Other version Working")*0.8+COUNTIF('Chaipro-SAP'!#REF!,"3.2.5.1 With Issues")*0.6+COUNTIF('Chaipro-SAP'!#REF!,"Other version With Issues")*0.4 + COUNTIF('Chaipro-SAP'!#REF!,"None")*0.25 -> #REF! | E18: =D18/C18 -> #REF!
A19: 6 | B19: KTDA Replicator | C19: =COUNTA('Infrastructure and Systems'!$C$54:$J$54) -> 8 | D19: =COUNTIF('Chaipro-SAP'!#REF!,"Working")*1+COUNTIF('Chaipro-SAP'!#REF!,"Working With Issues")*0.5 -> #REF! | E19: =D19/C19 -> #REF!
A20: 7 | B20: Chai Data | C20: =COUNTA('Infrastructure and Systems'!$C$54:$J$54) -> 8 | D20: =COUNTIF('Chaipro-SAP'!#REF!,"1.0.0.3")*1+COUNTIF('Chaipro-SAP'!#REF!,"Other version Working")*0.8+COUNTIF('Chaipro-SAP'!#REF!,"1.0.0.3 With Issues")*0.6+COUNTIF('Chaipro-SAP'!#REF!,"Other version With Issues")*0.4 + COUNTIF('Chaipro-SAP'!B8:L8,"None")*0.25 -> #REF! | E20: =D20/C20 -> #REF!
A21: 8 | B21: Chai POS | C21: =COUNTA('Infrastructure and Systems'!$C$54:$J$54) -> 8 | D21: =COUNTIF('Chaipro-SAP'!#REF!,"2.2")*1+COUNTIF('Chaipro-SAP'!#REF!,"Other version Working")*0.8+COUNTIF('Chaipro-SAP'!#REF!,"2.2 With Issues")*0.6+COUNTIF('Chaipro-SAP'!#REF!,"Other version With Issues")*0.4 + COUNTIF('Chaipro-SAP'!#REF!,"None")*0.25 -> #REF! | E21: =D21/C21 -> #REF!
B22: Average | E22: =AVERAGE(E15:E21) -> #REF!
B24: Inventory
A25: No | B25: Service | C25: No of Factories | D25: Region 4 | E25: % Uptime Service | F25: Factories Affected | G25: Issue
A26: 1 | B26: Network Equipments (e.g. Switch, 2, Functional, any additional details) | C26: =COUNTA('Infrastructure and Systems'!$C$54:$J$54) -> 8 | D26: =COUNTIF('ICT Inventory'!#REF!,"No Issue Reported")+COUNTIF('ICT Inventory'!#REF!,"Partially Working")*0.7+COUNTIF('ICT Inventory'!#REF!,"Total Failure")*0.3 -> #REF! | E26: =D26/C26 -> #REF!
A27: 2 | B27: Software (e.g. third party software) etc | C27: =COUNTA('Infrastructure and Systems'!$C$54:$J$54) -> 8 | D27: =COUNTIF('ICT Inventory'!#REF!,"No Issue Reported")+COUNTIF('ICT Inventory'!#REF!,"Partially Working")*0.7+COUNTIF('ICT Inventory'!#REF!,"Total Failure")*0.3 -> #REF! | E27: =D27/C27 -> #REF!
A28: 3 | B28: Hardware (e.g. Servers, PCs, Laptops, UPS, DAs, Printers, Scanners, ESD, Fiscal Printers, Tablets) | C28: =COUNTA('Infrastructure and Systems'!$C$54:$J$54) -> 8 | D28: =COUNTIF('ICT Inventory'!#REF!,"No Issue Reported")+COUNTIF('ICT Inventory'!#REF!,"Partially Working")*0.7+COUNTIF('ICT Inventory'!#REF!,"Total Failure")*0.3 -> #REF! | E28: =D28/C28 -> #REF!
A29: 4 | B29: Other Equipment (please specify) | C29: =COUNTA('Infrastructure and Systems'!$C$54:$J$54) -> 8 | D29: =COUNTIF('ICT Inventory'!#REF!,"No Issue Reported")+COUNTIF('ICT Inventory'!#REF!,"Partially Working")*0.7+COUNTIF('ICT Inventory'!#REF!,"Total Failure")*0.3 -> #REF! | E29: =D29/C29 -> #REF!
B30: Average | E30: =AVERAGE(E26:E29) -> #REF!
B32: BCP
A33: No | B33: Service | C33: No of Factories | D33: Region 4 | E33: % Uptime Service | F33: Factories Affected | G33: Issue
A34: 1 | B34: Business Continuity Mechanism e.g. Backups | C34: =COUNTA('Infrastructure and Systems'!$C$54:$J$54) -> 8 | D34: =COUNTIF(BCP!#REF!,"Offsite & Schedule backups in place") -> #REF! | E34: =D34/C34 -> #REF!
B35: Average | E35: =AVERAGE(E34) -> #REF!
B38: PURCHASES
A39: No | B39: Service | C39: No of Factories | D39: Total Cost | E39: Cost vs budget | F39: Factories Affected | G39: Issue
A40: 1 | B40: Purchases | C40: =COUNTA('ICT Cost'!#REF!) -> 1 | D40: ='ICT Cost'!J40 -> 1250644
B41: Average

Sheet R5
B1: Region 5 & 7
B2: Infrastructure
A3: ='Infrastructure and Systems'!A3 -> No. | B3: Service | C3: No of Factories | D3: Region 5 | E3: % Uptime Service | F3: Factories Having Issues | G3: Summary of Issues | H3: Duration (days) | I3: Tickets Raised
A4: ='Infrastructure and Systems'!A4 -> 1 | B4: ='Infrastructure and Systems'!B4 -> Local Area Network (LAN) | C4: =COUNTA('Infrastructure and Systems'!$C$71:$P$71) -> 14 | D4: =COUNTIF('Infrastructure and Systems'!C72:P72,"No Issue Reported")+COUNTIF('Infrastructure and Systems'!C72:P72,"Partially Working")*0.7+COUNTIF('Infrastructure and Systems'!C72:P72,"Total Failure")*0.3 -> 0 | E4: =D4/C4 -> 0
A5: ='Infrastructure and Systems'!A5 -> 2 | B5: ='Infrastructure and Systems'!B5 -> Wide Area Network (WAN) | C5: =COUNTA('Infrastructure and Systems'!$C$71:$P$71) -> 14 | D5: =COUNTIF('Infrastructure and Systems'!C73:P73,"No Issue Reported")+COUNTIF('Infrastructure and Systems'!C73:P73,"Partially Working")*0.7+COUNTIF('Infrastructure and Systems'!C73:P73,"Total Failure")*0.3 -> 0 | E5: =D5/C5 -> 0
A6: ='Infrastructure and Systems'!A7 -> 4 | B6: ='Infrastructure and Systems'!B7 -> Firewall | C6: =COUNTA('Infrastructure and Systems'!$C$71:$P$71) -> 14 | D6: =COUNTIF('Infrastructure and Systems'!C74:P74,"No Issue Reported")+COUNTIF('Infrastructure and Systems'!C74:P74,"Partially Working")*0.7+COUNTIF('Infrastructure and Systems'!C74:P74,"Total Failure")*0.3 -> 0 | E6: =D6/C6 -> 0
A7: ='Infrastructure and Systems'!A8 -> 5 | B7: ='Infrastructure and Systems'!B8 -> E-Mail Server | C7: =COUNTA('Infrastructure and Systems'!$C$71:$P$71) -> 14 | D7: =COUNTIF('Infrastructure and Systems'!C75:P75,"Domino in use")*1+COUNTIF('Infrastructure and Systems'!C75:P75,"Exchange in Use")*0.8+COUNTIF('Infrastructure and Systems'!C75:P75,"Domino In Use-Issues")*0.6+COUNTIF('Infrastructure and Systems'!C75:P75,"Exchange In Use-Issues")*0.4+COUNTIF('Infrastructure and Systems'!C75:P75,"None")*0.2 -> 0 | E7: =D7/C7 -> 0
A8: ='Infrastructure and Systems'!A9 -> 6 | B8: ='Infrastructure and Systems'!B9 -> Business Servers (EWS, Chaipro) | C8: =COUNTA('Infrastructure and Systems'!$C$71:$P$71) -> 14 | D8: =COUNTIF('Infrastructure and Systems'!C76:P76,"No Issue Reported")+COUNTIF('Infrastructure and Systems'!C76:P76,"Partially Working")*0.7+COUNTIF('Infrastructure and Systems'!C76:P76,"Total Failure")*0.3 -> 0 | E8: =D8/C8 -> 0
A9: ='Infrastructure and Systems'!A10 -> 7 | B9: ='Infrastructure and Systems'!B10 -> Electronic Weighment Solution (EWS Version) | C9: =COUNTA('Infrastructure and Systems'!$C$71:$P$71) -> 14 | D9: =COUNTIF('Infrastructure and Systems'!C77:P77,"No Issue Reported")+COUNTIF('Infrastructure and Systems'!C77:P77,"Partially Working")*0.7+COUNTIF('Infrastructure and Systems'!C77:P77,"Total Failure")*0.3 -> 0 | E9: =D9/C9 -> 0
A10: ='Infrastructure and Systems'!#REF! -> #REF! | B10: ='Infrastructure and Systems'!#REF! -> #REF! | C10: =COUNTA('Infrastructure and Systems'!$C$71:$P$71) -> 14 | D10: =COUNTIF('Infrastructure and Systems'!C78:P78,"No Issue Reported")+COUNTIF('Infrastructure and Systems'!C78:P78,"Partially Working")*0.7+COUNTIF('Infrastructure and Systems'!C78:P78,"Total Failure")*0.3 -> 0 | E10: =D10/C10 -> 0
B11: Average | E11: =AVERAGE(E4:E10) -> 0
B13: ChaiPro
A14: No | B14: Service | C14: No of Factories | D14: Region 5 | E14: % Uptime Service | F14: Factories Affected | G14: Issue | K14: =COUNTIF('Chaipro-SAP'!C52:U52,"SAP") -> 0
A15: 1 | B15: Chaipro Financials | C15: 14 | D15: =COUNTIF('Chaipro-SAP'!C52:U52,"SAP")+COUNTIF('Chaipro-SAP'!C52:U52,"2.5.5.9")*1+COUNTIF('Chaipro-SAP'!C52:U52,"Other version Working")*0.8+COUNTIF('Chaipro-SAP'!C52:U52,"2.5.5.9With Issues")*0.6+COUNTIF('Chaipro-SAP'!C52:U52,"Other version With Issues")*0.4 + COUNTIF('Chaipro-SAP'!C52:U52,"None")*0.25 -> 6 | E15: =D15/C15 -> 0.42857143
A16: 2 | B16: Chaipro Factory/TVAP | C16: 14 | D16: =COUNTIF('Chaipro-SAP'!C53:P53,"2.5.2.7")*1+COUNTIF('Chaipro-SAP'!C53:P53,"SAP")*1+COUNTIF('Chaipro-SAP'!C53:U53,"Other version Working")*0.8+COUNTIF('Chaipro-SAP'!C53:U53,"2.5.2.7 With Issues")*0.6+COUNTIF('Chaipro-SAP'!C53:U53,"Other version With Issues")*0.4 + COUNTIF('Chaipro-SAP'!C53:U53,"None")*0.25 -> 6 | E16: =D16/C16 -> 0.42857143
A17: 3 | B17: Chaipro Farmers | C17: 14 | D17: =COUNTIF('Chaipro-SAP'!C54:U54,"3.0.0.0")*1+COUNTIF('Chaipro-SAP'!C54:U54,"2.8.0.0")*1+COUNTIF('Chaipro-SAP'!C54:U54,"Other version Working")*0.8+COUNTIF('Chaipro-SAP'!C54:U54,"2.8.0.0 With Issues")*0.6+COUNTIF('Chaipro-SAP'!C54:U54,"Other version With Issues")*0.4 + COUNTIF('Chaipro-SAP'!C54:U54,"None")*0.25 -> 0 | E17: =D17/C17 -> 0
A18: 4 | B18: Chaipro Fleet | C18: 14 | D18: =COUNTIF('Chaipro-SAP'!C55:U55,"SAP")*1+COUNTIF('Chaipro-SAP'!C55:U55,"3.2.5.1")*1+COUNTIF('Chaipro-SAP'!C55:U55,"Other version Working")*0.8+COUNTIF('Chaipro-SAP'!C55:U55,"3.2.5.1 With Issues")*0.6+COUNTIF('Chaipro-SAP'!C55:U55,"Other version With Issues")*0.4 + COUNTIF('Chaipro-SAP'!C55:U55,"None")*0.25 -> 6 | E18: =D18/C18 -> 0.42857143
A19: 6 | B19: KTDA Replicator | C19: 14 | D19: =COUNTIF('Chaipro-SAP'!C56:U56,"Working")*1+COUNTIF('Chaipro-SAP'!C56:U56,"Working With Issues")*0.5 -> 4 | E19: =D19/C19 -> 0.28571429
A20: 7 | B20: Chai Data | C20: 14 | D20: =COUNTIF('Chaipro-SAP'!C57:U57,"1.0.0.3")*1+COUNTIF('Chaipro-SAP'!C57:U57,"Other version Working")*0.8+COUNTIF('Chaipro-SAP'!C57:U57,"1.0.0.3 With Issues")*0.6+COUNTIF('Chaipro-SAP'!C57:U57,"Other version With Issues")*0.4 + COUNTIF('Chaipro-SAP'!C57:U57,"None")*0.25 -> 1 | E20: =D20/C20 -> 0.071428571
A21: 8 | B21: Chai POS | C21: 14 | D21: =COUNTIF('Chaipro-SAP'!C58:U58,"2.2")*1+COUNTIF('Chaipro-SAP'!C58:U58,"Other version Working")*0.8+COUNTIF('Chaipro-SAP'!C58:U58,"2.2 With Issues")*0.6+COUNTIF('Chaipro-SAP'!C58:U58,"Other version With Issues")*0.4 + COUNTIF('Chaipro-SAP'!C58:U58,"None")*0.25 -> 0 | E21: =D21/C21 -> 0
B22: Average | E22: =AVERAGE(E15:E21) -> 0.23469388
B24: Inventory
A25: No | B25: Service | C25: No of Factories | D25: Region 5 | E25: % Uptime Service | F25: Factories Affected | G25: Issue
A26: 1 | B26: Network Equipments (e.g. Switch, 2, Functional, any additional details) | C26: =COUNTA('ICT Inventory'!#REF!) -> 1 | D26: =COUNTIF('ICT Inventory'!#REF!,"No Issue Reported")+COUNTIF('ICT Inventory'!#REF!,"Partially Working")*0.7+COUNTIF('ICT Inventory'!#REF!,"Total Failure")*0.3 -> #REF! | E26: =D26/C26 -> #REF!
A27: 2 | B27: Software (e.g. third party software) etc | C27: =COUNTA('ICT Inventory'!#REF!) -> 1 | D27: =COUNTIF('ICT Inventory'!#REF!,"No Issue Reported")+COUNTIF('ICT Inventory'!#REF!,"Partially Working")*0.7+COUNTIF('ICT Inventory'!#REF!,"Total Failure")*0.3 -> #REF! | E27: =D27/C27 -> #REF!
A28: 3 | B28: Hardware (e.g. Servers, PCs, Laptops, UPS, DAs, Printers, Scanners, ESD, Fiscal Printers, Tablets) | C28: =COUNTA('ICT Inventory'!#REF!) -> 1 | D28: =COUNTIF('ICT Inventory'!#REF!,"No Issue Reported")+COUNTIF('ICT Inventory'!#REF!,"Partially Working")*0.7+COUNTIF('ICT Inventory'!#REF!,"Total Failure")*0.3 -> #REF! | E28: =D28/C28 -> #REF!
A29: 4 | B29: Other Equipment (please specify) | C29: =COUNTA('ICT Inventory'!#REF!) -> 1 | D29: =COUNTIF('ICT Inventory'!#REF!,"No Issue Reported")+COUNTIF('ICT Inventory'!#REF!,"Partially Working")*0.7+COUNTIF('ICT Inventory'!#REF!,"Total Failure")*0.3 -> #REF! | E29: =D29/C29 -> #REF!
B30: Average | E30: =AVERAGE(E26:E29) -> #REF!
B32: BCP
A33: No | B33: Service | C33: No of Factories | D33: Region 5 | E33: % Uptime Service | F33: Factories Affected | G33: Issue
A34: 1 | B34: Business Continuity Mechanism e.g. Backups | C34: =COUNTA(BCP!#REF!) -> 1 | D34: =COUNTIF(BCP!#REF!,"Offsite & Schedule backups in place") -> #REF! | E34: =D34/C34 -> #REF!
B35: Average | E35: =AVERAGE(E34) -> #REF!
B38: PURCHASES
A39: No | B39: Service | C39: No of Factories | D39: Total Cost | E39: Cost vs budget | F39: Factories Affected | G39: Issue
A40: 1 | B40: Purchases | C40: =COUNTA('ICT Cost'!#REF!) -> 1 | D40: ='ICT Cost'!R53 -> 2894127.9
B41: Average

Sheet R6
B1: Region 6
B2: Infrastructure
A3: ='Infrastructure and Systems'!A3 -> No. | B3: Service | C3: No of Factories | D3: Region 6 | E3: % Uptime Service | F3: Factories Having Issues | G3: Summary of Issues | H3: Duration (days) | I3: Tickets Raised
A4: ='Infrastructure and Systems'!A4 -> 1 | B4: ='Infrastructure and Systems'!B4 -> Local Area Network (LAN) | C4: =COUNTA('Infrastructure and Systems'!$C$88:$S$88) -> 14 | D4: =COUNTIF('Infrastructure and Systems'!C89:O89,"No Issue Reported")+COUNTIF('Infrastructure and Systems'!C89:O89,"Partially Working")*0.7+COUNTIF('Infrastructure and Systems'!C89:O89,"Total Failure")*0.3 -> 0 | E4: =D4/C4 -> 0
A5: ='Infrastructure and Systems'!A5 -> 2 | B5: ='Infrastructure and Systems'!B5 -> Wide Area Network (WAN) | C5: =COUNTA('Infrastructure and Systems'!$C$88:$O$88) -> 13 | D5: =COUNTIF('Infrastructure and Systems'!C90:O90,"No Issue Reported")+COUNTIF('Infrastructure and Systems'!C90:O90,"Partially Working")*0.7+COUNTIF('Infrastructure and Systems'!C90:O90,"Total Failure")*0.3 -> 0 | E5: =D5/C5 -> 0
A6: ='Infrastructure and Systems'!A7 -> 4 | B6: ='Infrastructure and Systems'!B7 -> Firewall | C6: =COUNTA('Infrastructure and Systems'!$C$88:$O$88) -> 13 | D6: =COUNTIF('Infrastructure and Systems'!C91:O91,"No Issue Reported")+COUNTIF('Infrastructure and Systems'!C91:O91,"Partially Working")*0.7+COUNTIF('Infrastructure and Systems'!C91:O91,"Total Failure")*0.3 -> 0 | E6: =IF('Infrastructure and Systems'!C7="Internet slow even sometimes not available",(D6/C6)/2,(D6/C6)) -> 0
A7: ='Infrastructure and Systems'!A8 -> 5 | B7: ='Infrastructure and Systems'!B8 -> E-Mail Server | C7: =COUNTA('Infrastructure and Systems'!$C$88:$O$88) -> 13 | D7: =COUNTIF('Infrastructure and Systems'!C92:O92,"Domino in use")*1+COUNTIF('Infrastructure and Systems'!C92:O92,"Exchange in Use")*0.8+COUNTIF('Infrastructure and Systems'!C92:O92,"Domino In Use-Issues")*0.6+COUNTIF('Infrastructure and Systems'!C92:O92,"Exchange In Use-Issues")*0.4+COUNTIF('Infrastructure and Systems'!C92:O92,"None")*0.2 -> 0 | E7: =D7/C7 -> 0
A8: ='Infrastructure and Systems'!A9 -> 6 | B8: ='Infrastructure and Systems'!B9 -> Business Servers (EWS, Chaipro) | C8: =COUNTA('Infrastructure and Systems'!$C$88:$O$88) -> 13 | D8: =COUNTIF('Infrastructure and Systems'!C93:O93,"No Issue Reported")+COUNTIF('Infrastructure and Systems'!C93:O93,"Partially Working")*0.7+COUNTIF('Infrastructure and Systems'!C93:O93,"Total Failure")*0.3 -> 0 | E8: =D8/C8 -> 0
A9: ='Infrastructure and Systems'!A10 -> 7 | B9: ='Infrastructure and Systems'!B10 -> Electronic Weighment Solution (EWS Version) | C9: =COUNTA('Infrastructure and Systems'!$C$88:$O$88) -> 13 | D9: =COUNTIF('Infrastructure and Systems'!C94:O94,"No Issue Reported")+COUNTIF('Infrastructure and Systems'!C94:O94,"Partially Working")*0.7+COUNTIF('Infrastructure and Systems'!C94:O94,"Total Failure")*0.3 -> 0 | E9: =D9/C9 -> 0
A10: ='Infrastructure and Systems'!#REF! -> #REF! | B10: ='Infrastructure and Systems'!#REF! -> #REF! | C10: =COUNTA('Infrastructure and Systems'!$C$88:$O$88) -> 13 | D10: =COUNTIF('Infrastructure and Systems'!C95:O95,"No Issue Reported")+COUNTIF('Infrastructure and Systems'!C95:O95,"Partially Working")*0.7+COUNTIF('Infrastructure and Systems'!C95:O95,"Total Failure")*0.3 -> 0 | E10: =D10/C10 -> 0
B11: Average | E11: =AVERAGE(E4:E10) -> 0
B13: ChaiPro
A14: No | B14: Service | C14: No of Factories | D14: Region 6 | E14: % Uptime Service | F14: Factories Affected | G14: Issue
A15: 1 | B15: Chaipro Financials | C15: =COUNTA('Infrastructure and Systems'!$C$88:$O$88) -> 13 | D15: =COUNTIF('Chaipro-SAP'!#REF!,"2.5.5.9")*1+COUNTIF('Chaipro-SAP'!#REF!,"SAP")*1+COUNTIF('Chaipro-SAP'!#REF!,"Other version Working")*0.8+COUNTIF('Chaipro-SAP'!#REF!,"2.5.5.7 With Issues")*0.6+COUNTIF('Chaipro-SAP'!#REF!,"Other version With Issues")*0.4 + COUNTIF('Chaipro-SAP'!#REF!,"None")*0.25 -> #REF! | E15: =D15/C15 -> #REF!
A16: 2 | B16: Chaipro Factory/TVAP | C16: =COUNTA('Infrastructure and Systems'!$C$88:$O$88) -> 13 | D16: =COUNTIF('Chaipro-SAP'!#REF!,"2.5.2.7")*1+COUNTIF('Chaipro-SAP'!#REF!,"SAP")*1+COUNTIF('Chaipro-SAP'!#REF!,"Other version Working")*0.8+COUNTIF('Chaipro-SAP'!#REF!,"2.5.2.5 With Issues")*0.6+COUNTIF('Chaipro-SAP'!#REF!,"Other version With Issues")*0.4 + COUNTIF('Chaipro-SAP'!#REF!,"None")*0.25 -> #REF! | E16: =D16/C16 -> #REF!
A17: 3 | B17: Chaipro Farmers | C17: =COUNTA('Infrastructure and Systems'!$C$88:$O$88) -> 13 | D17: =COUNTIF('Chaipro-SAP'!#REF!,"2.8.0.0")*1+COUNTIF('Chaipro-SAP'!#REF!,"Other version Working")*0.8+COUNTIF('Chaipro-SAP'!#REF!,"2.8.0.0 With Issues")*0.6+COUNTIF('Chaipro-SAP'!#REF!,"Other version With Issues")*0.4 + COUNTIF('Chaipro-SAP'!#REF!,"None")*0.25 -> #REF! | E17: =D17/C17 -> #REF!
A18: 4 | B18: Chaipro Fleet | C18: =COUNTA('Infrastructure and Systems'!$C$88:$O$88) -> 13 | D18: =COUNTIF('Chaipro-SAP'!#REF!,"3.2.5.1")*1+COUNTIF('Chaipro-SAP'!#REF!,"SAP")*1+COUNTIF('Chaipro-SAP'!#REF!,"Other version Working")*0.8+COUNTIF('Chaipro-SAP'!#REF!,"3.2.5.1 With Issues")*0.6+COUNTIF('Chaipro-SAP'!#REF!,"Other version With Issues")*0.4 + COUNTIF('Chaipro-SAP'!#REF!,"None")*0.25 -> #REF! | E18: =D18/C18 -> #REF!
A19: 6 | B19: KTDA Replicator | C19: =COUNTA('Infrastructure and Systems'!$C$88:$O$88) -> 13 | D19: =COUNTIF('Chaipro-SAP'!#REF!,"Working")*1+COUNTIF('Chaipro-SAP'!#REF!,"Working With Issues")*0.5 -> #REF! | E19: =D19/C19 -> #REF!
A20: 7 | B20: Chai Data | C20: =COUNTA('Infrastructure and Systems'!$C$88:$O$88) -> 13 | D20: =COUNTIF('Chaipro-SAP'!#REF!,"1.0.0.3")*1+COUNTIF('Chaipro-SAP'!#REF!,"Other version Working")*0.8+COUNTIF('Chaipro-SAP'!#REF!,"1.0.0.3 With Issues")*0.6+COUNTIF('Chaipro-SAP'!#REF!,"Other version With Issues")*0.4 + COUNTIF('Chaipro-SAP'!#REF!,"None")*0.25 -> #REF! | E20: =D20/C20 -> #REF!
A21: 8 | B21: Chai POS | C21: =COUNTA('Infrastructure and Systems'!$C$88:$O$88) -> 13 | D21: =COUNTIF('Chaipro-SAP'!#REF!,"2.2")*1+COUNTIF('Chaipro-SAP'!#REF!,"Other version Working")*0.8+COUNTIF('Chaipro-SAP'!#REF!,"2.2 With Issues")*0.6+COUNTIF('Chaipro-SAP'!#REF!,"Other version With Issues")*0.4 + COUNTIF('Chaipro-SAP'!#REF!,"None")*0.25 -> #REF! | E21: =D21/C21 -> #REF!
B22: Average | E22: =AVERAGE(E15:E21) -> #REF!
B24: Inventory
A25: No | B25: Service | C25: No of Factories | D25: Region 6 | E25: % Uptime Service | F25: Factories Affected | G25: Issue
A26: 1 | B26: Network Equipments (e.g. Switch, 2, Functional, any additional details) | C26: =COUNTA('ICT Inventory'!#REF!) -> 1 | D26: =COUNTIF('ICT Inventory'!#REF!,"No Issue Reported")+COUNTIF('ICT Inventory'!#REF!,"Partially Working")*0.7+COUNTIF('ICT Inventory'!#REF!,"Total Failure")*0.3 -> #REF! | E26: =D26/C26 -> #REF!
A27: 2 | B27: Software (e.g. third party software) etc | C27: =COUNTA('ICT Inventory'!#REF!) -> 1 | D27: =COUNTIF('ICT Inventory'!#REF!,"No Issue Reported")+COUNTIF('ICT Inventory'!#REF!,"Partially Working")*0.7+COUNTIF('ICT Inventory'!#REF!,"Total Failure")*0.3 -> #REF! | E27: =D27/C27 -> #REF!
A28: 3 | B28: Hardware (e.g. Servers, PCs, Laptops, UPS, DAs, Printers, Scanners, ESD, Fiscal Printers, Tablets) | C28: =COUNTA('ICT Inventory'!#REF!) -> 1 | D28: =COUNTIF('ICT Inventory'!#REF!,"No Issue Reported")+COUNTIF('ICT Inventory'!#REF!,"Partially Working")*0.7+COUNTIF('ICT Inventory'!#REF!,"Total Failure")*0.3 -> #REF! | E28: =D28/C28 -> #REF!
A29: 4 | B29: Other Equipment (please specify) | C29: =COUNTA('ICT Inventory'!#REF!) -> 1 | D29: =COUNTIF('ICT Inventory'!#REF!,"No Issue Reported")+COUNTIF('ICT Inventory'!#REF!,"Partially Working")*0.7+COUNTIF('ICT Inventory'!#REF!,"Total Failure")*0.3 -> #REF! | E29: =D29/C29 -> #REF!
B30: Average | E30: =AVERAGE(E26:E29) -> #REF!
B32: BCP
A33: No | B33: Service | C33: No of Factories | D33: Region 6 | E33: % Uptime Service | F33: Factories Affected | G33: Issue
A34: 1 | B34: Business Continuity Mechanism e.g. Backups | C34: =COUNTA(BCP!#REF!) -> 1 | D34: =COUNTIF(BCP!#REF!,"Offsite & Schedule backups in place") -> #REF! | E34: =D34/C34 -> #REF!
B35: Average | E35: =AVERAGE(E34) -> #REF!
B38: PURCHASES
A39: No | B39: Service | C39: No of Factories | D39: Total Cost | E39: Cost vs budget | F39: Factories Affected | G39: Issue
A40: 1 | B40: Purchases | C40: =COUNTA('ICT Cost'!#REF!) -> 1 | D40: ='ICT Cost'!#REF! -> #REF!
B41: Average

Sheet R7
B1: Region 7
B2: Infrastructure
A3: ='Infrastructure and Systems'!A3 -> No. | B3: Service | C3: No of Factories | D3: Region 7 | E3: % Uptime Service | F3: Factories Having Issues | G3: Summary of Issues | H3: Duration (days) | I3: Tickets Raised
A4: ='Infrastructure and Systems'!A4 -> 1 | B4: ='Infrastructure and Systems'!B4 -> Local Area Network (LAN) | C4: =COUNTA('Infrastructure and Systems'!$C$106:$F$106) -> 4 | D4: =COUNTIF('Infrastructure and Systems'!C106:F106,"No Issue Reported")+COUNTIF('Infrastructure and Systems'!C89:O89,"Partially Working")*0.7+COUNTIF('Infrastructure and Systems'!C89:O89,"Total Failure")*0.3 -> 0 | E4: =D4/C4 -> 0
A5: ='Infrastructure and Systems'!A5 -> 2 | B5: ='Infrastructure and Systems'!B5 -> Wide Area Network (WAN) | C5: =COUNTA('Infrastructure and Systems'!$C$106:$F$106) -> 4 | D5: =COUNTIF('Infrastructure and Systems'!C107:F107,"No Issue Reported")+COUNTIF('Infrastructure and Systems'!C90:O90,"Partially Working")*0.7+COUNTIF('Infrastructure and Systems'!C90:O90,"Total Failure")*0.3 -> 0 | E5: =D5/C5 -> 0
A6: ='Infrastructure and Systems'!A7 -> 4 | B6: ='Infrastructure and Systems'!B7 -> Firewall | C6: =COUNTA('Infrastructure and Systems'!$C$106:$F$106) -> 4 | D6: =COUNTIF('Infrastructure and Systems'!C108:F108,"No Issue Reported")+COUNTIF('Infrastructure and Systems'!C91:O91,"Partially Working")*0.7+COUNTIF('Infrastructure and Systems'!C91:O91,"Total Failure")*0.3 -> 0 | E6: =IF('Infrastructure and Systems'!C7="Internet slow even sometimes not available",(D6/C6)/2,(D6/C6)) -> 0
A7: ='Infrastructure and Systems'!A8 -> 5 | B7: ='Infrastructure and Systems'!B8 -> E-Mail Server | C7: =COUNTA('Infrastructure and Systems'!$C$106:$F$106) -> 4 | D7: 4 | E7: =D7/C7 -> 1
A8: ='Infrastructure and Systems'!A9 -> 6 | B8: ='Infrastructure and Systems'!B9 -> Business Servers (EWS, Chaipro) | C8: =COUNTA('Infrastructure and Systems'!$C$106:$F$106) -> 4 | D8: =COUNTIF('Infrastructure and Systems'!C110:F110,"No Issue Reported")+COUNTIF('Infrastructure and Systems'!C93:O93,"Partially Working")*0.7+COUNTIF('Infrastructure and Systems'!C93:O93,"Total Failure")*0.3 -> 0 | E8: =D8/C8 -> 0
A9: ='Infrastructure and Systems'!A10 -> 7 | B9: ='Infrastructure and Systems'!B10 -> Electronic Weighment Solution (EWS Version) | C9: =COUNTA('Infrastructure and Systems'!$C$106:$F$106) -> 4 | D9: =COUNTIF('Infrastructure and Systems'!C111:F111,"No Issue Reported")+COUNTIF('Infrastructure and Systems'!C94:O94,"Partially Working")*0.7+COUNTIF('Infrastructure and Systems'!C94:O94,"Total Failure")*0.3 -> 0 | E9: =D9/C9 -> 0
A10: ='Infrastructure and Systems'!#REF! -> #REF! | B10: ='Infrastructure and Systems'!#REF! -> #REF! | C10: =COUNTA('Infrastructure and Systems'!$C$106:$F$106) -> 4 | D10: =COUNTIF('Infrastructure and Systems'!C112:F112,"No Issue Reported")+COUNTIF('Infrastructure and Systems'!C95:O95,"Partially Working")*0.7+COUNTIF('Infrastructure and Systems'!C95:O95,"Total Failure")*0.3 -> 0 | E10: =D10/C10 -> 0
B11: Average | E11: =AVERAGE(E4:E10) -> 0.14285714
B13: ChaiPro
A14: No | B14: Service | C14: No of Factories | D14: Region 7 | E14: % Uptime Service | F14: Factories Affected | G14: Issue
A15: 1 | B15: Chaipro Financials | C15: =COUNTA('Chaipro-SAP'!#REF!) -> 1 | D15: =COUNTIF('Chaipro-SAP'!#REF!,"2.5.5.9")*1+COUNTIF('Chaipro-SAP'!#REF!,"SAP")*1+COUNTIF('Chaipro-SAP'!#REF!,"Other version Working")*0.8+COUNTIF('Chaipro-SAP'!#REF!,"2.5.5.7 With Issues")*0.6+COUNTIF('Chaipro-SAP'!#REF!,"Other version With Issues")*0.4 + COUNTIF('Chaipro-SAP'!#REF!,"None")*0.25 -> #REF! | E15: =D15/C15 -> #REF!
A16: 2 | B16: Chaipro Factory/TVAP | C16: =COUNTA('Chaipro-SAP'!#REF!) -> 1 | D16: =COUNTIF('Chaipro-SAP'!#REF!,"2.5.2.7")*1+COUNTIF('Chaipro-SAP'!#REF!,"SAP")*1++COUNTIF('Chaipro-SAP'!#REF!,"Other version Working")*0.8+COUNTIF('Chaipro-SAP'!#REF!,"2.5.2.5 With Issues")*0.6+COUNTIF('Chaipro-SAP'!#REF!,"Other version With Issues")*0.4 + COUNTIF('Chaipro-SAP'!#REF!,"None")*0.25 -> #REF! | E16: =D16/C16 -> #REF!
A17: 3 | B17: Chaipro Farmers | C17: =COUNTA('Chaipro-SAP'!#REF!) -> 1 | D17: =COUNTIF('Chaipro-SAP'!#REF!,"3.0.0.0")*1+COUNTIF('Chaipro-SAP'!#REF!,"2.8.0.0")*1+COUNTIF('Chaipro-SAP'!#REF!,"Other version Working")*0.8+COUNTIF('Chaipro-SAP'!#REF!,"2.8.0.0 With Issues")*0.6+COUNTIF('Chaipro-SAP'!#REF!,"Other version With Issues")*0.4 + COUNTIF('Chaipro-SAP'!#REF!,"None")*0.25 -> #REF! | E17: =D17/C17 -> #REF!
A18: 4 | B18: Chaipro Fleet | C18: =COUNTA('Chaipro-SAP'!#REF!) -> 1 | D18: =COUNTIF('Chaipro-SAP'!#REF!,"3.2.5.1")*1+COUNTIF('Chaipro-SAP'!#REF!,"SAP")*1+COUNTIF('Chaipro-SAP'!#REF!,"Other version Working")*0.8+COUNTIF('Chaipro-SAP'!#REF!,"3.2.5.1 With Issues")*0.6+COUNTIF('Chaipro-SAP'!#REF!,"Other version With Issues")*0.4 + COUNTIF('Chaipro-SAP'!#REF!,"None")*0.25 -> #REF! | E18: =D18/C18 -> #REF!
A19: 6 | B19: KTDA Replicator | C19: =COUNTA('Chaipro-SAP'!#REF!) -> 1 | D19: =COUNTIF('Chaipro-SAP'!#REF!,"Working")*1+COUNTIF('Chaipro-SAP'!#REF!,"Working With Issues")*0.5 -> #REF! | E19: =D19/C19 -> #REF!
A20: 7 | B20: Chai Data | C20: =COUNTA('Chaipro-SAP'!#REF!) -> 1 | D20: =COUNTIF('Chaipro-SAP'!#REF!,"1.0.0.3")*1+COUNTIF('Chaipro-SAP'!#REF!,"Other version Working")*0.8+COUNTIF('Chaipro-SAP'!#REF!,"1.0.0.3 With Issues")*0.6+COUNTIF('Chaipro-SAP'!#REF!,"Other version With Issues")*0.4 + COUNTIF('Chaipro-SAP'!#REF!,"None")*0.25 -> #REF! | E20: =D20/C20 -> #REF!
A21: 8 | B21: Chai POS | C21: =COUNTA('Chaipro-SAP'!#REF!) -> 1 | D21: =COUNTIF('Chaipro-SAP'!#REF!,"2.2")*1+COUNTIF('Chaipro-SAP'!#REF!,"Other version Working")*0.8+COUNTIF('Chaipro-SAP'!#REF!,"2.2 With Issues")*0.6+COUNTIF('Chaipro-SAP'!#REF!,"Other version With Issues")*0.4 + COUNTIF('Chaipro-SAP'!#REF!,"None")*0.25 -> #REF! | E21: =D21/C21 -> #REF!
B22: Average | E22: =AVERAGE(E15:E21) -> #REF!
B24: Inventory
A25: No | B25: Service | C25: No of Factories | D25: Region 7 | E25: % Uptime Service | F25: Factories Affected | G25: Issue
A26: 1 | B26: Network Equipments (e.g. Switch, 2, Functional, any additional details) | C26: =COUNTA('ICT Inventory'!#REF!) -> 1 | D26: =COUNTIF('ICT Inventory'!#REF!,"No Issue Reported")+COUNTIF('ICT Inventory'!#REF!,"Partially Working")*0.7+COUNTIF('ICT Inventory'!#REF!,"Total Failure")*0.3 -> #REF! | E26: =D26/C26 -> #REF!
A27: 2 | B27: Software (e.g. third party software) etc | C27: =COUNTA('ICT Inventory'!#REF!) -> 1 | D27: =COUNTIF('ICT Inventory'!#REF!,"No Issue Reported")+COUNTIF('ICT Inventory'!#REF!,"Partially Working")*0.7+COUNTIF('ICT Inventory'!#REF!,"Total Failure")*0.3 -> #REF! | E27: =D27/C27 -> #REF!
A28: 3 | B28: Hardware (e.g. Servers, PCs, Laptops, UPS, DAs, Printers, Scanners, ESD, Fiscal Printers, Tablets) | C28: =COUNTA('ICT Inventory'!#REF!) -> 1 | D28: =COUNTIF('ICT Inventory'!#REF!,"No Issue Reported")+COUNTIF('ICT Inventory'!#REF!,"Partially Working")*0.7+COUNTIF('ICT Inventory'!#REF!,"Total Failure")*0.3 -> #REF! | E28: =D28/C28 -> #REF!
A29: 4 | B29: Other Equipment (please specify) | C29: =COUNTA('ICT Inventory'!#REF!) -> 1 | D29: =COUNTIF('ICT Inventory'!#REF!,"No Issue Reported")+COUNTIF('ICT Inventory'!#REF!,"Partially Working")*0.7+COUNTIF('ICT Inventory'!#REF!,"Total Failure")*0.3 -> #REF! | E29: =D29/C29 -> #REF!
B30: Average | E30: =AVERAGE(E26:E29) -> #REF!
B32: BCP
A33: No | B33: Service | C33: No of Factories | D33: Region 7 | E33: % Uptime Service | F33: Factories Affected | G33: Issue
A34: 1 | B34: Business Continuity Mechanism e.g. Backups | C34: =COUNTA(BCP!#REF!) -> 1 | D34: =COUNTIF(BCP!#REF!,"Offsite & Schedule backups in place") -> #REF! | E34: =D34/C34 -> #REF!
B35: Average | E35: =AVERAGE(E34) -> #REF!
B38: PURCHASES
A39: No | B39: Service | C39: No of Factories | D39: Total Cost | E39: Cost vs budget | F39: Factories Affected | G39: Issue
A40: 1 | B40: Purchases | C40: =COUNTA('ICT Cost'!#REF!) -> 1 | D40: ='ICT Cost'!F75 -> 1170132.1 | E40: ='ICT Cost'!F76 -> 0
B41: Average

Sheet SUM PERFORMANCE
B1: All Regions Performance | H1: ='Infrastructure and Systems'!M2 -> 45930
B2: Overall Performance
A3: Service | B3: Region 1 | C3: Region 2 | D3: Region 3 | E3: Region 4 | F3: Region 5 | G3: Region 6 | H3: Region 7 | I3: Common Issues /Trend Noted
A4: Infrastructure and Systems | B4: 1 | C4: 1 | D4: 0.99285714 | E4: 1 | F4: 0.99795918 | G4: 1 | H4: 1
A5: ='R1'!B13 -> ChaiPro/SAP | B5: 0.98571429 | C5: 0.9968254 | D5: 1 | E5: 1 | F5: 1 | G5: 1 | H5: 1
A6: ='R1'!B24 -> Inventory | B6: 1 | C6: 1 | D6: 1 | E6: 1 | F6: 1 | G6: 1 | H6: 1
A7: ='R1'!B32 -> BCP | B7: 1 | C7: 1 | D7: 1 | E7: 1 | F7: 1 | G7: 1 | H7: 1
A8: Total ICT costs for the Month | B8: ='ICT Cost'!N8 -> 6945720.9 | C8: ='ICT Cost'!K19 -> 643526 | D8: ='ICT Cost'!P64 -> 2274787.1 | E8: ='ICT Cost'!J42 -> 2103543 | F8: ='ICT Cost'!R53 -> 2894127.9 | G8: ='ICT Cost'!P64 -> 2274787.1 | H8: ='ICT Cost'!P64 -> 2274787.1
A9: Average | B9: =AVERAGE(B4:B7) -> 0.99642857 | C9: =AVERAGE(C4:C7) -> 0.99920635 | D9: =AVERAGE(D4:D7) -> 0.99821429 | E9: =AVERAGE(E4:E7) -> 1 | F9: =AVERAGE(F4:F7) -> 0.9994898 | G9: =AVERAGE(G4:G7) -> 1 | H9: =AVERAGE(H4:H7) -> 1
A10: Target Performance | B10: 0.99 | C10: 0.99 | D10: 0.99 | E10: 0.99 | F10: 0.99 | G10: 0.99 | H10: 0.99
A11: Variance | B11: =B9-B10 -> 0.0064285714 | C11: =C9-C10 -> 0.0092063492 | D11: =D9-D10 -> 0.0082142857 | E11: =E9-E10 -> 0.01 | F11: =F9-F10 -> 0.0094897959 | G11: =G9-G10 -> 0.01 | H11: =H9-H10 -> 0.01
A12: Purchases Total To date 2025/2026 | B12: ='ICT Cost'!N8 -> 6945720.9 | C12: ='ICT Cost'!K18 -> 0 | D12: ='ICT Cost'!J31 -> 0 | E12: ='ICT Cost'!J41 -> 774899 | F12: ='ICT Cost'!R53 -> 2894127.9 | G12: ='ICT Cost'!P64 -> 2274787.1 | H12: ='ICT Cost'!F75 -> 1170132.1
A13: Budget Total To date 2025/2026 | B13: ='ICT Cost'!N10 -> 0 | C13: ='ICT Cost'!K21 -> 0 | D13: ='ICT Cost'!J33 -> 153855313 | E13: ='ICT Cost'!J44 -> 110421960 | F13: ='ICT Cost'!R55 -> 348325500 | G13: ='ICT Cost'!P66 -> 41920000 | H13: ='ICT Cost'!F77 -> 57352702

Sheet Pending Issues-SEPT 2025
G1: ALL REGIONS
A2: LANSUPPORT/ITSM PENDING ISSUES AS AT END OF SEPT 2025 | G2: FIELD REPORT PENDING ISSUES FIELD AS AT END OF SEPT 2025
A4: Regions | B4: Client | C4: Ref. # | D4: Subject | E4: Date | F4: Appears on Field Report | G4: Client | H4: Ref. # | I4: Subject | J4: Appears on Lansupport Report | K4: Remarks | L4: Assigned
A5: Region 1 | B5: Ikumbi Tea Factory Co. Ltd | C5: 18414 | D5: Faulty laptop L540 | E5: 43815 | F5: Yes | G5: Ikumbi Tea Factory Co. Ltd | H5: 18414 | I5: Faulty laptop L540 | J5: Yes | K5: Faulty laptop awaiting to sent back to factory | L5: Winfred Kabuuri
B6: Ikumbi Tea Factory Co. Ltd | C6: 37884 | D6: Faulty Directors tablet | E6: 45404 | F6: yes | G6: Ikumbi Tea Factory Co. Ltd | H6: 37884 | I6: Faulty Directors tablet | J6: Yes | K6: technical report attached | L6: Anthony Wanjau
B7: Theta Tea Factory Co. Ltd | C7: 39100 | D7: HP PRO DESK COMPUTER FAILURE | E7: 45784 | F7: No | G7: Theta Tea Factory Co. Ltd | H7: 39100 | I7: HP PRO DESK COMPUTER FAILURE | J7: Yes | K7: Vendor picked up the machine. | L7: Denis Nganga
B8: region 1 ndakaini | C8: 28063 | D8: Monitor display faulty | E8: 44260 | F8: yes | G8: region 1 ndakaini | H8: 28063 | I8: Monitor display faulty | J8: yes | L8: Peter Kibe
B9: Kagwe Tea Factory Co. Ltd | C9: 38622 | D9: SAP GL Variance | E9: 45621 | F9: No | G9: Kagwe Tea Factory Co. Ltd | H9: 38622 | I9: SAP GL Variance | J9: No | K9: The issue is now resolved. Need to be closed | L9: Avelline Ondari
B10: Kagwe Tea Factory Co. Ltd | C10: 38427 | D10: Lenovo E590 laptop not booting | E10: 45544 | F10: yes | G10: Kagwe Tea Factory Co. Ltd | H10: 38427 | I10: Lenovo E590 laptop not booting | J10: No | K10: The issue is now resolved. Need to be closed | L10: Peter Kibe
B11: Ndarugu Tea Factory Co. Ltd | C11: 38889 | D11: Insured damaged tablet sreen | E11: 45715 | F11: No | G11: Ndarugu Tea Factory Co. Ltd | H11: 38889 | I11: Insured damaged tablet sreen | J11: Yes | K11: Waiting a response from the factory whether the issue was resolved | L11: Sheila Maina
B12: Nduti Tea Factory Co. Ltd | C12: 39446 | D12: FAULTY LAPTOP BATTERY S/N PF-4HRDEN | E12: 45878 | F12: No | G12: Nduti Tea Factory Co. Ltd | H12: 39446 | I12: FAULTY LAPTOP BATTERY S/N PF-4HRDEN | J12: Yes | K12: awaiting laptop to be sent to HQ | L12: Peter Kibe
B13: Nduti Tea Factory Co. Ltd | C13: 39447 | D13: FAULTY LAPTOP S/N PF-2Z6BWD | E13: 45899 | F13: No | G13: Nduti Tea Factory Co. Ltd | H13: 39447 | I13: FAULTY LAPTOP S/N PF-2Z6BWD | J13: Yes | K13: Laptop received at HO and forwarded to ICT hardware for further diagnosis | L13: John Maroko
B14: Njunu Tea Factory Co. Ltd | C14: 39238 | D14: Loss of HP Probook UMA G7 Laptop | E14: 45826 | F14: yes | G14: Njunu Tea Factory Co. Ltd | H14: 39238 | I14: Loss of HP Probook UMA G7 Laptop | J14: Yes | K14: Awaiting proforma invoice of a similar model | L14: Sheila Maina
D15: Total - 5- Lansupport | G15: Total -8 -
A16: Region 2 | B16: Gatunguru Tea Factory Co. Ltd | C16: 36405 | D16: mail server faulty | E16: 45138 | F16: Yes | G16: Gatunguru Tea Factory Co. Ltd | H16: 36405 | I16: mail server faulty | K16: Awaiting confirmation from RICTM | L16: Erick Kinyeki
B17: Githambo Tea Factory Co. Ltd | C17: 34395 | D17: DAMAGE OF FUM LAPTOP BY RAIN WATER | E17: 44797 | F17: Yes | G17: Githambo Tea Factory Co. Ltd | H17: 34395 | I17: DAMAGE OF FUM LAPTOP BY RAIN WATER | K17: The claim remains unattended to. | L17: Erick Kinyeki
B18: Githambo Tea Factory Co. Ltd | C18: 38340 | D18: WAn Connectivity Down | E18: 45516 | F18: Yes | G18: Githambo Tea Factory Co. Ltd | H18: 38340 | I18: WAn Connectivity Down | K18: Affected services: - SAP - Emails - Internet - data replication/uploads | L18: Erick Kinyeki
B19: Githambo Tea Factory Co. Ltd | C19: 38695 | D19: NEW LAPTOP- OVERHEATING | E19: 45646 | F19: Yes | G19: Githambo Tea Factory Co. Ltd | H19: 38695 | I19: NEW LAPTOP- OVERHEATING | K19: laptop is yet to be dispatched to HQ | L19: Erick Kinyeki
B20: Githambo Tea Factory Co. Ltd | C20: 39064 | D20: KTDA Leaf Buying application | E20: 45771 | F20: Yes | G20: Githambo Tea Factory Co. Ltd | H20: 39064 | I20: KTDA Leaf Buying application | K20: Awaiting confirmation from Simon | L20: Simon Kiragu
B21: Githambo Tea Factory Co. Ltd | C21: 39486 | D21: DFX Printer have Developed Printing | E21: 45912 | F21: Yes | G21: Githambo Tea Factory Co. Ltd | H21: 39486 | I21: DFX Printer have Developed Printing | K21: working to see the printer repaired | L21: Benjamin Ndungu
B22: Kanyenyaini Tea Factory Co. Ltd | C22: 36516 | D22: LAN UPGRADE | E22: 45282 | F22: Yes | G22: Kanyenyaini Tea Factory Co. Ltd | H22: 36516 | I22: LAN UPGRADE | K22: Awaiting confirmation from RICTM | L22: Erick Kinyeki
B23: Kanyenyaini Tea Factory Co. Ltd | C23: 38341 | D23: Faulty Epson DFX 9000 | E23: 45517 | F23: Yes | G23: Kanyenyaini Tea Factory Co. Ltd | H23: 38341 | I23: Faulty Epson DFX 9000 | K23: Awaiting FSA to Advise on the location of the printer. | L23: Erick Kinyeki
B24: Kanyenyaini Tea Factory Co. Ltd | C24: 38439 | D24: LAN Connectivity Factory/Admin Block | E24: 45551 | F24: Yes | G24: Kanyenyaini Tea Factory Co. Ltd | H24: 38439 | I24: LAN Connectivity Factory/Admin Block | K24: challenges with connectivity from the factory Bldg to Administration block due to severed network cables | L24: Erick Kinyeki
B25: Kanyenyaini Tea Factory Co. Ltd | C25: 38745 | D25: Internet Access | E25: 45672 | F25: Yes | G25: Kanyenyaini Tea Factory Co. Ltd | H25: 38745 | I25: Internet Access | K25: awaiting confrimation from the FSA on the fiber replacement. | L25: Erick Kinyeki
B26: Gathuthi Tea Factory Co. Ltd | C26: 12951 | D26: Loss of tablet-director David W. Gitonga | E26: 45154 | F26: Yes | G26: Gathuthi Tea Factory Co. Ltd | H26: 12951 | I26: Loss of tablet-director David W. Gitonga | K26: Florence to advice on the status of the tablet. | L26: Florence Barasa
B27: Gathuthi Tea Factory Co. Ltd | C27: 27612 | D27: faulty Samsung tablet s/n R52MB0M7QZB | E27: 44250 | F27: Yes | G27: Gathuthi Tea Factory Co. Ltd | H27: 27612 | I27: faulty Samsung tablet s/n R52MB0M7QZB | K27: Winnie to advice on the status of the tablet | L27: Winfred Kabuuri
B28: Gathuthi Tea Factory Co. Ltd | C28: 39027 | D28: FAULTY LENOVO THINKPAD E15 | E28: 45764 | F28: Yes | G28: Gathuthi Tea Factory Co. Ltd | H28: 39027 | I28: FAULTY LENOVO THINKPAD E15 | K28: laptop is yet to be dispatched to HQ | L28: Erick Kinyeki
D29: Total - 13- Lansupport | G29: Total - 0 -
A30: Region 3 | B30: Region office | C30: 35041 | D30: Screen damaged Lenovo tablet | E30: 44894 | F30: No | G30: Region office | H30: 35041 | I30: Screen damaged Lenovo tablet | J30: YES | K30: Documents yet to be received in the factory | L30: Jackson Gachuki
B31: Region office | C31: 38846 | D31: MICHIMIKURU VPN LINES | E31: 45699 | F31: No | G31: Region office | H31: 38846 | I31: MICHIMIKURU VPN LINES | K31: Waiting fot vendor to fix the machine | L31: Jackson Gachuki
B32: Kionyo | C32: 38874 | D32: Email addition to PA Group | E32: 45709 | F32: No | G32: Kionyo | H32: 38874 | I32: Email addition to PA Group | J32: Yes | K32: Laptop waiting keyboard replacement | L32: Jackson Gachuki
D33: Total - 4- Lansupport | G33: Total - 3 -
A34: Region 4 | B34: Region office | C34: 35041 | D34: Screen damaged Lenovo tablet | E34: 44894 | F34: No | G34: Region office | H34: 35041 | I34: Screen damaged Lenovo tablet | J34: Yes | K34: Awaiting confirmation from the RICTM whether the claim was settled | L34: Jackson Gachuki
B35: Region office | C35: 38846 | D35: MICHIMIKURU VPN LINES | E35: 45699 | F35: No | G35: Region office | H35: 38846 | I35: MICHIMIKURU VPN LINES | J35: Yes | K35: Awaiting confirmation from the RICTM whether the lines are working | L35: Jackson Gachuki
B36: Kionyo | C36: 38874 | D36: Email addition to PA Group | E36: 45709 | F36: No | G36: Kionyo | H36: 38874 | I36: Email addition to PA Group | J36: Yes | K36: The action is with the FSA to create PA group at Kionyo | L36: Jackson Gachuki
D37: Total - 0- Lansupport | I37: Total - 4
A38: Region 5 | B38: Tegat Tea Factory Co. Ltd. | C38: 39005 | D38: Faulty Firewall | E38: Escalated | F38: yes | G38: Tegat Tea Factory Co. Ltd. | H38: 39005 | I38: Faulty Firewall | J38: Yes | K38: Insurance | L38: Edwin Mwosa
B39: Kapset Tea Factory Co. Ltd | C39: 9531 | D39: Damaged Tablet Screen | E39: 42376 | F39: yes | G39: Kapset Tea Factory Co. Ltd | H39: 9531 | I39: Damaged Tablet Screen | J39: Yes | L39: Florence Barasa
B40: Kapset Tea Factory Co. Ltd | C40: 39487 | D40: Scale | F40: yes | G40: Kapset Tea Factory Co. Ltd | H40: 39487 | I40: Scale | J40: Yes | K40: Insurance | L40: Dennis
B41: Kapset Tea Factory Co. Ltd | C41: 8841 | D41: DIRECTOR TABLET | E41: 42263 | F41: yes | G41: Kapset Tea Factory Co. Ltd | H41: 8841 | I41: DIRECTOR TABLET | J41: Yes | L41: Florence Barasa
B42: Motigo Tea Factory | C42: 39151 | D42: Sim Card | E42: 23/05/2025 | F42: No | G42: Motigo Tea Factory | H42: 39151 | I42: Sim Card | J42: Yes | L42: Winnie Kabuuri
B43: Motigo Tea Factory | C43: 37340 | D43: Faulty tablet | E43: 45294 | F43: yes | G43: Motigo Tea Factory | H43: 37340 | I43: Faulty tablet | J43: Yes | L43: Enock Ogara
B44: kobel | C44: 39549 | D44: Faulty Laptop | E44: 45726 | F44: No | G44: kobel | H44: 39549 | I44: Faulty Laptop | J44: Yes | L44: Beatrice
B45: Rorok | C45: 39548 | D45: Epson Printer | E45: 45726 | F45: yes | G45: Rorok | H45: 39548 | I45: Epson Printer | J45: Yes | L45: Ndungu
B46: Litein Tea Factory | C46: 39285 | D46: Lost Tablet | E46: 45876 | F46: NO | G46: Litein Tea Factory | H46: 39285 | I46: Lost Tablet | J46: Yes | L46: Sheila Maina
B47: Kapset Tea Factory Co. Ltd | C47: 38909 | D47: FARGO faulty card printer | E47: 45811 | F47: YES | G47: Kapset Tea Factory Co. Ltd | H47: 38909 | I47: FARGO faulty card printer | J47: Yes | K47: Insurance | L47: not assigned
B48: Region 5 - Litein | C48: 9937 | D48: Laptop not powering | E48: 42438 | F48: yes | G48: Region 5 - Litein | H48: 9937 | I48: Laptop not powering | J48: Yes | L48: Florence Barasa
B49: Chelal Tea Factory Co. Ltd | C49: 39436 | D49: Faulty Laptop (Sn. 5CD2130Y31) | E49: 20/8/2025 | F49: yes | G49: Chelal Tea Factory Co. Ltd | H49: 39436 | I49: Faulty Laptop (Sn. 5CD2130Y31) | J49: Yes | L49: Dennis
D50: Total - 8 - Lansupport | G50: Total - 13 -
A51: Region 6 | B51: Nyamache | C51: 15865 | D51: Tablet Screen broken | E51: 43650 | F51: No | G51: Nyamache | H51: 15865 | I51: Tablet Screen broken | J51: yes | K51: Insurance claim at Majani | L51: Sheila Maina
B52: Sanganyi | C52: 27491 | D52: Tablet Screen broken | E52: 44249 | F52: No | G52: Sanganyi | H52: 27491 | I52: Tablet Screen broken | J52: yes | K52: Awaiting FSA respose whether the tablet can be taken to insurer and send relevant documents for insurance | L52: Winfred Kabuuri
B53: Nyankoba | C53: 37264 | D53: Faulty Laptop | E53: 45273 | F53: Yes | G53: Nyankoba | H53: 37264 | I53: Faulty Laptop | J53: yes | K53: Awaiting documents for Insurance claim | L53: John Maroko
B54: Nyankoba | C54: 37677 | D54: Faulty tablets | E54: 45352 | F54: Yes | G54: Nyankoba | H54: 37677 | I54: Faulty tablets | J54: No | K54: Insurance claim at Majani | L54: Sheila Maina
B55: Tombe | C55: 38982 | D55: Epson DFX 9000 Printer | E55: 45750 | F55: No | G55: Tombe | H55: 38982 | I55: Epson DFX 9000 Printer | J55: No | K55: Printer dispatched on 4th August 2025 | L55: John Maroko
B56: Tombe | C56: 37870 | D56: Request for a VPN Line | E56: 45436 | F56: No | G56: Tombe | H56: 37870 | I56: Request for a VPN Line | J56: No | K56: The line is on 3G - vpn.ktdateas.com & 4G - Safaricom APN Factory to test and confirm | L56: Winfred Kabuuri
B57: Rianyamwamu | C57: 39216 | D57: SAMSUNG TAB S9 DAMAGED | E57: 45820 | F57: No | G57: Rianyamwamu | H57: 39216 | I57: SAMSUNG TAB S9 DAMAGED | J57: No | K57: Awaiting documents for Insurance claim | L57: Sheila Maina
D58: Total - 2 - Lansupport | G58: Total - 3-
A59: Region 7 | B59: Chebut Tea Factory Co. Ltd | C59: 36070 | D59: Laptop Lenovo-Not Powering | E59: 45065 | F59: Yes | G59: Chebut Tea Factory Co. Ltd | H59: 36070 | I59: Laptop Lenovo-Not Powering | J59: Yes | K59: procurement of motherboard ongoing | L59: Eric Ngetich
B60: Mudete Tea Factory Co. Ltd | C60: 37748 | D60: VPN line not working | E60: 45369 | F60: No | G60: Mudete Tea Factory Co. Ltd | H60: 37748 | I60: VPN line not working | J60: Yes | K60: line not connecting to vpn.mudete.com | L60: Eric Ngetich
B61: Mudete Tea Factory Co. Ltd | C61: 29144 | D61: Tablet(broken Screen) | E61: 44450 | F61: No | G61: Mudete Tea Factory Co. Ltd | H61: 29144 | I61: Tablet(broken Screen) | J61: Yes | K61: Awaiting the FSA to advise if the tablet should be taken to insurance or have screen replaced | L61: Winfred Kabuuri
B62: Kapsara Tea Factory Co. Ltd | C62: 16108 | D62: faulty directors tablet | E62: 43705 | F62: No | G62: Kapsara Tea Factory Co. Ltd | H62: 16108 | I62: faulty directors tablet | J62: Yes | K62: awaiting the tablet to be sent to the factory | L62: Winfred Kabuuri
D63: Total - 1 - Lansupport | G63: Total - 4 -
